Workbook

Sheet Exec_Summary
B1: Meridian Technology Services — FP&A Performance Pack
B2: Illustrative company · USD · fiscal year April–March · all figures formula-driven from the Data sheet · change the fiscal year in C4
B4: Fiscal year ▸ | C4: FY26 | E4: Prior year | F4: =IF(C4="FY24","n/a",IF(C4="FY25","FY24","FY25")) -> FY25 | H4: Model status | I4: =Checks!C4 -> ALL CHECKS PASS
B5: RAG: on track if variance ≥ | C5: -0.02 | E5: watch if ≥ | F5: -0.05
B6: Margin RAG (pp): on track ≥ | C6: -0.005 | E6: watch if ≥ | F6: -0.015
B8: 1 · HEADLINE SCORECARD (selected fiscal year)
B9: Metric | C9: Actual | D9: Budget | E9: Variance | F9: Var % | G9: Prior year | H9: YoY % | I9: Status
B10: Revenue | C10: =SUMIFS(Data!$G$6:$G$1085,Data!$A$6:$A$1085,$C$4) -> 171736155 | D10: =SUMIFS(Data!$F$6:$F$1085,Data!$A$6:$A$1085,$C$4) -> 175860622 | E10: =C10-D10 -> -4124467 | F10: =IF(D10=0,0,E10/D10) -> -0.023453045 | G10: =IF($F$4="n/a","n/a",SUMIFS(Data!$G$6:$G$1085,Data!$A$6:$A$1085,$F$4)) -> 159976070 | H10: =IF($F$4="n/a","n/a",C10/G10-1) -> 0.073511526 | I10: =IF(F10>=$C$5,"● On track",IF(F10>=$F$5,"● Watch","● Off track")) -> ● Watch
B11: Gross profit | C11: =SUMIFS(Data!$O$6:$O$1085,Data!$A$6:$A$1085,$C$4) -> 66137743 | D11: =SUMIFS(Data!$P$6:$P$1085,Data!$A$6:$A$1085,$C$4) -> 69774543 | E11: =C11-D11 -> -3636800 | F11: =IF(D11=0,0,E11/D11) -> -0.052122162 | G11: =IF($F$4="n/a","n/a",SUMIFS(Data!$O$6:$O$1085,Data!$A$6:$A$1085,$F$4)) -> 62699579 | H11: =IF($F$4="n/a","n/a",C11/G11-1) -> 0.05483552 | I11: =IF(F11>=$C$5,"● On track",IF(F11>=$F$5,"● Watch","● Off track")) -> ● Off track
B12: Operating income | C12: =SUMIFS(Data!$R$6:$R$1085,Data!$A$6:$A$1085,$C$4) -> 39558377 | D12: =SUMIFS(Data!$Q$6:$Q$1085,Data!$A$6:$A$1085,$C$4) -> 43196410 | E12: =C12-D12 -> -3638033 | F12: =IF(D12=0,0,E12/D12) -> -0.084220726 | G12: =IF($F$4="n/a","n/a",SUMIFS(Data!$R$6:$R$1085,Data!$A$6:$A$1085,$F$4)) -> 38416409 | H12: =IF($F$4="n/a","n/a",C12/G12-1) -> 0.029726048 | I12: =IF(F12>=$C$5,"● On track",IF(F12>=$F$5,"● Watch","● Off track")) -> ● Off track
B13: Gross margin % | C13: =C11/C10 -> 0.38511252 | D13: =D11/D10 -> 0.39676047 | E13: =(C13-D13)*100 -> -1.1647952 | F13: =C13-D13 -> -0.011647952 | G13: =IF($F$4="n/a","n/a",G11/G10) -> 0.39193099 | H13: =IF($F$4="n/a","n/a",(C13-G13)*100) -> -0.68184694 | I13: =IF(F13>=$C$6,"● On track",IF(F13>=$F$6,"● Watch","● Off track")) -> ● Watch
B14: Operating margin % | C14: =C12/C10 -> 0.23034391 | D14: =D12/D10 -> 0.24562867 | E14: =(C14-D14)*100 -> -1.5284759 | F14: =C14-D14 -> -0.015284759 | G14: =IF($F$4="n/a","n/a",G12/G10) -> 0.24013847 | H14: =IF($F$4="n/a","n/a",(C14-G14)*100) -> -0.97945645 | I14: =IF(F14>=$C$6,"● On track",IF(F14>=$F$6,"● Watch","● Off track")) -> ● Off track
B15: Revenue per head ($K, avg HC) | C15: =C10/(SUMIFS(Data!$L$6:$L$1085,Data!$A$6:$A$1085,$C$4)/12)/1000 -> 196.18394 | D15: n/a | G15: =IF($F$4="n/a","n/a",G10/(SUMIFS(Data!$L$6:$L$1085,Data!$A$6:$A$1085,$F$4)/12)/1000) -> 193.64632 | H15: =IF($F$4="n/a","n/a",C15/G15-1) -> 0.013104403
B16: Revenue forecast accuracy (1 − WAPE) | C16: =1-Heatmap!C44 -> 0.95343178
B17: Adverse cell-months (OI >15% below budget) | C17: =COUNTIFS(Data!$U$6:$U$1085,"ADVERSE",Data!$A$6:$A$1085,$C$4) -> 104 | D17: =COUNTIFS(Data!$A$6:$A$1085,$C$4) -> 360 | E17: =C17/D17 -> 0.28888889 | F17: of cell-months
B19: 2 · BUSINESS-UNIT PERFORMANCE
B20: Segment | C20: Revenue | D20: Budget | E20: Var % | F20: Gross margin | G20: Op margin | H20: Op income | I20: OI vs budget | J20: Status
B21: Banking & Financial Services | C21: =SUMIFS(Data!$G$6:$G$1085,Data!$A$6:$A$1085,$C$4,Data!$D$6:$D$1085,$B21) -> 51801767 | D21: =SUMIFS(Data!$F$6:$F$1085,Data!$A$6:$A$1085,$C$4,Data!$D$6:$D$1085,$B21) -> 52900847 | E21: =C21/D21-1 -> -0.020776227 | F21: =(SUMIFS(Data!$O$6:$O$1085,Data!$A$6:$A$1085,$C$4,Data!$D$6:$D$1085,$B21))/C21 -> 0.41552693 | G21: =H21/C21 -> 0.24967905 | H21: =SUMIFS(Data!$R$6:$R$1085,Data!$A$6:$A$1085,$C$4,Data!$D$6:$D$1085,$B21) -> 12933816 | I21: =H21/(SUMIFS(Data!$Q$6:$Q$1085,Data!$A$6:$A$1085,$C$4,Data!$D$6:$D$1085,$B21))-1 -> -0.066825993 | J21: =IF(I21>=$C$5,"● On track",IF(I21>=$F$5,"● Watch","● Off track")) -> ● Off track
B22: Retail & Consumer | C22: =SUMIFS(Data!$G$6:$G$1085,Data!$A$6:$A$1085,$C$4,Data!$D$6:$D$1085,$B22) -> 36864343 | D22: =SUMIFS(Data!$F$6:$F$1085,Data!$A$6:$A$1085,$C$4,Data!$D$6:$D$1085,$B22) -> 39576220 | E22: =C22/D22-1 -> -0.068522891 | F22: =(SUMIFS(Data!$O$6:$O$1085,Data!$A$6:$A$1085,$C$4,Data!$D$6:$D$1085,$B22))/C22 -> 0.36853504 | G22: =H22/C22 -> 0.2115997 | H22: =SUMIFS(Data!$R$6:$R$1085,Data!$A$6:$A$1085,$C$4,Data!$D$6:$D$1085,$B22) -> 7800484 | I22: =H22/(SUMIFS(Data!$Q$6:$Q$1085,Data!$A$6:$A$1085,$C$4,Data!$D$6:$D$1085,$B22))-1 -> -0.13171665 | J22: =IF(I22>=$C$5,"● On track",IF(I22>=$F$5,"● Watch","● Off track")) -> ● Off track
B23: Healthcare & Life Sciences | C23: =SUMIFS(Data!$G$6:$G$1085,Data!$A$6:$A$1085,$C$4,Data!$D$6:$D$1085,$B23) -> 30512053 | D23: =SUMIFS(Data!$F$6:$F$1085,Data!$A$6:$A$1085,$C$4,Data!$D$6:$D$1085,$B23) -> 28479528 | E23: =C23/D23-1 -> 0.071367931 | F23: =(SUMIFS(Data!$O$6:$O$1085,Data!$A$6:$A$1085,$C$4,Data!$D$6:$D$1085,$B23))/C23 -> 0.44620134 | G23: =H23/C23 -> 0.28726887 | H23: =SUMIFS(Data!$R$6:$R$1085,Data!$A$6:$A$1085,$C$4,Data!$D$6:$D$1085,$B23) -> 8765163 | I23: =H23/(SUMIFS(Data!$Q$6:$Q$1085,Data!$A$6:$A$1085,$C$4,Data!$D$6:$D$1085,$B23))-1 -> 0.036264688 | J23: =IF(I23>=$C$5,"● On track",IF(I23>=$F$5,"● Watch","● Off track")) -> ● On track
B24: Manufacturing & Logistics | C24: =SUMIFS(Data!$G$6:$G$1085,Data!$A$6:$A$1085,$C$4,Data!$D$6:$D$1085,$B24) -> 32005589 | D24: =SUMIFS(Data!$F$6:$F$1085,Data!$A$6:$A$1085,$C$4,Data!$D$6:$D$1085,$B24) -> 34095118 | E24: =C24/D24-1 -> -0.061285284 | F24: =(SUMIFS(Data!$O$6:$O$1085,Data!$A$6:$A$1085,$C$4,Data!$D$6:$D$1085,$B24))/C24 -> 0.29251422 | G24: =H24/C24 -> 0.15621375 | H24: =SUMIFS(Data!$R$6:$R$1085,Data!$A$6:$A$1085,$C$4,Data!$D$6:$D$1085,$B24) -> 4999713 | I24: =H24/(SUMIFS(Data!$Q$6:$Q$1085,Data!$A$6:$A$1085,$C$4,Data!$D$6:$D$1085,$B24))-1 -> -0.23624988 | J24: =IF(I24>=$C$5,"● On track",IF(I24>=$F$5,"● Watch","● Off track")) -> ● Off track
B25: Public Sector & Utilities | C25: =SUMIFS(Data!$G$6:$G$1085,Data!$A$6:$A$1085,$C$4,Data!$D$6:$D$1085,$B25) -> 20552403 | D25: =SUMIFS(Data!$F$6:$F$1085,Data!$A$6:$A$1085,$C$4,Data!$D$6:$D$1085,$B25) -> 20808909 | E25: =C25/D25-1 -> -0.012326739 | F25: =(SUMIFS(Data!$O$6:$O$1085,Data!$A$6:$A$1085,$C$4,Data!$D$6:$D$1085,$B25))/C25 -> 0.39169644 | G25: =H25/C25 -> 0.24616105 | H25: =SUMIFS(Data!$R$6:$R$1085,Data!$A$6:$A$1085,$C$4,Data!$D$6:$D$1085,$B25) -> 5059201 | I25: =H25/(SUMIFS(Data!$Q$6:$Q$1085,Data!$A$6:$A$1085,$C$4,Data!$D$6:$D$1085,$B25))-1 -> -0.053982735 | J25: =IF(I25>=$C$5,"● On track",IF(I25>=$F$5,"● Watch","● Off track")) -> ● Off track
B26: Total | C26: =SUM(C21:C25) -> 171736155 | D26: =SUM(D21:D25) -> 175860622 | E26: =C26/D26-1 -> -0.023453045 | F26: =C11/C10 -> 0.38511252 | G26: =H26/C26 -> 0.23034391 | H26: =SUM(H21:H25) -> 39558377 | I26: =F12 -> -0.084220726 | J26: =IF(I26>=$C$5,"● On track",IF(I26>=$F$5,"● Watch","● Off track")) -> ● Off track
B28: 3 · REGIONAL PERFORMANCE
B29: Segment | C29: Revenue | D29: Budget | E29: Var % | F29: Gross margin | G29: Op margin | H29: Op income | I29: OI vs budget | J29: Status
B30: UAE | C30: =SUMIFS(Data!$G$6:$G$1085,Data!$A$6:$A$1085,$C$4,Data!$E$6:$E$1085,$B30) -> 41463881 | D30: =SUMIFS(Data!$F$6:$F$1085,Data!$A$6:$A$1085,$C$4,Data!$E$6:$E$1085,$B30) -> 42272767 | E30: =C30/D30-1 -> -0.01913492 | F30: =(SUMIFS(Data!$O$6:$O$1085,Data!$A$6:$A$1085,$C$4,Data!$E$6:$E$1085,$B30))/C30 -> 0.39363488 | G30: =H30/C30 -> 0.23956619 | H30: =SUMIFS(Data!$R$6:$R$1085,Data!$A$6:$A$1085,$C$4,Data!$E$6:$E$1085,$B30) -> 9933344 | I30: =H30/(SUMIFS(Data!$Q$6:$Q$1085,Data!$A$6:$A$1085,$C$4,Data!$E$6:$E$1085,$B30))-1 -> -0.042991075 | J30: =IF(I30>=$C$5,"● On track",IF(I30>=$F$5,"● Watch","● Off track")) -> ● Watch
B31: KSA | C31: =SUMIFS(Data!$G$6:$G$1085,Data!$A$6:$A$1085,$C$4,Data!$E$6:$E$1085,$B31) -> 29043865 | D31: =SUMIFS(Data!$F$6:$F$1085,Data!$A$6:$A$1085,$C$4,Data!$E$6:$E$1085,$B31) -> 29861097 | E31: =C31/D31-1 -> -0.027367782 | F31: =(SUMIFS(Data!$O$6:$O$1085,Data!$A$6:$A$1085,$C$4,Data!$E$6:$E$1085,$B31))/C31 -> 0.36420917 | G31: =H31/C31 -> 0.20914858 | H31: =SUMIFS(Data!$R$6:$R$1085,Data!$A$6:$A$1085,$C$4,Data!$E$6:$E$1085,$B31) -> 6074483 | I31: =H31/(SUMIFS(Data!$Q$6:$Q$1085,Data!$A$6:$A$1085,$C$4,Data!$E$6:$E$1085,$B31))-1 -> -0.17174314 | J31: =IF(I31>=$C$5,"● On track",IF(I31>=$F$5,"● Watch","● Off track")) -> ● Off track
B32: India | C32: =SUMIFS(Data!$G$6:$G$1085,Data!$A$6:$A$1085,$C$4,Data!$E$6:$E$1085,$B32) -> 34487273 | D32: =SUMIFS(Data!$F$6:$F$1085,Data!$A$6:$A$1085,$C$4,Data!$E$6:$E$1085,$B32) -> 35152935 | E32: =C32/D32-1 -> -0.018936171 | F32: =(SUMIFS(Data!$O$6:$O$1085,Data!$A$6:$A$1085,$C$4,Data!$E$6:$E$1085,$B32))/C32 -> 0.3757342 | G32: =H32/C32 -> 0.22103716 | H32: =SUMIFS(Data!$R$6:$R$1085,Data!$A$6:$A$1085,$C$4,Data!$E$6:$E$1085,$B32) -> 7622969 | I32: =H32/(SUMIFS(Data!$Q$6:$Q$1085,Data!$A$6:$A$1085,$C$4,Data!$E$6:$E$1085,$B32))-1 -> -0.11726299 | J32: =IF(I32>=$C$5,"● On track",IF(I32>=$F$5,"● Watch","● Off track")) -> ● Off track
B33: UK | C33: =SUMIFS(Data!$G$6:$G$1085,Data!$A$6:$A$1085,$C$4,Data!$E$6:$E$1085,$B33) -> 25380235 | D33: =SUMIFS(Data!$F$6:$F$1085,Data!$A$6:$A$1085,$C$4,Data!$E$6:$E$1085,$B33) -> 26339370 | E33: =C33/D33-1 -> -0.0364145 | F33: =(SUMIFS(Data!$O$6:$O$1085,Data!$A$6:$A$1085,$C$4,Data!$E$6:$E$1085,$B33))/C33 -> 0.39494788 | G33: =H33/C33 -> 0.23992898 | H33: =SUMIFS(Data!$R$6:$R$1085,Data!$A$6:$A$1085,$C$4,Data!$E$6:$E$1085,$B33) -> 6089454 | I33: =H33/(SUMIFS(Data!$Q$6:$Q$1085,Data!$A$6:$A$1085,$C$4,Data!$E$6:$E$1085,$B33))-1 -> -0.059130673 | J33: =IF(I33>=$C$5,"● On track",IF(I33>=$F$5,"● Watch","● Off track")) -> ● Off track
B34: USA | C34: =SUMIFS(Data!$G$6:$G$1085,Data!$A$6:$A$1085,$C$4,Data!$E$6:$E$1085,$B34) -> 27640311 | D34: =SUMIFS(Data!$F$6:$F$1085,Data!$A$6:$A$1085,$C$4,Data!$E$6:$E$1085,$B34) -> 28154851 | E34: =C34/D34-1 -> -0.018275359 | F34: =(SUMIFS(Data!$O$6:$O$1085,Data!$A$6:$A$1085,$C$4,Data!$E$6:$E$1085,$B34))/C34 -> 0.39275278 | G34: =H34/C34 -> 0.23737551 | H34: =SUMIFS(Data!$R$6:$R$1085,Data!$A$6:$A$1085,$C$4,Data!$E$6:$E$1085,$B34) -> 6561133 | I34: =H34/(SUMIFS(Data!$Q$6:$Q$1085,Data!$A$6:$A$1085,$C$4,Data!$E$6:$E$1085,$B34))-1 -> -0.051168748 | J34: =IF(I34>=$C$5,"● On track",IF(I34>=$F$5,"● Watch","● Off track")) -> ● Off track
B35: Singapore | C35: =SUMIFS(Data!$G$6:$G$1085,Data!$A$6:$A$1085,$C$4,Data!$E$6:$E$1085,$B35) -> 13720590 | D35: =SUMIFS(Data!$F$6:$F$1085,Data!$A$6:$A$1085,$C$4,Data!$E$6:$E$1085,$B35) -> 14079602 | E35: =C35/D35-1 -> -0.025498732 | F35: =(SUMIFS(Data!$O$6:$O$1085,Data!$A$6:$A$1085,$C$4,Data!$E$6:$E$1085,$B35))/C35 -> 0.39359415 | G35: =H35/C35 -> 0.23883769 | H35: =SUMIFS(Data!$R$6:$R$1085,Data!$A$6:$A$1085,$C$4,Data!$E$6:$E$1085,$B35) -> 3276994 | I35: =H35/(SUMIFS(Data!$Q$6:$Q$1085,Data!$A$6:$A$1085,$C$4,Data!$E$6:$E$1085,$B35))-1 -> -0.052906689 | J35: =IF(I35>=$C$5,"● On track",IF(I35>=$F$5,"● Watch","● Off track")) -> ● Off track
B36: Total | C36: =SUM(C30:C35) -> 171736155 | D36: =SUM(D30:D35) -> 175860622 | E36: =C36/D36-1 -> -0.023453045 | F36: =C11/C10 -> 0.38511252 | G36: =H36/C36 -> 0.23034391 | H36: =SUM(H30:H35) -> 39558377 | I36: =F12 -> -0.084220726 | J36: =IF(I36>=$C$5,"● On track",IF(I36>=$F$5,"● Watch","● Off track")) -> ● Off track
B38: 4 · KEY MESSAGES (auto-generated from the numbers above)
B39: ="Revenue of "&TEXT(C10/1000000,"$0.0")&"M"&" is "&TEXT(ABS(F10),"0.0%")&IF(F10>=0," ahead of"," behind")&" budget and "&IF($F$4="n/a","first year of data",TEXT(ABS(H10),"0.0%")&IF(H10>=0," up"," down")&" on "&$F$4)&"; operating margin is "&TEXT(C14,"0.0%")&" ("&TEXT(E14,"+0.0;-0.0")&" pp vs budget)." -> Revenue of $171.7M is 2.3% behind budget and 7.4% up on FY25; operating margin is 23.0% (-1.5 pp vs budget).
B40: ="Operating income of "&TEXT(C12/1000000,"$0.0")&"M"&" is "&TEXT(ABS(E12)/1000000,"$0.0")&"M"&IF(E12>=0," above"," below")&" budget ("&TEXT(F12,"+0.0%;-0.0%")&"), status: "&MID(I12,3,20)&"." -> Operating income of $39.6M is $3.6M below budget (-8.4%), status: Off track.
B41: ="Strongest unit vs budget: "&INDEX(B21:B25,MATCH(MAX(I21:I25),I21:I25,0))&" ("&TEXT(MAX(I21:I25),"+0.0%;-0.0%")&" OI vs budget). Weakest: "&INDEX(B21:B25,MATCH(MIN(I21:I25),I21:I25,0))&" ("&TEXT(MIN(I21:I25),"+0.0%;-0.0%")&")." -> Strongest unit vs budget: Healthcare & Life Sciences (+3.6% OI vs budget). Weakest: Manufacturing & Logistics (-23.6%).
B42: ="Regional watch-point: "&INDEX(B30:B35,MATCH(MIN(I30:I35),I30:I35,0))&" is the weakest region ("&TEXT(MIN(I30:I35),"+0.0%;-0.0%")&" OI vs budget); strongest is "&INDEX(B30:B35,MATCH(MAX(I30:I35),I30:I35,0))&"." -> Regional watch-point: KSA is the weakest region (-17.2% OI vs budget); strongest is UAE.
B43: ="Budget quality: weighted absolute revenue error across 30 BU-region cells is "&TEXT(Heatmap!C44,"0.0%")&"; "&C17&" of "&D17&" cell-months ("&TEXT(E17,"0%")&") breached the 15% adverse-OI trigger." -> Budget quality: weighted absolute revenue error across 30 BU-region cells is 4.7%; 104 of 360 cell-months (29%) breached the 15% adverse-OI trigger.
B44: ="Margin driver (see Bridge): volume "&TEXT(Bridge!C7/1000000,"+$0.0;-$0.0")&"M, direct-cost rate "&TEXT(Bridge!C8/1000000,"+$0.0;-$0.0")&"M, opex rate "&TEXT(Bridge!C9/1000000,"+$0.0;-$0.0")&"M vs budget." -> Margin driver (see Bridge): volume -$0.8M, direct-cost rate -$2.3M, opex rate -$0.6M vs budget.

Sheet Heatmap
B1: BU × Region heatmap
B2: Selected fiscal year from Exec_Summary!C4 · colour scale shows where margin and budget accuracy are strongest / weakest
B3: Operating margin % (OI actual ÷ revenue actual)
B4: Business unit | C4: UAE | D4: KSA | E4: India | F4: UK | G4: USA | H4: Singapore | I4: All
B5: Banking & Financial Services | C5: =(SUMIFS(Data!$R$6:$R$1085,Data!$A$6:$A$1085,Exec_Summary!$C$4,Data!$D$6:$D$1085,$B5,Data!$E$6:$E$1085,C$4))/(SUMIFS(Data!$G$6:$G$1085,Data!$A$6:$A$1085,Exec_Summary!$C$4,Data!$D$6:$D$1085,$B5,Data!$E$6:$E$1085,C$4)) -> 0.25944141 | D5: =(SUMIFS(Data!$R$6:$R$1085,Data!$A$6:$A$1085,Exec_Summary!$C$4,Data!$D$6:$D$1085,$B5,Data!$E$6:$E$1085,D$4))/(SUMIFS(Data!$G$6:$G$1085,Data!$A$6:$A$1085,Exec_Summary!$C$4,Data!$D$6:$D$1085,$B5,Data!$E$6:$E$1085,D$4)) -> 0.23062416 | E5: =(SUMIFS(Data!$R$6:$R$1085,Data!$A$6:$A$1085,Exec_Summary!$C$4,Data!$D$6:$D$1085,$B5,Data!$E$6:$E$1085,E$4))/(SUMIFS(Data!$G$6:$G$1085,Data!$A$6:$A$1085,Exec_Summary!$C$4,Data!$D$6:$D$1085,$B5,Data!$E$6:$E$1085,E$4)) -> 0.2415455 | F5: =(SUMIFS(Data!$R$6:$R$1085,Data!$A$6:$A$1085,Exec_Summary!$C$4,Data!$D$6:$D$1085,$B5,Data!$E$6:$E$1085,F$4))/(SUMIFS(Data!$G$6:$G$1085,Data!$A$6:$A$1085,Exec_Summary!$C$4,Data!$D$6:$D$1085,$B5,Data!$E$6:$E$1085,F$4)) -> 0.25799616 | G5: =(SUMIFS(Data!$R$6:$R$1085,Data!$A$6:$A$1085,Exec_Summary!$C$4,Data!$D$6:$D$1085,$B5,Data!$E$6:$E$1085,G$4))/(SUMIFS(Data!$G$6:$G$1085,Data!$A$6:$A$1085,Exec_Summary!$C$4,Data!$D$6:$D$1085,$B5,Data!$E$6:$E$1085,G$4)) -> 0.25357482 | H5: =(SUMIFS(Data!$R$6:$R$1085,Data!$A$6:$A$1085,Exec_Summary!$C$4,Data!$D$6:$D$1085,$B5,Data!$E$6:$E$1085,H$4))/(SUMIFS(Data!$G$6:$G$1085,Data!$A$6:$A$1085,Exec_Summary!$C$4,Data!$D$6:$D$1085,$B5,Data!$E$6:$E$1085,H$4)) -> 0.25785115 | I5: =(SUMIFS(Data!$R$6:$R$1085,Data!$A$6:$A$1085,Exec_Summary!$C$4,Data!$D$6:$D$1085,$B5))/(SUMIFS(Data!$G$6:$G$1085,Data!$A$6:$A$1085,Exec_Summary!$C$4,Data!$D$6:$D$1085,$B5)) -> 0.24967905
B6: Retail & Consumer | C6: =(SUMIFS(Data!$R$6:$R$1085,Data!$A$6:$A$1085,Exec_Summary!$C$4,Data!$D$6:$D$1085,$B6,Data!$E$6:$E$1085,C$4))/(SUMIFS(Data!$G$6:$G$1085,Data!$A$6:$A$1085,Exec_Summary!$C$4,Data!$D$6:$D$1085,$B6,Data!$E$6:$E$1085,C$4)) -> 0.22180017 | D6: =(SUMIFS(Data!$R$6:$R$1085,Data!$A$6:$A$1085,Exec_Summary!$C$4,Data!$D$6:$D$1085,$B6,Data!$E$6:$E$1085,D$4))/(SUMIFS(Data!$G$6:$G$1085,Data!$A$6:$A$1085,Exec_Summary!$C$4,Data!$D$6:$D$1085,$B6,Data!$E$6:$E$1085,D$4)) -> 0.19120901 | E6: =(SUMIFS(Data!$R$6:$R$1085,Data!$A$6:$A$1085,Exec_Summary!$C$4,Data!$D$6:$D$1085,$B6,Data!$E$6:$E$1085,E$4))/(SUMIFS(Data!$G$6:$G$1085,Data!$A$6:$A$1085,Exec_Summary!$C$4,Data!$D$6:$D$1085,$B6,Data!$E$6:$E$1085,E$4)) -> 0.19993505 | F6: =(SUMIFS(Data!$R$6:$R$1085,Data!$A$6:$A$1085,Exec_Summary!$C$4,Data!$D$6:$D$1085,$B6,Data!$E$6:$E$1085,F$4))/(SUMIFS(Data!$G$6:$G$1085,Data!$A$6:$A$1085,Exec_Summary!$C$4,Data!$D$6:$D$1085,$B6,Data!$E$6:$E$1085,F$4)) -> 0.22257796 | G6: =(SUMIFS(Data!$R$6:$R$1085,Data!$A$6:$A$1085,Exec_Summary!$C$4,Data!$D$6:$D$1085,$B6,Data!$E$6:$E$1085,G$4))/(SUMIFS(Data!$G$6:$G$1085,Data!$A$6:$A$1085,Exec_Summary!$C$4,Data!$D$6:$D$1085,$B6,Data!$E$6:$E$1085,G$4)) -> 0.21840613 | H6: =(SUMIFS(Data!$R$6:$R$1085,Data!$A$6:$A$1085,Exec_Summary!$C$4,Data!$D$6:$D$1085,$B6,Data!$E$6:$E$1085,H$4))/(SUMIFS(Data!$G$6:$G$1085,Data!$A$6:$A$1085,Exec_Summary!$C$4,Data!$D$6:$D$1085,$B6,Data!$E$6:$E$1085,H$4)) -> 0.21960326 | I6: =(SUMIFS(Data!$R$6:$R$1085,Data!$A$6:$A$1085,Exec_Summary!$C$4,Data!$D$6:$D$1085,$B6))/(SUMIFS(Data!$G$6:$G$1085,Data!$A$6:$A$1085,Exec_Summary!$C$4,Data!$D$6:$D$1085,$B6)) -> 0.2115997
B7: Healthcare & Life Sciences | C7: =(SUMIFS(Data!$R$6:$R$1085,Data!$A$6:$A$1085,Exec_Summary!$C$4,Data!$D$6:$D$1085,$B7,Data!$E$6:$E$1085,C$4))/(SUMIFS(Data!$G$6:$G$1085,Data!$A$6:$A$1085,Exec_Summary!$C$4,Data!$D$6:$D$1085,$B7,Data!$E$6:$E$1085,C$4)) -> 0.29483354 | D7: =(SUMIFS(Data!$R$6:$R$1085,Data!$A$6:$A$1085,Exec_Summary!$C$4,Data!$D$6:$D$1085,$B7,Data!$E$6:$E$1085,D$4))/(SUMIFS(Data!$G$6:$G$1085,Data!$A$6:$A$1085,Exec_Summary!$C$4,Data!$D$6:$D$1085,$B7,Data!$E$6:$E$1085,D$4)) -> 0.26723827 | E7: =(SUMIFS(Data!$R$6:$R$1085,Data!$A$6:$A$1085,Exec_Summary!$C$4,Data!$D$6:$D$1085,$B7,Data!$E$6:$E$1085,E$4))/(SUMIFS(Data!$G$6:$G$1085,Data!$A$6:$A$1085,Exec_Summary!$C$4,Data!$D$6:$D$1085,$B7,Data!$E$6:$E$1085,E$4)) -> 0.27952147 | F7: =(SUMIFS(Data!$R$6:$R$1085,Data!$A$6:$A$1085,Exec_Summary!$C$4,Data!$D$6:$D$1085,$B7,Data!$E$6:$E$1085,F$4))/(SUMIFS(Data!$G$6:$G$1085,Data!$A$6:$A$1085,Exec_Summary!$C$4,Data!$D$6:$D$1085,$B7,Data!$E$6:$E$1085,F$4)) -> 0.29738194 | G7: =(SUMIFS(Data!$R$6:$R$1085,Data!$A$6:$A$1085,Exec_Summary!$C$4,Data!$D$6:$D$1085,$B7,Data!$E$6:$E$1085,G$4))/(SUMIFS(Data!$G$6:$G$1085,Data!$A$6:$A$1085,Exec_Summary!$C$4,Data!$D$6:$D$1085,$B7,Data!$E$6:$E$1085,G$4)) -> 0.29295189 | H7: =(SUMIFS(Data!$R$6:$R$1085,Data!$A$6:$A$1085,Exec_Summary!$C$4,Data!$D$6:$D$1085,$B7,Data!$E$6:$E$1085,H$4))/(SUMIFS(Data!$G$6:$G$1085,Data!$A$6:$A$1085,Exec_Summary!$C$4,Data!$D$6:$D$1085,$B7,Data!$E$6:$E$1085,H$4)) -> 0.29535484 | I7: =(SUMIFS(Data!$R$6:$R$1085,Data!$A$6:$A$1085,Exec_Summary!$C$4,Data!$D$6:$D$1085,$B7))/(SUMIFS(Data!$G$6:$G$1085,Data!$A$6:$A$1085,Exec_Summary!$C$4,Data!$D$6:$D$1085,$B7)) -> 0.28726887
B8: Manufacturing & Logistics | C8: =(SUMIFS(Data!$R$6:$R$1085,Data!$A$6:$A$1085,Exec_Summary!$C$4,Data!$D$6:$D$1085,$B8,Data!$E$6:$E$1085,C$4))/(SUMIFS(Data!$G$6:$G$1085,Data!$A$6:$A$1085,Exec_Summary!$C$4,Data!$D$6:$D$1085,$B8,Data!$E$6:$E$1085,C$4)) -> 0.16443561 | D8: =(SUMIFS(Data!$R$6:$R$1085,Data!$A$6:$A$1085,Exec_Summary!$C$4,Data!$D$6:$D$1085,$B8,Data!$E$6:$E$1085,D$4))/(SUMIFS(Data!$G$6:$G$1085,Data!$A$6:$A$1085,Exec_Summary!$C$4,Data!$D$6:$D$1085,$B8,Data!$E$6:$E$1085,D$4)) -> 0.1300631 | E8: =(SUMIFS(Data!$R$6:$R$1085,Data!$A$6:$A$1085,Exec_Summary!$C$4,Data!$D$6:$D$1085,$B8,Data!$E$6:$E$1085,E$4))/(SUMIFS(Data!$G$6:$G$1085,Data!$A$6:$A$1085,Exec_Summary!$C$4,Data!$D$6:$D$1085,$B8,Data!$E$6:$E$1085,E$4)) -> 0.1465819 | F8: =(SUMIFS(Data!$R$6:$R$1085,Data!$A$6:$A$1085,Exec_Summary!$C$4,Data!$D$6:$D$1085,$B8,Data!$E$6:$E$1085,F$4))/(SUMIFS(Data!$G$6:$G$1085,Data!$A$6:$A$1085,Exec_Summary!$C$4,Data!$D$6:$D$1085,$B8,Data!$E$6:$E$1085,F$4)) -> 0.16734243 | G8: =(SUMIFS(Data!$R$6:$R$1085,Data!$A$6:$A$1085,Exec_Summary!$C$4,Data!$D$6:$D$1085,$B8,Data!$E$6:$E$1085,G$4))/(SUMIFS(Data!$G$6:$G$1085,Data!$A$6:$A$1085,Exec_Summary!$C$4,Data!$D$6:$D$1085,$B8,Data!$E$6:$E$1085,G$4)) -> 0.16804613 | H8: =(SUMIFS(Data!$R$6:$R$1085,Data!$A$6:$A$1085,Exec_Summary!$C$4,Data!$D$6:$D$1085,$B8,Data!$E$6:$E$1085,H$4))/(SUMIFS(Data!$G$6:$G$1085,Data!$A$6:$A$1085,Exec_Summary!$C$4,Data!$D$6:$D$1085,$B8,Data!$E$6:$E$1085,H$4)) -> 0.16609087 | I8: =(SUMIFS(Data!$R$6:$R$1085,Data!$A$6:$A$1085,Exec_Summary!$C$4,Data!$D$6:$D$1085,$B8))/(SUMIFS(Data!$G$6:$G$1085,Data!$A$6:$A$1085,Exec_Summary!$C$4,Data!$D$6:$D$1085,$B8)) -> 0.15621375
B9: Public Sector & Utilities | C9: =(SUMIFS(Data!$R$6:$R$1085,Data!$A$6:$A$1085,Exec_Summary!$C$4,Data!$D$6:$D$1085,$B9,Data!$E$6:$E$1085,C$4))/(SUMIFS(Data!$G$6:$G$1085,Data!$A$6:$A$1085,Exec_Summary!$C$4,Data!$D$6:$D$1085,$B9,Data!$E$6:$E$1085,C$4)) -> 0.25778258 | D9: =(SUMIFS(Data!$R$6:$R$1085,Data!$A$6:$A$1085,Exec_Summary!$C$4,Data!$D$6:$D$1085,$B9,Data!$E$6:$E$1085,D$4))/(SUMIFS(Data!$G$6:$G$1085,Data!$A$6:$A$1085,Exec_Summary!$C$4,Data!$D$6:$D$1085,$B9,Data!$E$6:$E$1085,D$4)) -> 0.22350034 | E9: =(SUMIFS(Data!$R$6:$R$1085,Data!$A$6:$A$1085,Exec_Summary!$C$4,Data!$D$6:$D$1085,$B9,Data!$E$6:$E$1085,E$4))/(SUMIFS(Data!$G$6:$G$1085,Data!$A$6:$A$1085,Exec_Summary!$C$4,Data!$D$6:$D$1085,$B9,Data!$E$6:$E$1085,E$4)) -> 0.23774372 | F9: =(SUMIFS(Data!$R$6:$R$1085,Data!$A$6:$A$1085,Exec_Summary!$C$4,Data!$D$6:$D$1085,$B9,Data!$E$6:$E$1085,F$4))/(SUMIFS(Data!$G$6:$G$1085,Data!$A$6:$A$1085,Exec_Summary!$C$4,Data!$D$6:$D$1085,$B9,Data!$E$6:$E$1085,F$4)) -> 0.25116745 | G9: =(SUMIFS(Data!$R$6:$R$1085,Data!$A$6:$A$1085,Exec_Summary!$C$4,Data!$D$6:$D$1085,$B9,Data!$E$6:$E$1085,G$4))/(SUMIFS(Data!$G$6:$G$1085,Data!$A$6:$A$1085,Exec_Summary!$C$4,Data!$D$6:$D$1085,$B9,Data!$E$6:$E$1085,G$4)) -> 0.25550465 | H9: =(SUMIFS(Data!$R$6:$R$1085,Data!$A$6:$A$1085,Exec_Summary!$C$4,Data!$D$6:$D$1085,$B9,Data!$E$6:$E$1085,H$4))/(SUMIFS(Data!$G$6:$G$1085,Data!$A$6:$A$1085,Exec_Summary!$C$4,Data!$D$6:$D$1085,$B9,Data!$E$6:$E$1085,H$4)) -> 0.25265212 | I9: =(SUMIFS(Data!$R$6:$R$1085,Data!$A$6:$A$1085,Exec_Summary!$C$4,Data!$D$6:$D$1085,$B9))/(SUMIFS(Data!$G$6:$G$1085,Data!$A$6:$A$1085,Exec_Summary!$C$4,Data!$D$6:$D$1085,$B9)) -> 0.24616105
B10: All | C10: =(SUMIFS(Data!$R$6:$R$1085,Data!$A$6:$A$1085,Exec_Summary!$C$4,Data!$E$6:$E$1085,C$4))/(SUMIFS(Data!$G$6:$G$1085,Data!$A$6:$A$1085,Exec_Summary!$C$4,Data!$E$6:$E$1085,C$4)) -> 0.23956619 | D10: =(SUMIFS(Data!$R$6:$R$1085,Data!$A$6:$A$1085,Exec_Summary!$C$4,Data!$E$6:$E$1085,D$4))/(SUMIFS(Data!$G$6:$G$1085,Data!$A$6:$A$1085,Exec_Summary!$C$4,Data!$E$6:$E$1085,D$4)) -> 0.20914858 | E10: =(SUMIFS(Data!$R$6:$R$1085,Data!$A$6:$A$1085,Exec_Summary!$C$4,Data!$E$6:$E$1085,E$4))/(SUMIFS(Data!$G$6:$G$1085,Data!$A$6:$A$1085,Exec_Summary!$C$4,Data!$E$6:$E$1085,E$4)) -> 0.22103716 | F10: =(SUMIFS(Data!$R$6:$R$1085,Data!$A$6:$A$1085,Exec_Summary!$C$4,Data!$E$6:$E$1085,F$4))/(SUMIFS(Data!$G$6:$G$1085,Data!$A$6:$A$1085,Exec_Summary!$C$4,Data!$E$6:$E$1085,F$4)) -> 0.23992898 | G10: =(SUMIFS(Data!$R$6:$R$1085,Data!$A$6:$A$1085,Exec_Summary!$C$4,Data!$E$6:$E$1085,G$4))/(SUMIFS(Data!$G$6:$G$1085,Data!$A$6:$A$1085,Exec_Summary!$C$4,Data!$E$6:$E$1085,G$4)) -> 0.23737551 | H10: =(SUMIFS(Data!$R$6:$R$1085,Data!$A$6:$A$1085,Exec_Summary!$C$4,Data!$E$6:$E$1085,H$4))/(SUMIFS(Data!$G$6:$G$1085,Data!$A$6:$A$1085,Exec_Summary!$C$4,Data!$E$6:$E$1085,H$4)) -> 0.23883769 | I10: =(SUMIFS(Data!$R$6:$R$1085,Data!$A$6:$A$1085,Exec_Summary!$C$4))/(SUMIFS(Data!$G$6:$G$1085,Data!$A$6:$A$1085,Exec_Summary!$C$4)) -> 0.23034391
B11: Operating income vs budget %
B12: Business unit | C12: UAE | D12: KSA | E12: India | F12: UK | G12: USA | H12: Singapore | I12: All
B13: Banking & Financial Services | C13: =(SUMIFS(Data!$R$6:$R$1085,Data!$A$6:$A$1085,Exec_Summary!$C$4,Data!$D$6:$D$1085,$B13,Data!$E$6:$E$1085,C$12))/(SUMIFS(Data!$Q$6:$Q$1085,Data!$A$6:$A$1085,Exec_Summary!$C$4,Data!$D$6:$D$1085,$B13,Data!$E$6:$E$1085,C$12))-1 -> -0.028899783 | D13: =(SUMIFS(Data!$R$6:$R$1085,Data!$A$6:$A$1085,Exec_Summary!$C$4,Data!$D$6:$D$1085,$B13,Data!$E$6:$E$1085,D$12))/(SUMIFS(Data!$Q$6:$Q$1085,Data!$A$6:$A$1085,Exec_Summary!$C$4,Data!$D$6:$D$1085,$B13,Data!$E$6:$E$1085,D$12))-1 -> -0.13821423 | E13: =(SUMIFS(Data!$R$6:$R$1085,Data!$A$6:$A$1085,Exec_Summary!$C$4,Data!$D$6:$D$1085,$B13,Data!$E$6:$E$1085,E$12))/(SUMIFS(Data!$Q$6:$Q$1085,Data!$A$6:$A$1085,Exec_Summary!$C$4,Data!$D$6:$D$1085,$B13,Data!$E$6:$E$1085,E$12))-1 -> -0.090445882 | F13: =(SUMIFS(Data!$R$6:$R$1085,Data!$A$6:$A$1085,Exec_Summary!$C$4,Data!$D$6:$D$1085,$B13,Data!$E$6:$E$1085,F$12))/(SUMIFS(Data!$Q$6:$Q$1085,Data!$A$6:$A$1085,Exec_Summary!$C$4,Data!$D$6:$D$1085,$B13,Data!$E$6:$E$1085,F$12))-1 -> -0.034420088 | G13: =(SUMIFS(Data!$R$6:$R$1085,Data!$A$6:$A$1085,Exec_Summary!$C$4,Data!$D$6:$D$1085,$B13,Data!$E$6:$E$1085,G$12))/(SUMIFS(Data!$Q$6:$Q$1085,Data!$A$6:$A$1085,Exec_Summary!$C$4,Data!$D$6:$D$1085,$B13,Data!$E$6:$E$1085,G$12))-1 -> -0.064664551 | H13: =(SUMIFS(Data!$R$6:$R$1085,Data!$A$6:$A$1085,Exec_Summary!$C$4,Data!$D$6:$D$1085,$B13,Data!$E$6:$E$1085,H$12))/(SUMIFS(Data!$Q$6:$Q$1085,Data!$A$6:$A$1085,Exec_Summary!$C$4,Data!$D$6:$D$1085,$B13,Data!$E$6:$E$1085,H$12))-1 -> -0.03544366 | I13: =(SUMIFS(Data!$R$6:$R$1085,Data!$A$6:$A$1085,Exec_Summary!$C$4,Data!$D$6:$D$1085,$B13))/(SUMIFS(Data!$Q$6:$Q$1085,Data!$A$6:$A$1085,Exec_Summary!$C$4,Data!$D$6:$D$1085,$B13))-1 -> -0.066825993
B14: Retail & Consumer | C14: =(SUMIFS(Data!$R$6:$R$1085,Data!$A$6:$A$1085,Exec_Summary!$C$4,Data!$D$6:$D$1085,$B14,Data!$E$6:$E$1085,C$12))/(SUMIFS(Data!$Q$6:$Q$1085,Data!$A$6:$A$1085,Exec_Summary!$C$4,Data!$D$6:$D$1085,$B14,Data!$E$6:$E$1085,C$12))-1 -> -0.069266416 | D14: =(SUMIFS(Data!$R$6:$R$1085,Data!$A$6:$A$1085,Exec_Summary!$C$4,Data!$D$6:$D$1085,$B14,Data!$E$6:$E$1085,D$12))/(SUMIFS(Data!$Q$6:$Q$1085,Data!$A$6:$A$1085,Exec_Summary!$C$4,Data!$D$6:$D$1085,$B14,Data!$E$6:$E$1085,D$12))-1 -> -0.21684677 | E14: =(SUMIFS(Data!$R$6:$R$1085,Data!$A$6:$A$1085,Exec_Summary!$C$4,Data!$D$6:$D$1085,$B14,Data!$E$6:$E$1085,E$12))/(SUMIFS(Data!$Q$6:$Q$1085,Data!$A$6:$A$1085,Exec_Summary!$C$4,Data!$D$6:$D$1085,$B14,Data!$E$6:$E$1085,E$12))-1 -> -0.17408751 | F14: =(SUMIFS(Data!$R$6:$R$1085,Data!$A$6:$A$1085,Exec_Summary!$C$4,Data!$D$6:$D$1085,$B14,Data!$E$6:$E$1085,F$12))/(SUMIFS(Data!$Q$6:$Q$1085,Data!$A$6:$A$1085,Exec_Summary!$C$4,Data!$D$6:$D$1085,$B14,Data!$E$6:$E$1085,F$12))-1 -> -0.14324926 | G14: =(SUMIFS(Data!$R$6:$R$1085,Data!$A$6:$A$1085,Exec_Summary!$C$4,Data!$D$6:$D$1085,$B14,Data!$E$6:$E$1085,G$12))/(SUMIFS(Data!$Q$6:$Q$1085,Data!$A$6:$A$1085,Exec_Summary!$C$4,Data!$D$6:$D$1085,$B14,Data!$E$6:$E$1085,G$12))-1 -> -0.092949394 | H14: =(SUMIFS(Data!$R$6:$R$1085,Data!$A$6:$A$1085,Exec_Summary!$C$4,Data!$D$6:$D$1085,$B14,Data!$E$6:$E$1085,H$12))/(SUMIFS(Data!$Q$6:$Q$1085,Data!$A$6:$A$1085,Exec_Summary!$C$4,Data!$D$6:$D$1085,$B14,Data!$E$6:$E$1085,H$12))-1 -> -0.088764815 | I14: =(SUMIFS(Data!$R$6:$R$1085,Data!$A$6:$A$1085,Exec_Summary!$C$4,Data!$D$6:$D$1085,$B14))/(SUMIFS(Data!$Q$6:$Q$1085,Data!$A$6:$A$1085,Exec_Summary!$C$4,Data!$D$6:$D$1085,$B14))-1 -> -0.13171665
B15: Healthcare & Life Sciences | C15: =(SUMIFS(Data!$R$6:$R$1085,Data!$A$6:$A$1085,Exec_Summary!$C$4,Data!$D$6:$D$1085,$B15,Data!$E$6:$E$1085,C$12))/(SUMIFS(Data!$Q$6:$Q$1085,Data!$A$6:$A$1085,Exec_Summary!$C$4,Data!$D$6:$D$1085,$B15,Data!$E$6:$E$1085,C$12))-1 -> 0.060407972 | D15: =(SUMIFS(Data!$R$6:$R$1085,Data!$A$6:$A$1085,Exec_Summary!$C$4,Data!$D$6:$D$1085,$B15,Data!$E$6:$E$1085,D$12))/(SUMIFS(Data!$Q$6:$Q$1085,Data!$A$6:$A$1085,Exec_Summary!$C$4,Data!$D$6:$D$1085,$B15,Data!$E$6:$E$1085,D$12))-1 -> -0.044220537 | E15: =(SUMIFS(Data!$R$6:$R$1085,Data!$A$6:$A$1085,Exec_Summary!$C$4,Data!$D$6:$D$1085,$B15,Data!$E$6:$E$1085,E$12))/(SUMIFS(Data!$Q$6:$Q$1085,Data!$A$6:$A$1085,Exec_Summary!$C$4,Data!$D$6:$D$1085,$B15,Data!$E$6:$E$1085,E$12))-1 -> -0.0036396398 | F15: =(SUMIFS(Data!$R$6:$R$1085,Data!$A$6:$A$1085,Exec_Summary!$C$4,Data!$D$6:$D$1085,$B15,Data!$E$6:$E$1085,F$12))/(SUMIFS(Data!$Q$6:$Q$1085,Data!$A$6:$A$1085,Exec_Summary!$C$4,Data!$D$6:$D$1085,$B15,Data!$E$6:$E$1085,F$12))-1 -> 0.078536692 | G15: =(SUMIFS(Data!$R$6:$R$1085,Data!$A$6:$A$1085,Exec_Summary!$C$4,Data!$D$6:$D$1085,$B15,Data!$E$6:$E$1085,G$12))/(SUMIFS(Data!$Q$6:$Q$1085,Data!$A$6:$A$1085,Exec_Summary!$C$4,Data!$D$6:$D$1085,$B15,Data!$E$6:$E$1085,G$12))-1 -> 0.089019582 | H15: =(SUMIFS(Data!$R$6:$R$1085,Data!$A$6:$A$1085,Exec_Summary!$C$4,Data!$D$6:$D$1085,$B15,Data!$E$6:$E$1085,H$12))/(SUMIFS(Data!$Q$6:$Q$1085,Data!$A$6:$A$1085,Exec_Summary!$C$4,Data!$D$6:$D$1085,$B15,Data!$E$6:$E$1085,H$12))-1 -> 0.050290343 | I15: =(SUMIFS(Data!$R$6:$R$1085,Data!$A$6:$A$1085,Exec_Summary!$C$4,Data!$D$6:$D$1085,$B15))/(SUMIFS(Data!$Q$6:$Q$1085,Data!$A$6:$A$1085,Exec_Summary!$C$4,Data!$D$6:$D$1085,$B15))-1 -> 0.036264688
B16: Manufacturing & Logistics | C16: =(SUMIFS(Data!$R$6:$R$1085,Data!$A$6:$A$1085,Exec_Summary!$C$4,Data!$D$6:$D$1085,$B16,Data!$E$6:$E$1085,C$12))/(SUMIFS(Data!$Q$6:$Q$1085,Data!$A$6:$A$1085,Exec_Summary!$C$4,Data!$D$6:$D$1085,$B16,Data!$E$6:$E$1085,C$12))-1 -> -0.19801645 | D16: =(SUMIFS(Data!$R$6:$R$1085,Data!$A$6:$A$1085,Exec_Summary!$C$4,Data!$D$6:$D$1085,$B16,Data!$E$6:$E$1085,D$12))/(SUMIFS(Data!$Q$6:$Q$1085,Data!$A$6:$A$1085,Exec_Summary!$C$4,Data!$D$6:$D$1085,$B16,Data!$E$6:$E$1085,D$12))-1 -> -0.37181748 | E16: =(SUMIFS(Data!$R$6:$R$1085,Data!$A$6:$A$1085,Exec_Summary!$C$4,Data!$D$6:$D$1085,$B16,Data!$E$6:$E$1085,E$12))/(SUMIFS(Data!$Q$6:$Q$1085,Data!$A$6:$A$1085,Exec_Summary!$C$4,Data!$D$6:$D$1085,$B16,Data!$E$6:$E$1085,E$12))-1 -> -0.27723825 | F16: =(SUMIFS(Data!$R$6:$R$1085,Data!$A$6:$A$1085,Exec_Summary!$C$4,Data!$D$6:$D$1085,$B16,Data!$E$6:$E$1085,F$12))/(SUMIFS(Data!$Q$6:$Q$1085,Data!$A$6:$A$1085,Exec_Summary!$C$4,Data!$D$6:$D$1085,$B16,Data!$E$6:$E$1085,F$12))-1 -> -0.17394694 | G16: =(SUMIFS(Data!$R$6:$R$1085,Data!$A$6:$A$1085,Exec_Summary!$C$4,Data!$D$6:$D$1085,$B16,Data!$E$6:$E$1085,G$12))/(SUMIFS(Data!$Q$6:$Q$1085,Data!$A$6:$A$1085,Exec_Summary!$C$4,Data!$D$6:$D$1085,$B16,Data!$E$6:$E$1085,G$12))-1 -> -0.17266403 | H16: =(SUMIFS(Data!$R$6:$R$1085,Data!$A$6:$A$1085,Exec_Summary!$C$4,Data!$D$6:$D$1085,$B16,Data!$E$6:$E$1085,H$12))/(SUMIFS(Data!$Q$6:$Q$1085,Data!$A$6:$A$1085,Exec_Summary!$C$4,Data!$D$6:$D$1085,$B16,Data!$E$6:$E$1085,H$12))-1 -> -0.20439708 | I16: =(SUMIFS(Data!$R$6:$R$1085,Data!$A$6:$A$1085,Exec_Summary!$C$4,Data!$D$6:$D$1085,$B16))/(SUMIFS(Data!$Q$6:$Q$1085,Data!$A$6:$A$1085,Exec_Summary!$C$4,Data!$D$6:$D$1085,$B16))-1 -> -0.23624988
B17: Public Sector & Utilities | C17: =(SUMIFS(Data!$R$6:$R$1085,Data!$A$6:$A$1085,Exec_Summary!$C$4,Data!$D$6:$D$1085,$B17,Data!$E$6:$E$1085,C$12))/(SUMIFS(Data!$Q$6:$Q$1085,Data!$A$6:$A$1085,Exec_Summary!$C$4,Data!$D$6:$D$1085,$B17,Data!$E$6:$E$1085,C$12))-1 -> -0.0074516498 | D17: =(SUMIFS(Data!$R$6:$R$1085,Data!$A$6:$A$1085,Exec_Summary!$C$4,Data!$D$6:$D$1085,$B17,Data!$E$6:$E$1085,D$12))/(SUMIFS(Data!$Q$6:$Q$1085,Data!$A$6:$A$1085,Exec_Summary!$C$4,Data!$D$6:$D$1085,$B17,Data!$E$6:$E$1085,D$12))-1 -> -0.13917704 | E17: =(SUMIFS(Data!$R$6:$R$1085,Data!$A$6:$A$1085,Exec_Summary!$C$4,Data!$D$6:$D$1085,$B17,Data!$E$6:$E$1085,E$12))/(SUMIFS(Data!$Q$6:$Q$1085,Data!$A$6:$A$1085,Exec_Summary!$C$4,Data!$D$6:$D$1085,$B17,Data!$E$6:$E$1085,E$12))-1 -> -0.075830302 | F17: =(SUMIFS(Data!$R$6:$R$1085,Data!$A$6:$A$1085,Exec_Summary!$C$4,Data!$D$6:$D$1085,$B17,Data!$E$6:$E$1085,F$12))/(SUMIFS(Data!$Q$6:$Q$1085,Data!$A$6:$A$1085,Exec_Summary!$C$4,Data!$D$6:$D$1085,$B17,Data!$E$6:$E$1085,F$12))-1 -> -0.060355976 | G17: =(SUMIFS(Data!$R$6:$R$1085,Data!$A$6:$A$1085,Exec_Summary!$C$4,Data!$D$6:$D$1085,$B17,Data!$E$6:$E$1085,G$12))/(SUMIFS(Data!$Q$6:$Q$1085,Data!$A$6:$A$1085,Exec_Summary!$C$4,Data!$D$6:$D$1085,$B17,Data!$E$6:$E$1085,G$12))-1 -> -0.018257971 | H17: =(SUMIFS(Data!$R$6:$R$1085,Data!$A$6:$A$1085,Exec_Summary!$C$4,Data!$D$6:$D$1085,$B17,Data!$E$6:$E$1085,H$12))/(SUMIFS(Data!$Q$6:$Q$1085,Data!$A$6:$A$1085,Exec_Summary!$C$4,Data!$D$6:$D$1085,$B17,Data!$E$6:$E$1085,H$12))-1 -> -0.017896274 | I17: =(SUMIFS(Data!$R$6:$R$1085,Data!$A$6:$A$1085,Exec_Summary!$C$4,Data!$D$6:$D$1085,$B17))/(SUMIFS(Data!$Q$6:$Q$1085,Data!$A$6:$A$1085,Exec_Summary!$C$4,Data!$D$6:$D$1085,$B17))-1 -> -0.053982735
B18: All | C18: =(SUMIFS(Data!$R$6:$R$1085,Data!$A$6:$A$1085,Exec_Summary!$C$4,Data!$E$6:$E$1085,C$12))/(SUMIFS(Data!$Q$6:$Q$1085,Data!$A$6:$A$1085,Exec_Summary!$C$4,Data!$E$6:$E$1085,C$12))-1 -> -0.042991075 | D18: =(SUMIFS(Data!$R$6:$R$1085,Data!$A$6:$A$1085,Exec_Summary!$C$4,Data!$E$6:$E$1085,D$12))/(SUMIFS(Data!$Q$6:$Q$1085,Data!$A$6:$A$1085,Exec_Summary!$C$4,Data!$E$6:$E$1085,D$12))-1 -> -0.17174314 | E18: =(SUMIFS(Data!$R$6:$R$1085,Data!$A$6:$A$1085,Exec_Summary!$C$4,Data!$E$6:$E$1085,E$12))/(SUMIFS(Data!$Q$6:$Q$1085,Data!$A$6:$A$1085,Exec_Summary!$C$4,Data!$E$6:$E$1085,E$12))-1 -> -0.11726299 | F18: =(SUMIFS(Data!$R$6:$R$1085,Data!$A$6:$A$1085,Exec_Summary!$C$4,Data!$E$6:$E$1085,F$12))/(SUMIFS(Data!$Q$6:$Q$1085,Data!$A$6:$A$1085,Exec_Summary!$C$4,Data!$E$6:$E$1085,F$12))-1 -> -0.059130673 | G18: =(SUMIFS(Data!$R$6:$R$1085,Data!$A$6:$A$1085,Exec_Summary!$C$4,Data!$E$6:$E$1085,G$12))/(SUMIFS(Data!$Q$6:$Q$1085,Data!$A$6:$A$1085,Exec_Summary!$C$4,Data!$E$6:$E$1085,G$12))-1 -> -0.051168748 | H18: =(SUMIFS(Data!$R$6:$R$1085,Data!$A$6:$A$1085,Exec_Summary!$C$4,Data!$E$6:$E$1085,H$12))/(SUMIFS(Data!$Q$6:$Q$1085,Data!$A$6:$A$1085,Exec_Summary!$C$4,Data!$E$6:$E$1085,H$12))-1 -> -0.052906689 | I18: =(SUMIFS(Data!$R$6:$R$1085,Data!$A$6:$A$1085,Exec_Summary!$C$4))/(SUMIFS(Data!$Q$6:$Q$1085,Data!$A$6:$A$1085,Exec_Summary!$C$4))-1 -> -0.084220726
B19: Revenue actual ($)
B20: Business unit | C20: UAE | D20: KSA | E20: India | F20: UK | G20: USA | H20: Singapore | I20: All
B21: Banking & Financial Services | C21: =SUMIFS(Data!$G$6:$G$1085,Data!$A$6:$A$1085,Exec_Summary!$C$4,Data!$D$6:$D$1085,$B21,Data!$E$6:$E$1085,C$20) -> 12476470 | D21: =SUMIFS(Data!$G$6:$G$1085,Data!$A$6:$A$1085,Exec_Summary!$C$4,Data!$D$6:$D$1085,$B21,Data!$E$6:$E$1085,D$20) -> 8785875 | E21: =SUMIFS(Data!$G$6:$G$1085,Data!$A$6:$A$1085,Exec_Summary!$C$4,Data!$D$6:$D$1085,$B21,Data!$E$6:$E$1085,E$20) -> 10426934 | F21: =SUMIFS(Data!$G$6:$G$1085,Data!$A$6:$A$1085,Exec_Summary!$C$4,Data!$D$6:$D$1085,$B21,Data!$E$6:$E$1085,F$20) -> 7757259 | G21: =SUMIFS(Data!$G$6:$G$1085,Data!$A$6:$A$1085,Exec_Summary!$C$4,Data!$D$6:$D$1085,$B21,Data!$E$6:$E$1085,G$20) -> 8199564 | H21: =SUMIFS(Data!$G$6:$G$1085,Data!$A$6:$A$1085,Exec_Summary!$C$4,Data!$D$6:$D$1085,$B21,Data!$E$6:$E$1085,H$20) -> 4155665 | I21: =SUMIFS(Data!$G$6:$G$1085,Data!$A$6:$A$1085,Exec_Summary!$C$4,Data!$D$6:$D$1085,$B21) -> 51801767
B22: Retail & Consumer | C22: =SUMIFS(Data!$G$6:$G$1085,Data!$A$6:$A$1085,Exec_Summary!$C$4,Data!$D$6:$D$1085,$B22,Data!$E$6:$E$1085,C$20) -> 9087847 | D22: =SUMIFS(Data!$G$6:$G$1085,Data!$A$6:$A$1085,Exec_Summary!$C$4,Data!$D$6:$D$1085,$B22,Data!$E$6:$E$1085,D$20) -> 6257341 | E22: =SUMIFS(Data!$G$6:$G$1085,Data!$A$6:$A$1085,Exec_Summary!$C$4,Data!$D$6:$D$1085,$B22,Data!$E$6:$E$1085,E$20) -> 7405930 | F22: =SUMIFS(Data!$G$6:$G$1085,Data!$A$6:$A$1085,Exec_Summary!$C$4,Data!$D$6:$D$1085,$B22,Data!$E$6:$E$1085,F$20) -> 5190114 | G22: =SUMIFS(Data!$G$6:$G$1085,Data!$A$6:$A$1085,Exec_Summary!$C$4,Data!$D$6:$D$1085,$B22,Data!$E$6:$E$1085,G$20) -> 5944412 | H22: =SUMIFS(Data!$G$6:$G$1085,Data!$A$6:$A$1085,Exec_Summary!$C$4,Data!$D$6:$D$1085,$B22,Data!$E$6:$E$1085,H$20) -> 2978699 | I22: =SUMIFS(Data!$G$6:$G$1085,Data!$A$6:$A$1085,Exec_Summary!$C$4,Data!$D$6:$D$1085,$B22) -> 36864343
B23: Healthcare & Life Sciences | C23: =SUMIFS(Data!$G$6:$G$1085,Data!$A$6:$A$1085,Exec_Summary!$C$4,Data!$D$6:$D$1085,$B23,Data!$E$6:$E$1085,C$20) -> 7272039 | D23: =SUMIFS(Data!$G$6:$G$1085,Data!$A$6:$A$1085,Exec_Summary!$C$4,Data!$D$6:$D$1085,$B23,Data!$E$6:$E$1085,D$20) -> 5130227 | E23: =SUMIFS(Data!$G$6:$G$1085,Data!$A$6:$A$1085,Exec_Summary!$C$4,Data!$D$6:$D$1085,$B23,Data!$E$6:$E$1085,E$20) -> 6061266 | F23: =SUMIFS(Data!$G$6:$G$1085,Data!$A$6:$A$1085,Exec_Summary!$C$4,Data!$D$6:$D$1085,$B23,Data!$E$6:$E$1085,F$20) -> 4609668 | G23: =SUMIFS(Data!$G$6:$G$1085,Data!$A$6:$A$1085,Exec_Summary!$C$4,Data!$D$6:$D$1085,$B23,Data!$E$6:$E$1085,G$20) -> 5018097 | H23: =SUMIFS(Data!$G$6:$G$1085,Data!$A$6:$A$1085,Exec_Summary!$C$4,Data!$D$6:$D$1085,$B23,Data!$E$6:$E$1085,H$20) -> 2420756 | I23: =SUMIFS(Data!$G$6:$G$1085,Data!$A$6:$A$1085,Exec_Summary!$C$4,Data!$D$6:$D$1085,$B23) -> 30512053
B24: Manufacturing & Logistics | C24: =SUMIFS(Data!$G$6:$G$1085,Data!$A$6:$A$1085,Exec_Summary!$C$4,Data!$D$6:$D$1085,$B24,Data!$E$6:$E$1085,C$20) -> 7696575 | D24: =SUMIFS(Data!$G$6:$G$1085,Data!$A$6:$A$1085,Exec_Summary!$C$4,Data!$D$6:$D$1085,$B24,Data!$E$6:$E$1085,D$20) -> 5369886 | E24: =SUMIFS(Data!$G$6:$G$1085,Data!$A$6:$A$1085,Exec_Summary!$C$4,Data!$D$6:$D$1085,$B24,Data!$E$6:$E$1085,E$20) -> 6461282 | F24: =SUMIFS(Data!$G$6:$G$1085,Data!$A$6:$A$1085,Exec_Summary!$C$4,Data!$D$6:$D$1085,$B24,Data!$E$6:$E$1085,F$20) -> 4805936 | G24: =SUMIFS(Data!$G$6:$G$1085,Data!$A$6:$A$1085,Exec_Summary!$C$4,Data!$D$6:$D$1085,$B24,Data!$E$6:$E$1085,G$20) -> 5175668 | H24: =SUMIFS(Data!$G$6:$G$1085,Data!$A$6:$A$1085,Exec_Summary!$C$4,Data!$D$6:$D$1085,$B24,Data!$E$6:$E$1085,H$20) -> 2496242 | I24: =SUMIFS(Data!$G$6:$G$1085,Data!$A$6:$A$1085,Exec_Summary!$C$4,Data!$D$6:$D$1085,$B24) -> 32005589
B25: Public Sector & Utilities | C25: =SUMIFS(Data!$G$6:$G$1085,Data!$A$6:$A$1085,Exec_Summary!$C$4,Data!$D$6:$D$1085,$B25,Data!$E$6:$E$1085,C$20) -> 4930950 | D25: =SUMIFS(Data!$G$6:$G$1085,Data!$A$6:$A$1085,Exec_Summary!$C$4,Data!$D$6:$D$1085,$B25,Data!$E$6:$E$1085,D$20) -> 3500536 | E25: =SUMIFS(Data!$G$6:$G$1085,Data!$A$6:$A$1085,Exec_Summary!$C$4,Data!$D$6:$D$1085,$B25,Data!$E$6:$E$1085,E$20) -> 4131861 | F25: =SUMIFS(Data!$G$6:$G$1085,Data!$A$6:$A$1085,Exec_Summary!$C$4,Data!$D$6:$D$1085,$B25,Data!$E$6:$E$1085,F$20) -> 3017258 | G25: =SUMIFS(Data!$G$6:$G$1085,Data!$A$6:$A$1085,Exec_Summary!$C$4,Data!$D$6:$D$1085,$B25,Data!$E$6:$E$1085,G$20) -> 3302570 | H25: =SUMIFS(Data!$G$6:$G$1085,Data!$A$6:$A$1085,Exec_Summary!$C$4,Data!$D$6:$D$1085,$B25,Data!$E$6:$E$1085,H$20) -> 1669228 | I25: =SUMIFS(Data!$G$6:$G$1085,Data!$A$6:$A$1085,Exec_Summary!$C$4,Data!$D$6:$D$1085,$B25) -> 20552403
B26: All | C26: =SUMIFS(Data!$G$6:$G$1085,Data!$A$6:$A$1085,Exec_Summary!$C$4,Data!$E$6:$E$1085,C$20) -> 41463881 | D26: =SUMIFS(Data!$G$6:$G$1085,Data!$A$6:$A$1085,Exec_Summary!$C$4,Data!$E$6:$E$1085,D$20) -> 29043865 | E26: =SUMIFS(Data!$G$6:$G$1085,Data!$A$6:$A$1085,Exec_Summary!$C$4,Data!$E$6:$E$1085,E$20) -> 34487273 | F26: =SUMIFS(Data!$G$6:$G$1085,Data!$A$6:$A$1085,Exec_Summary!$C$4,Data!$E$6:$E$1085,F$20) -> 25380235 | G26: =SUMIFS(Data!$G$6:$G$1085,Data!$A$6:$A$1085,Exec_Summary!$C$4,Data!$E$6:$E$1085,G$20) -> 27640311 | H26: =SUMIFS(Data!$G$6:$G$1085,Data!$A$6:$A$1085,Exec_Summary!$C$4,Data!$E$6:$E$1085,H$20) -> 13720590 | I26: =SUMIFS(Data!$G$6:$G$1085,Data!$A$6:$A$1085,Exec_Summary!$C$4) -> 171736155
B27: Revenue budget ($)
B28: Business unit | C28: UAE | D28: KSA | E28: India | F28: UK | G28: USA | H28: Singapore | I28: All
B29: Banking & Financial Services | C29: =SUMIFS(Data!$F$6:$F$1085,Data!$A$6:$A$1085,Exec_Summary!$C$4,Data!$D$6:$D$1085,$B29,Data!$E$6:$E$1085,C$28) -> 12722282 | D29: =SUMIFS(Data!$F$6:$F$1085,Data!$A$6:$A$1085,Exec_Summary!$C$4,Data!$D$6:$D$1085,$B29,Data!$E$6:$E$1085,D$28) -> 8974069 | E29: =SUMIFS(Data!$F$6:$F$1085,Data!$A$6:$A$1085,Exec_Summary!$C$4,Data!$D$6:$D$1085,$B29,Data!$E$6:$E$1085,E$28) -> 10568806 | F29: =SUMIFS(Data!$F$6:$F$1085,Data!$A$6:$A$1085,Exec_Summary!$C$4,Data!$D$6:$D$1085,$B29,Data!$E$6:$E$1085,F$28) -> 7911009 | G29: =SUMIFS(Data!$F$6:$F$1085,Data!$A$6:$A$1085,Exec_Summary!$C$4,Data!$D$6:$D$1085,$B29,Data!$E$6:$E$1085,G$28) -> 8484541 | H29: =SUMIFS(Data!$F$6:$F$1085,Data!$A$6:$A$1085,Exec_Summary!$C$4,Data!$D$6:$D$1085,$B29,Data!$E$6:$E$1085,H$28) -> 4240140 | I29: =SUMIFS(Data!$F$6:$F$1085,Data!$A$6:$A$1085,Exec_Summary!$C$4,Data!$D$6:$D$1085,$B29) -> 52900847
B30: Retail & Consumer | C30: =SUMIFS(Data!$F$6:$F$1085,Data!$A$6:$A$1085,Exec_Summary!$C$4,Data!$D$6:$D$1085,$B30,Data!$E$6:$E$1085,C$28) -> 9540513 | D30: =SUMIFS(Data!$F$6:$F$1085,Data!$A$6:$A$1085,Exec_Summary!$C$4,Data!$D$6:$D$1085,$B30,Data!$E$6:$E$1085,D$28) -> 6730168 | E30: =SUMIFS(Data!$F$6:$F$1085,Data!$A$6:$A$1085,Exec_Summary!$C$4,Data!$D$6:$D$1085,$B30,Data!$E$6:$E$1085,E$28) -> 7897842 | F30: =SUMIFS(Data!$F$6:$F$1085,Data!$A$6:$A$1085,Exec_Summary!$C$4,Data!$D$6:$D$1085,$B30,Data!$E$6:$E$1085,F$28) -> 5939899 | G30: =SUMIFS(Data!$F$6:$F$1085,Data!$A$6:$A$1085,Exec_Summary!$C$4,Data!$D$6:$D$1085,$B30,Data!$E$6:$E$1085,G$28) -> 6305450 | H30: =SUMIFS(Data!$F$6:$F$1085,Data!$A$6:$A$1085,Exec_Summary!$C$4,Data!$D$6:$D$1085,$B30,Data!$E$6:$E$1085,H$28) -> 3162348 | I30: =SUMIFS(Data!$F$6:$F$1085,Data!$A$6:$A$1085,Exec_Summary!$C$4,Data!$D$6:$D$1085,$B30) -> 39576220
B31: Healthcare & Life Sciences | C31: =SUMIFS(Data!$F$6:$F$1085,Data!$A$6:$A$1085,Exec_Summary!$C$4,Data!$D$6:$D$1085,$B31,Data!$E$6:$E$1085,C$28) -> 6807745 | D31: =SUMIFS(Data!$F$6:$F$1085,Data!$A$6:$A$1085,Exec_Summary!$C$4,Data!$D$6:$D$1085,$B31,Data!$E$6:$E$1085,D$28) -> 4829712 | E31: =SUMIFS(Data!$F$6:$F$1085,Data!$A$6:$A$1085,Exec_Summary!$C$4,Data!$D$6:$D$1085,$B31,Data!$E$6:$E$1085,E$28) -> 5725395 | F31: =SUMIFS(Data!$F$6:$F$1085,Data!$A$6:$A$1085,Exec_Summary!$C$4,Data!$D$6:$D$1085,$B31,Data!$E$6:$E$1085,F$28) -> 4279505 | G31: =SUMIFS(Data!$F$6:$F$1085,Data!$A$6:$A$1085,Exec_Summary!$C$4,Data!$D$6:$D$1085,$B31,Data!$E$6:$E$1085,G$28) -> 4545103 | H31: =SUMIFS(Data!$F$6:$F$1085,Data!$A$6:$A$1085,Exec_Summary!$C$4,Data!$D$6:$D$1085,$B31,Data!$E$6:$E$1085,H$28) -> 2292068 | I31: =SUMIFS(Data!$F$6:$F$1085,Data!$A$6:$A$1085,Exec_Summary!$C$4,Data!$D$6:$D$1085,$B31) -> 28479528
B32: Manufacturing & Logistics | C32: =SUMIFS(Data!$F$6:$F$1085,Data!$A$6:$A$1085,Exec_Summary!$C$4,Data!$D$6:$D$1085,$B32,Data!$E$6:$E$1085,C$28) -> 8219133 | D32: =SUMIFS(Data!$F$6:$F$1085,Data!$A$6:$A$1085,Exec_Summary!$C$4,Data!$D$6:$D$1085,$B32,Data!$E$6:$E$1085,D$28) -> 5790718 | E32: =SUMIFS(Data!$F$6:$F$1085,Data!$A$6:$A$1085,Exec_Summary!$C$4,Data!$D$6:$D$1085,$B32,Data!$E$6:$E$1085,E$28) -> 6824985 | F32: =SUMIFS(Data!$F$6:$F$1085,Data!$A$6:$A$1085,Exec_Summary!$C$4,Data!$D$6:$D$1085,$B32,Data!$E$6:$E$1085,F$28) -> 5070773 | G32: =SUMIFS(Data!$F$6:$F$1085,Data!$A$6:$A$1085,Exec_Summary!$C$4,Data!$D$6:$D$1085,$B32,Data!$E$6:$E$1085,G$28) -> 5475343 | H32: =SUMIFS(Data!$F$6:$F$1085,Data!$A$6:$A$1085,Exec_Summary!$C$4,Data!$D$6:$D$1085,$B32,Data!$E$6:$E$1085,H$28) -> 2714166 | I32: =SUMIFS(Data!$F$6:$F$1085,Data!$A$6:$A$1085,Exec_Summary!$C$4,Data!$D$6:$D$1085,$B32) -> 34095118
B33: Public Sector & Utilities | C33: =SUMIFS(Data!$F$6:$F$1085,Data!$A$6:$A$1085,Exec_Summary!$C$4,Data!$D$6:$D$1085,$B33,Data!$E$6:$E$1085,C$28) -> 4983094 | D33: =SUMIFS(Data!$F$6:$F$1085,Data!$A$6:$A$1085,Exec_Summary!$C$4,Data!$D$6:$D$1085,$B33,Data!$E$6:$E$1085,D$28) -> 3536430 | E33: =SUMIFS(Data!$F$6:$F$1085,Data!$A$6:$A$1085,Exec_Summary!$C$4,Data!$D$6:$D$1085,$B33,Data!$E$6:$E$1085,E$28) -> 4135907 | F33: =SUMIFS(Data!$F$6:$F$1085,Data!$A$6:$A$1085,Exec_Summary!$C$4,Data!$D$6:$D$1085,$B33,Data!$E$6:$E$1085,F$28) -> 3138184 | G33: =SUMIFS(Data!$F$6:$F$1085,Data!$A$6:$A$1085,Exec_Summary!$C$4,Data!$D$6:$D$1085,$B33,Data!$E$6:$E$1085,G$28) -> 3344414 | H33: =SUMIFS(Data!$F$6:$F$1085,Data!$A$6:$A$1085,Exec_Summary!$C$4,Data!$D$6:$D$1085,$B33,Data!$E$6:$E$1085,H$28) -> 1670880 | I33: =SUMIFS(Data!$F$6:$F$1085,Data!$A$6:$A$1085,Exec_Summary!$C$4,Data!$D$6:$D$1085,$B33) -> 20808909
B34: All | C34: =SUMIFS(Data!$F$6:$F$1085,Data!$A$6:$A$1085,Exec_Summary!$C$4,Data!$E$6:$E$1085,C$28) -> 42272767 | D34: =SUMIFS(Data!$F$6:$F$1085,Data!$A$6:$A$1085,Exec_Summary!$C$4,Data!$E$6:$E$1085,D$28) -> 29861097 | E34: =SUMIFS(Data!$F$6:$F$1085,Data!$A$6:$A$1085,Exec_Summary!$C$4,Data!$E$6:$E$1085,E$28) -> 35152935 | F34: =SUMIFS(Data!$F$6:$F$1085,Data!$A$6:$A$1085,Exec_Summary!$C$4,Data!$E$6:$E$1085,F$28) -> 26339370 | G34: =SUMIFS(Data!$F$6:$F$1085,Data!$A$6:$A$1085,Exec_Summary!$C$4,Data!$E$6:$E$1085,G$28) -> 28154851 | H34: =SUMIFS(Data!$F$6:$F$1085,Data!$A$6:$A$1085,Exec_Summary!$C$4,Data!$E$6:$E$1085,H$28) -> 14079602 | I34: =SUMIFS(Data!$F$6:$F$1085,Data!$A$6:$A$1085,Exec_Summary!$C$4) -> 175860622
B35: Absolute revenue error by cell |actual − budget| (feeds forecast-accuracy KPI)
B36: Business unit | C36: UAE | D36: KSA | E36: India | F36: UK | G36: USA | H36: Singapore | I36: All
B37: Banking & Financial Services | C37: =ABS(SUMIFS(Data!$G$6:$G$1085,Data!$A$6:$A$1085,Exec_Summary!$C$4,Data!$D$6:$D$1085,$B37,Data!$E$6:$E$1085,C$36)-SUMIFS(Data!$F$6:$F$1085,Data!$A$6:$A$1085,Exec_Summary!$C$4,Data!$D$6:$D$1085,$B37,Data!$E$6:$E$1085,C$36)) -> 245812 | D37: =ABS(SUMIFS(Data!$G$6:$G$1085,Data!$A$6:$A$1085,Exec_Summary!$C$4,Data!$D$6:$D$1085,$B37,Data!$E$6:$E$1085,D$36)-SUMIFS(Data!$F$6:$F$1085,Data!$A$6:$A$1085,Exec_Summary!$C$4,Data!$D$6:$D$1085,$B37,Data!$E$6:$E$1085,D$36)) -> 188194 | E37: =ABS(SUMIFS(Data!$G$6:$G$1085,Data!$A$6:$A$1085,Exec_Summary!$C$4,Data!$D$6:$D$1085,$B37,Data!$E$6:$E$1085,E$36)-SUMIFS(Data!$F$6:$F$1085,Data!$A$6:$A$1085,Exec_Summary!$C$4,Data!$D$6:$D$1085,$B37,Data!$E$6:$E$1085,E$36)) -> 141872 | F37: =ABS(SUMIFS(Data!$G$6:$G$1085,Data!$A$6:$A$1085,Exec_Summary!$C$4,Data!$D$6:$D$1085,$B37,Data!$E$6:$E$1085,F$36)-SUMIFS(Data!$F$6:$F$1085,Data!$A$6:$A$1085,Exec_Summary!$C$4,Data!$D$6:$D$1085,$B37,Data!$E$6:$E$1085,F$36)) -> 153750 | G37: =ABS(SUMIFS(Data!$G$6:$G$1085,Data!$A$6:$A$1085,Exec_Summary!$C$4,Data!$D$6:$D$1085,$B37,Data!$E$6:$E$1085,G$36)-SUMIFS(Data!$F$6:$F$1085,Data!$A$6:$A$1085,Exec_Summary!$C$4,Data!$D$6:$D$1085,$B37,Data!$E$6:$E$1085,G$36)) -> 284977 | H37: =ABS(SUMIFS(Data!$G$6:$G$1085,Data!$A$6:$A$1085,Exec_Summary!$C$4,Data!$D$6:$D$1085,$B37,Data!$E$6:$E$1085,H$36)-SUMIFS(Data!$F$6:$F$1085,Data!$A$6:$A$1085,Exec_Summary!$C$4,Data!$D$6:$D$1085,$B37,Data!$E$6:$E$1085,H$36)) -> 84475 | I37: =SUM(C37:H37) -> 1099080
B38: Retail & Consumer | C38: =ABS(SUMIFS(Data!$G$6:$G$1085,Data!$A$6:$A$1085,Exec_Summary!$C$4,Data!$D$6:$D$1085,$B38,Data!$E$6:$E$1085,C$36)-SUMIFS(Data!$F$6:$F$1085,Data!$A$6:$A$1085,Exec_Summary!$C$4,Data!$D$6:$D$1085,$B38,Data!$E$6:$E$1085,C$36)) -> 452666 | D38: =ABS(SUMIFS(Data!$G$6:$G$1085,Data!$A$6:$A$1085,Exec_Summary!$C$4,Data!$D$6:$D$1085,$B38,Data!$E$6:$E$1085,D$36)-SUMIFS(Data!$F$6:$F$1085,Data!$A$6:$A$1085,Exec_Summary!$C$4,Data!$D$6:$D$1085,$B38,Data!$E$6:$E$1085,D$36)) -> 472827 | E38: =ABS(SUMIFS(Data!$G$6:$G$1085,Data!$A$6:$A$1085,Exec_Summary!$C$4,Data!$D$6:$D$1085,$B38,Data!$E$6:$E$1085,E$36)-SUMIFS(Data!$F$6:$F$1085,Data!$A$6:$A$1085,Exec_Summary!$C$4,Data!$D$6:$D$1085,$B38,Data!$E$6:$E$1085,E$36)) -> 491912 | F38: =ABS(SUMIFS(Data!$G$6:$G$1085,Data!$A$6:$A$1085,Exec_Summary!$C$4,Data!$D$6:$D$1085,$B38,Data!$E$6:$E$1085,F$36)-SUMIFS(Data!$F$6:$F$1085,Data!$A$6:$A$1085,Exec_Summary!$C$4,Data!$D$6:$D$1085,$B38,Data!$E$6:$E$1085,F$36)) -> 749785 | G38: =ABS(SUMIFS(Data!$G$6:$G$1085,Data!$A$6:$A$1085,Exec_Summary!$C$4,Data!$D$6:$D$1085,$B38,Data!$E$6:$E$1085,G$36)-SUMIFS(Data!$F$6:$F$1085,Data!$A$6:$A$1085,Exec_Summary!$C$4,Data!$D$6:$D$1085,$B38,Data!$E$6:$E$1085,G$36)) -> 361038 | H38: =ABS(SUMIFS(Data!$G$6:$G$1085,Data!$A$6:$A$1085,Exec_Summary!$C$4,Data!$D$6:$D$1085,$B38,Data!$E$6:$E$1085,H$36)-SUMIFS(Data!$F$6:$F$1085,Data!$A$6:$A$1085,Exec_Summary!$C$4,Data!$D$6:$D$1085,$B38,Data!$E$6:$E$1085,H$36)) -> 183649 | I38: =SUM(C38:H38) -> 2711877
B39: Healthcare & Life Sciences | C39: =ABS(SUMIFS(Data!$G$6:$G$1085,Data!$A$6:$A$1085,Exec_Summary!$C$4,Data!$D$6:$D$1085,$B39,Data!$E$6:$E$1085,C$36)-SUMIFS(Data!$F$6:$F$1085,Data!$A$6:$A$1085,Exec_Summary!$C$4,Data!$D$6:$D$1085,$B39,Data!$E$6:$E$1085,C$36)) -> 464294 | D39: =ABS(SUMIFS(Data!$G$6:$G$1085,Data!$A$6:$A$1085,Exec_Summary!$C$4,Data!$D$6:$D$1085,$B39,Data!$E$6:$E$1085,D$36)-SUMIFS(Data!$F$6:$F$1085,Data!$A$6:$A$1085,Exec_Summary!$C$4,Data!$D$6:$D$1085,$B39,Data!$E$6:$E$1085,D$36)) -> 300515 | E39: =ABS(SUMIFS(Data!$G$6:$G$1085,Data!$A$6:$A$1085,Exec_Summary!$C$4,Data!$D$6:$D$1085,$B39,Data!$E$6:$E$1085,E$36)-SUMIFS(Data!$F$6:$F$1085,Data!$A$6:$A$1085,Exec_Summary!$C$4,Data!$D$6:$D$1085,$B39,Data!$E$6:$E$1085,E$36)) -> 335871 | F39: =ABS(SUMIFS(Data!$G$6:$G$1085,Data!$A$6:$A$1085,Exec_Summary!$C$4,Data!$D$6:$D$1085,$B39,Data!$E$6:$E$1085,F$36)-SUMIFS(Data!$F$6:$F$1085,Data!$A$6:$A$1085,Exec_Summary!$C$4,Data!$D$6:$D$1085,$B39,Data!$E$6:$E$1085,F$36)) -> 330163 | G39: =ABS(SUMIFS(Data!$G$6:$G$1085,Data!$A$6:$A$1085,Exec_Summary!$C$4,Data!$D$6:$D$1085,$B39,Data!$E$6:$E$1085,G$36)-SUMIFS(Data!$F$6:$F$1085,Data!$A$6:$A$1085,Exec_Summary!$C$4,Data!$D$6:$D$1085,$B39,Data!$E$6:$E$1085,G$36)) -> 472994 | H39: =ABS(SUMIFS(Data!$G$6:$G$1085,Data!$A$6:$A$1085,Exec_Summary!$C$4,Data!$D$6:$D$1085,$B39,Data!$E$6:$E$1085,H$36)-SUMIFS(Data!$F$6:$F$1085,Data!$A$6:$A$1085,Exec_Summary!$C$4,Data!$D$6:$D$1085,$B39,Data!$E$6:$E$1085,H$36)) -> 128688 | I39: =SUM(C39:H39) -> 2032525
B40: Manufacturing & Logistics | C40: =ABS(SUMIFS(Data!$G$6:$G$1085,Data!$A$6:$A$1085,Exec_Summary!$C$4,Data!$D$6:$D$1085,$B40,Data!$E$6:$E$1085,C$36)-SUMIFS(Data!$F$6:$F$1085,Data!$A$6:$A$1085,Exec_Summary!$C$4,Data!$D$6:$D$1085,$B40,Data!$E$6:$E$1085,C$36)) -> 522558 | D40: =ABS(SUMIFS(Data!$G$6:$G$1085,Data!$A$6:$A$1085,Exec_Summary!$C$4,Data!$D$6:$D$1085,$B40,Data!$E$6:$E$1085,D$36)-SUMIFS(Data!$F$6:$F$1085,Data!$A$6:$A$1085,Exec_Summary!$C$4,Data!$D$6:$D$1085,$B40,Data!$E$6:$E$1085,D$36)) -> 420832 | E40: =ABS(SUMIFS(Data!$G$6:$G$1085,Data!$A$6:$A$1085,Exec_Summary!$C$4,Data!$D$6:$D$1085,$B40,Data!$E$6:$E$1085,E$36)-SUMIFS(Data!$F$6:$F$1085,Data!$A$6:$A$1085,Exec_Summary!$C$4,Data!$D$6:$D$1085,$B40,Data!$E$6:$E$1085,E$36)) -> 363703 | F40: =ABS(SUMIFS(Data!$G$6:$G$1085,Data!$A$6:$A$1085,Exec_Summary!$C$4,Data!$D$6:$D$1085,$B40,Data!$E$6:$E$1085,F$36)-SUMIFS(Data!$F$6:$F$1085,Data!$A$6:$A$1085,Exec_Summary!$C$4,Data!$D$6:$D$1085,$B40,Data!$E$6:$E$1085,F$36)) -> 264837 | G40: =ABS(SUMIFS(Data!$G$6:$G$1085,Data!$A$6:$A$1085,Exec_Summary!$C$4,Data!$D$6:$D$1085,$B40,Data!$E$6:$E$1085,G$36)-SUMIFS(Data!$F$6:$F$1085,Data!$A$6:$A$1085,Exec_Summary!$C$4,Data!$D$6:$D$1085,$B40,Data!$E$6:$E$1085,G$36)) -> 299675 | H40: =ABS(SUMIFS(Data!$G$6:$G$1085,Data!$A$6:$A$1085,Exec_Summary!$C$4,Data!$D$6:$D$1085,$B40,Data!$E$6:$E$1085,H$36)-SUMIFS(Data!$F$6:$F$1085,Data!$A$6:$A$1085,Exec_Summary!$C$4,Data!$D$6:$D$1085,$B40,Data!$E$6:$E$1085,H$36)) -> 217924 | I40: =SUM(C40:H40) -> 2089529
B41: Public Sector & Utilities | C41: =ABS(SUMIFS(Data!$G$6:$G$1085,Data!$A$6:$A$1085,Exec_Summary!$C$4,Data!$D$6:$D$1085,$B41,Data!$E$6:$E$1085,C$36)-SUMIFS(Data!$F$6:$F$1085,Data!$A$6:$A$1085,Exec_Summary!$C$4,Data!$D$6:$D$1085,$B41,Data!$E$6:$E$1085,C$36)) -> 52144 | D41: =ABS(SUMIFS(Data!$G$6:$G$1085,Data!$A$6:$A$1085,Exec_Summary!$C$4,Data!$D$6:$D$1085,$B41,Data!$E$6:$E$1085,D$36)-SUMIFS(Data!$F$6:$F$1085,Data!$A$6:$A$1085,Exec_Summary!$C$4,Data!$D$6:$D$1085,$B41,Data!$E$6:$E$1085,D$36)) -> 35894 | E41: =ABS(SUMIFS(Data!$G$6:$G$1085,Data!$A$6:$A$1085,Exec_Summary!$C$4,Data!$D$6:$D$1085,$B41,Data!$E$6:$E$1085,E$36)-SUMIFS(Data!$F$6:$F$1085,Data!$A$6:$A$1085,Exec_Summary!$C$4,Data!$D$6:$D$1085,$B41,Data!$E$6:$E$1085,E$36)) -> 4046 | F41: =ABS(SUMIFS(Data!$G$6:$G$1085,Data!$A$6:$A$1085,Exec_Summary!$C$4,Data!$D$6:$D$1085,$B41,Data!$E$6:$E$1085,F$36)-SUMIFS(Data!$F$6:$F$1085,Data!$A$6:$A$1085,Exec_Summary!$C$4,Data!$D$6:$D$1085,$B41,Data!$E$6:$E$1085,F$36)) -> 120926 | G41: =ABS(SUMIFS(Data!$G$6:$G$1085,Data!$A$6:$A$1085,Exec_Summary!$C$4,Data!$D$6:$D$1085,$B41,Data!$E$6:$E$1085,G$36)-SUMIFS(Data!$F$6:$F$1085,Data!$A$6:$A$1085,Exec_Summary!$C$4,Data!$D$6:$D$1085,$B41,Data!$E$6:$E$1085,G$36)) -> 41844 | H41: =ABS(SUMIFS(Data!$G$6:$G$1085,Data!$A$6:$A$1085,Exec_Summary!$C$4,Data!$D$6:$D$1085,$B41,Data!$E$6:$E$1085,H$36)-SUMIFS(Data!$F$6:$F$1085,Data!$A$6:$A$1085,Exec_Summary!$C$4,Data!$D$6:$D$1085,$B41,Data!$E$6:$E$1085,H$36)) -> 1652 | I41: =SUM(C41:H41) -> 256506
B42: Total absolute error | C42: =SUM(I37:I41) -> 8189517
B43: Total revenue budget | C43: =I34 -> 175860622
B44: WAPE (weighted absolute % error) | C44: =C42/C43 -> 0.046568225

Sheet Bridge
B1: Operating-income bridge: Budget → Actual
B2: Exact three-factor decomposition per business unit: volume (revenue variance at budget margin), direct-cost rate, opex rate · selected fiscal year
B3: Fiscal year | C3: =Exec_Summary!C4 -> FY26
B5: Step | C5: $
B6: Budget operating income | C6: =I20 -> 43196410
B7: Volume / revenue effect | C7: =J20 -> -767006.99
B8: Direct-cost rate effect | C8: =K20 -> -2293774.3
B9: Opex rate effect | C9: =L20 -> -577251.71
B10: Actual operating income | C10: =SUM(C6:C9) -> 39558377
B13: Bridge by business unit
B14: Business unit | C14: Rev budget | D14: Rev actual | E14: Direct cost bud | F14: Direct cost act | G14: Opex budget | H14: Opex actual | I14: Budget OI | J14: Volume | K14: Direct-cost rate | L14: Opex rate | M14: Actual OI | N14: Check
B15: Banking & Financial Services | C15: =SUMIFS(Data!$F$6:$F$1085,Data!$A$6:$A$1085,Exec_Summary!$C$4,Data!$D$6:$D$1085,$B15) -> 52900847 | D15: =SUMIFS(Data!$G$6:$G$1085,Data!$A$6:$A$1085,Exec_Summary!$C$4,Data!$D$6:$D$1085,$B15) -> 51801767 | E15: =SUMIFS(Data!$H$6:$H$1085,Data!$A$6:$A$1085,Exec_Summary!$C$4,Data!$D$6:$D$1085,$B15) -> 30391533 | F15: =SUMIFS(Data!$I$6:$I$1085,Data!$A$6:$A$1085,Exec_Summary!$C$4,Data!$D$6:$D$1085,$B15) -> 30276738 | G15: =SUMIFS(Data!$J$6:$J$1085,Data!$A$6:$A$1085,Exec_Summary!$C$4,Data!$D$6:$D$1085,$B15) -> 8649288 | H15: =SUMIFS(Data!$K$6:$K$1085,Data!$A$6:$A$1085,Exec_Summary!$C$4,Data!$D$6:$D$1085,$B15) -> 8591213 | I15: =C15-E15-G15 -> 13860026 | J15: =(D15-C15)*(1-E15/C15-G15/C15) -> -287959.04 | K15: =-D15*(F15/D15-E15/C15) -> -516626.39 | L15: =-D15*(H15/D15-G15/C15) -> -121624.57 | M15: =SUM(I15:L15) -> 12933816 | N15: =ROUND(M15-(D15-F15-H15),2) -> 0
B16: Retail & Consumer | C16: =SUMIFS(Data!$F$6:$F$1085,Data!$A$6:$A$1085,Exec_Summary!$C$4,Data!$D$6:$D$1085,$B16) -> 39576220 | D16: =SUMIFS(Data!$G$6:$G$1085,Data!$A$6:$A$1085,Exec_Summary!$C$4,Data!$D$6:$D$1085,$B16) -> 36864343 | E16: =SUMIFS(Data!$H$6:$H$1085,Data!$A$6:$A$1085,Exec_Summary!$C$4,Data!$D$6:$D$1085,$B16) -> 24715353 | F16: =SUMIFS(Data!$I$6:$I$1085,Data!$A$6:$A$1085,Exec_Summary!$C$4,Data!$D$6:$D$1085,$B16) -> 23278541 | G16: =SUMIFS(Data!$J$6:$J$1085,Data!$A$6:$A$1085,Exec_Summary!$C$4,Data!$D$6:$D$1085,$B16) -> 5877067 | H16: =SUMIFS(Data!$K$6:$K$1085,Data!$A$6:$A$1085,Exec_Summary!$C$4,Data!$D$6:$D$1085,$B16) -> 5785318 | I16: =C16-E16-G16 -> 8983800 | J16: =(D16-C16)*(1-E16/C16-G16/C16) -> -615595.95 | K16: =-D16*(F16/D16-E16/C16) -> -256755.43 | L16: =-D16*(H16/D16-G16/C16) -> -310964.62 | M16: =SUM(I16:L16) -> 7800484 | N16: =ROUND(M16-(D16-F16-H16),2) -> 0
B17: Healthcare & Life Sciences | C17: =SUMIFS(Data!$F$6:$F$1085,Data!$A$6:$A$1085,Exec_Summary!$C$4,Data!$D$6:$D$1085,$B17) -> 28479528 | D17: =SUMIFS(Data!$G$6:$G$1085,Data!$A$6:$A$1085,Exec_Summary!$C$4,Data!$D$6:$D$1085,$B17) -> 30512053 | E17: =SUMIFS(Data!$H$6:$H$1085,Data!$A$6:$A$1085,Exec_Summary!$C$4,Data!$D$6:$D$1085,$B17) -> 15507102 | F17: =SUMIFS(Data!$I$6:$I$1085,Data!$A$6:$A$1085,Exec_Summary!$C$4,Data!$D$6:$D$1085,$B17) -> 16897534 | G17: =SUMIFS(Data!$J$6:$J$1085,Data!$A$6:$A$1085,Exec_Summary!$C$4,Data!$D$6:$D$1085,$B17) -> 4514005 | H17: =SUMIFS(Data!$K$6:$K$1085,Data!$A$6:$A$1085,Exec_Summary!$C$4,Data!$D$6:$D$1085,$B17) -> 4849356 | I17: =C17-E17-G17 -> 8458421 | J17: =(D17-C17)*(1-E17/C17-G17/C17) -> 603660.01 | K17: =-D17*(F17/D17-E17/C17) -> -283722.21 | L17: =-D17*(H17/D17-G17/C17) -> -13195.801 | M17: =SUM(I17:L17) -> 8765163 | N17: =ROUND(M17-(D17-F17-H17),2) -> 0
B18: Manufacturing & Logistics | C18: =SUMIFS(Data!$F$6:$F$1085,Data!$A$6:$A$1085,Exec_Summary!$C$4,Data!$D$6:$D$1085,$B18) -> 34095118 | D18: =SUMIFS(Data!$G$6:$G$1085,Data!$A$6:$A$1085,Exec_Summary!$C$4,Data!$D$6:$D$1085,$B18) -> 32005589 | E18: =SUMIFS(Data!$H$6:$H$1085,Data!$A$6:$A$1085,Exec_Summary!$C$4,Data!$D$6:$D$1085,$B18) -> 22997151 | F18: =SUMIFS(Data!$I$6:$I$1085,Data!$A$6:$A$1085,Exec_Summary!$C$4,Data!$D$6:$D$1085,$B18) -> 22643499 | G18: =SUMIFS(Data!$J$6:$J$1085,Data!$A$6:$A$1085,Exec_Summary!$C$4,Data!$D$6:$D$1085,$B18) -> 4551699 | H18: =SUMIFS(Data!$K$6:$K$1085,Data!$A$6:$A$1085,Exec_Summary!$C$4,Data!$D$6:$D$1085,$B18) -> 4362377 | I18: =C18-E18-G18 -> 6546268 | J18: =(D18-C18)*(1-E18/C18-G18/C18) -> -401189.9 | K18: =-D18*(F18/D18-E18/C18) -> -1055734.9 | L18: =-D18*(H18/D18-G18/C18) -> -89630.167 | M18: =SUM(I18:L18) -> 4999713 | N18: =ROUND(M18-(D18-F18-H18),2) -> 0
B19: Public Sector & Utilities | C19: =SUMIFS(Data!$F$6:$F$1085,Data!$A$6:$A$1085,Exec_Summary!$C$4,Data!$D$6:$D$1085,$B19) -> 20808909 | D19: =SUMIFS(Data!$G$6:$G$1085,Data!$A$6:$A$1085,Exec_Summary!$C$4,Data!$D$6:$D$1085,$B19) -> 20552403 | E19: =SUMIFS(Data!$H$6:$H$1085,Data!$A$6:$A$1085,Exec_Summary!$C$4,Data!$D$6:$D$1085,$B19) -> 12474940 | F19: =SUMIFS(Data!$I$6:$I$1085,Data!$A$6:$A$1085,Exec_Summary!$C$4,Data!$D$6:$D$1085,$B19) -> 12502100 | G19: =SUMIFS(Data!$J$6:$J$1085,Data!$A$6:$A$1085,Exec_Summary!$C$4,Data!$D$6:$D$1085,$B19) -> 2986074 | H19: =SUMIFS(Data!$K$6:$K$1085,Data!$A$6:$A$1085,Exec_Summary!$C$4,Data!$D$6:$D$1085,$B19) -> 2991102 | I19: =C19-E19-G19 -> 5347895 | J19: =(D19-C19)*(1-E19/C19-G19/C19) -> -65922.108 | K19: =-D19*(F19/D19-E19/C19) -> -180935.34 | L19: =-D19*(H19/D19-G19/C19) -> -41836.556 | M19: =SUM(I19:L19) -> 5059201 | N19: =ROUND(M19-(D19-F19-H19),2) -> 0
B20: Total | C20: =SUM(C15:C19) -> 175860622 | D20: =SUM(D15:D19) -> 171736155 | E20: =SUM(E15:E19) -> 106086079 | F20: =SUM(F15:F19) -> 105598412 | G20: =SUM(G15:G19) -> 26578133 | H20: =SUM(H15:H19) -> 26579366 | I20: =SUM(I15:I19) -> 43196410 | J20: =SUM(J15:J19) -> -767006.99 | ... N20: =SUM(N15:N19) -> 0
B23: Waterfall chart data (helper)
B24: Step | C24: Movement | D24: Cumulative | E24: Base (hidden) | F24: Increase | G24: Decrease | H24: Total
B25: Budget OI | C25: =C6 -> 43196410 | D25: =C25 -> 43196410 | E25: =0 -> 0 | F25: =0 -> 0 | G25: =0 -> 0 | H25: =C25 -> 43196410
B26: Volume | C26: =C7 -> -767006.99 | D26: =D25+C26 -> 42429403 | E26: =MIN(D25,D26) -> 42429403 | F26: =MAX(C26,0) -> 0 | G26: =MAX(-C26,0) -> 767006.99 | H26: =0 -> 0
B27: Direct-cost rate | C27: =C8 -> -2293774.3 | D27: =D26+C27 -> 40135629 | E27: =MIN(D26,D27) -> 40135629 | F27: =MAX(C27,0) -> 0 | G27: =MAX(-C27,0) -> 2293774.3 | H27: =0 -> 0
B28: Opex rate | C28: =C9 -> -577251.71 | D28: =D27+C28 -> 39558377 | E28: =MIN(D27,D28) -> 39558377 | F28: =MAX(C28,0) -> 0 | G28: =MAX(-C28,0) -> 577251.71 | H28: =0 -> 0
B29: Actual OI | C29: =C10 -> 39558377 | D29: =C29 -> 39558377 | E29: =0 -> 0 | F29: =0 -> 0 | G29: =0 -> 0 | H29: =C29 -> 39558377

Sheet Monthly_Trend
B1: Monthly trend — selected fiscal year
B2: Rolling 12-month view driven by Exec_Summary!C4
B5: Month | C5: Revenue budget | D5: Revenue actual | E5: Rev var % | F5: Gross margin % | G5: OI budget | H5: OI actual | I5: OI margin % | J5: Adverse cells
B6: =DATE(2000+VALUE(RIGHT(Exec_Summary!$C$4,2))-1,4,1) -> 45748 | C6: =SUMIFS(Data!$F$6:$F$1085,Data!$C$6:$C$1085,$B6) -> 13963521 | D6: =SUMIFS(Data!$G$6:$G$1085,Data!$C$6:$C$1085,$B6) -> 13752296 | E6: =D6/C6-1 -> -0.015126915 | F6: =(SUMIFS(Data!$O$6:$O$1085,Data!$C$6:$C$1085,$B6))/D6 -> 0.38452539 | G6: =SUMIFS(Data!$Q$6:$Q$1085,Data!$C$6:$C$1085,$B6) -> 3420189 | H6: =SUMIFS(Data!$R$6:$R$1085,Data!$C$6:$C$1085,$B6) -> 3122880 | I6: =H6/D6 -> 0.22708063 | J6: =COUNTIFS(Data!$C$6:$C$1085,$B6,Data!$U$6:$U$1085,"ADVERSE") -> 9
B7: =EDATE(B6,1) -> 45778 | C7: =SUMIFS(Data!$F$6:$F$1085,Data!$C$6:$C$1085,$B7) -> 13984396 | D7: =SUMIFS(Data!$G$6:$G$1085,Data!$C$6:$C$1085,$B7) -> 13814565 | E7: =D7/C7-1 -> -0.012144321 | F7: =(SUMIFS(Data!$O$6:$O$1085,Data!$C$6:$C$1085,$B7))/D7 -> 0.38349459 | G7: =SUMIFS(Data!$Q$6:$Q$1085,Data!$C$6:$C$1085,$B7) -> 3426513 | H7: =SUMIFS(Data!$R$6:$R$1085,Data!$C$6:$C$1085,$B7) -> 3179333 | I7: =H7/D7 -> 0.23014355 | J7: =COUNTIFS(Data!$C$6:$C$1085,$B7,Data!$U$6:$U$1085,"ADVERSE") -> 8
B8: =EDATE(B7,1) -> 45809 | C8: =SUMIFS(Data!$F$6:$F$1085,Data!$C$6:$C$1085,$B8) -> 14300927 | D8: =SUMIFS(Data!$G$6:$G$1085,Data!$C$6:$C$1085,$B8) -> 13944756 | E8: =D8/C8-1 -> -0.024905448 | F8: =(SUMIFS(Data!$O$6:$O$1085,Data!$C$6:$C$1085,$B8))/D8 -> 0.38547795 | G8: =SUMIFS(Data!$Q$6:$Q$1085,Data!$C$6:$C$1085,$B8) -> 3507297 | H8: =SUMIFS(Data!$R$6:$R$1085,Data!$C$6:$C$1085,$B8) -> 3205988 | I8: =H8/D8 -> 0.22990635 | J8: =COUNTIFS(Data!$C$6:$C$1085,$B8,Data!$U$6:$U$1085,"ADVERSE") -> 9
B9: =EDATE(B8,1) -> 45839 | C9: =SUMIFS(Data!$F$6:$F$1085,Data!$C$6:$C$1085,$B9) -> 14580210 | D9: =SUMIFS(Data!$G$6:$G$1085,Data!$C$6:$C$1085,$B9) -> 14131317 | E9: =D9/C9-1 -> -0.030787828 | F9: =(SUMIFS(Data!$O$6:$O$1085,Data!$C$6:$C$1085,$B9))/D9 -> 0.38388149 | G9: =SUMIFS(Data!$Q$6:$Q$1085,Data!$C$6:$C$1085,$B9) -> 3576805 | H9: =SUMIFS(Data!$R$6:$R$1085,Data!$C$6:$C$1085,$B9) -> 3243707 | I9: =H9/D9 -> 0.22954032 | J9: =COUNTIFS(Data!$C$6:$C$1085,$B9,Data!$U$6:$U$1085,"ADVERSE") -> 10
B10: =EDATE(B9,1) -> 45870 | C10: =SUMIFS(Data!$F$6:$F$1085,Data!$C$6:$C$1085,$B10) -> 14127260 | D10: =SUMIFS(Data!$G$6:$G$1085,Data!$C$6:$C$1085,$B10) -> 14003303 | E10: =D10/C10-1 -> -0.0087743129 | F10: =(SUMIFS(Data!$O$6:$O$1085,Data!$C$6:$C$1085,$B10))/D10 -> 0.38625337 | G10: =SUMIFS(Data!$Q$6:$Q$1085,Data!$C$6:$C$1085,$B10) -> 3467405 | H10: =SUMIFS(Data!$R$6:$R$1085,Data!$C$6:$C$1085,$B10) -> 3267889 | I10: =H10/D10 -> 0.23336559 | J10: =COUNTIFS(Data!$C$6:$C$1085,$B10,Data!$U$6:$U$1085,"ADVERSE") -> 7
B11: =EDATE(B10,1) -> 45901 | C11: =SUMIFS(Data!$F$6:$F$1085,Data!$C$6:$C$1085,$B11) -> 14546136 | D11: =SUMIFS(Data!$G$6:$G$1085,Data!$C$6:$C$1085,$B11) -> 14340747 | E11: =D11/C11-1 -> -0.014119832 | F11: =(SUMIFS(Data!$O$6:$O$1085,Data!$C$6:$C$1085,$B11))/D11 -> 0.38352354 | G11: =SUMIFS(Data!$Q$6:$Q$1085,Data!$C$6:$C$1085,$B11) -> 3571054 | H11: =SUMIFS(Data!$R$6:$R$1085,Data!$C$6:$C$1085,$B11) -> 3273677 | I11: =H11/D11 -> 0.228278 | J11: =COUNTIFS(Data!$C$6:$C$1085,$B11,Data!$U$6:$U$1085,"ADVERSE") -> 9
B12: =EDATE(B11,1) -> 45931 | C12: =SUMIFS(Data!$F$6:$F$1085,Data!$C$6:$C$1085,$B12) -> 15080602 | D12: =SUMIFS(Data!$G$6:$G$1085,Data!$C$6:$C$1085,$B12) -> 14671871 | E12: =D12/C12-1 -> -0.027103096 | F12: =(SUMIFS(Data!$O$6:$O$1085,Data!$C$6:$C$1085,$B12))/D12 -> 0.38387926 | G12: =SUMIFS(Data!$Q$6:$Q$1085,Data!$C$6:$C$1085,$B12) -> 3704854 | H12: =SUMIFS(Data!$R$6:$R$1085,Data!$C$6:$C$1085,$B12) -> 3382462 | I12: =H12/D12 -> 0.2305406 | J12: =COUNTIFS(Data!$C$6:$C$1085,$B12,Data!$U$6:$U$1085,"ADVERSE") -> 7
B13: =EDATE(B12,1) -> 45962 | C13: =SUMIFS(Data!$F$6:$F$1085,Data!$C$6:$C$1085,$B13) -> 14995115 | D13: =SUMIFS(Data!$G$6:$G$1085,Data!$C$6:$C$1085,$B13) -> 14596887 | E13: =D13/C13-1 -> -0.026557182 | F13: =(SUMIFS(Data!$O$6:$O$1085,Data!$C$6:$C$1085,$B13))/D13 -> 0.38639554 | G13: =SUMIFS(Data!$Q$6:$Q$1085,Data!$C$6:$C$1085,$B13) -> 3685539 | H13: =SUMIFS(Data!$R$6:$R$1085,Data!$C$6:$C$1085,$B13) -> 3369820 | I13: =H13/D13 -> 0.23085881 | J13: =COUNTIFS(Data!$C$6:$C$1085,$B13,Data!$U$6:$U$1085,"ADVERSE") -> 9
B14: =EDATE(B13,1) -> 45992 | C14: =SUMIFS(Data!$F$6:$F$1085,Data!$C$6:$C$1085,$B14) -> 14889651 | D14: =SUMIFS(Data!$G$6:$G$1085,Data!$C$6:$C$1085,$B14) -> 14405688 | E14: =D14/C14-1 -> -0.032503314 | F14: =(SUMIFS(Data!$O$6:$O$1085,Data!$C$6:$C$1085,$B14))/D14 -> 0.38296782 | G14: =SUMIFS(Data!$Q$6:$Q$1085,Data!$C$6:$C$1085,$B14) -> 3662613 | H14: =SUMIFS(Data!$R$6:$R$1085,Data!$C$6:$C$1085,$B14) -> 3302069 | I14: =H14/D14 -> 0.22921981 | J14: =COUNTIFS(Data!$C$6:$C$1085,$B14,Data!$U$6:$U$1085,"ADVERSE") -> 10
B15: =EDATE(B14,1) -> 46023 | C15: =SUMIFS(Data!$F$6:$F$1085,Data!$C$6:$C$1085,$B15) -> 14496325 | D15: =SUMIFS(Data!$G$6:$G$1085,Data!$C$6:$C$1085,$B15) -> 14161709 | E15: =D15/C15-1 -> -0.023082816 | F15: =(SUMIFS(Data!$O$6:$O$1085,Data!$C$6:$C$1085,$B15))/D15 -> 0.38622584 | G15: =SUMIFS(Data!$Q$6:$Q$1085,Data!$C$6:$C$1085,$B15) -> 3566698 | H15: =SUMIFS(Data!$R$6:$R$1085,Data!$C$6:$C$1085,$B15) -> 3273988 | I15: =H15/D15 -> 0.23118594 | J15: =COUNTIFS(Data!$C$6:$C$1085,$B15,Data!$U$6:$U$1085,"ADVERSE") -> 7
B16: =EDATE(B15,1) -> 46054 | C16: =SUMIFS(Data!$F$6:$F$1085,Data!$C$6:$C$1085,$B16) -> 14769347 | D16: =SUMIFS(Data!$G$6:$G$1085,Data!$C$6:$C$1085,$B16) -> 14445787 | E16: =D16/C16-1 -> -0.021907536 | F16: =(SUMIFS(Data!$O$6:$O$1085,Data!$C$6:$C$1085,$B16))/D16 -> 0.38784408 | G16: =SUMIFS(Data!$Q$6:$Q$1085,Data!$C$6:$C$1085,$B16) -> 3636648 | H16: =SUMIFS(Data!$R$6:$R$1085,Data!$C$6:$C$1085,$B16) -> 3360722 | I16: =H16/D16 -> 0.23264375 | J16: =COUNTIFS(Data!$C$6:$C$1085,$B16,Data!$U$6:$U$1085,"ADVERSE") -> 9
B17: =EDATE(B16,1) -> 46082 | C17: =SUMIFS(Data!$F$6:$F$1085,Data!$C$6:$C$1085,$B17) -> 16127132 | D17: =SUMIFS(Data!$G$6:$G$1085,Data!$C$6:$C$1085,$B17) -> 15467229 | E17: =D17/C17-1 -> -0.040918807 | F17: =(SUMIFS(Data!$O$6:$O$1085,Data!$C$6:$C$1085,$B17))/D17 -> 0.3867012 | G17: =SUMIFS(Data!$Q$6:$Q$1085,Data!$C$6:$C$1085,$B17) -> 3970795 | H17: =SUMIFS(Data!$R$6:$R$1085,Data!$C$6:$C$1085,$B17) -> 3575842 | I17: =H17/D17 -> 0.23118828 | J17: =COUNTIFS(Data!$C$6:$C$1085,$B17,Data!$U$6:$U$1085,"ADVERSE") -> 10
B18: Full year | C18: =SUM(C6:C17) -> 175860622 | D18: =SUM(D6:D17) -> 171736155 | E18: =D18/C18-1 -> -0.023453045 | G18: =SUM(G6:G17) -> 43196410 | H18: =SUM(H6:H17) -> 39558377 | I18: =H18/D18 -> 0.23034391 | J18: =SUM(J6:J17) -> 104

Sheet Segment_Trends
B1: Three-year segment trends
B2: Revenue, operating margin and budget accuracy by business unit and region across FY24–FY26
B4: Business units
B5: Segment | C5: Rev FY24 | D5: Rev FY25 | E5: Rev FY26 | F5: OM% FY24 | G5: OM% FY25 | H5: OM% FY26 | I5: Rev vs bud FY24 | J5: Rev vs bud FY25 | K5: Rev vs bud FY26
B6: Banking & Financial Services | C6: =SUMIFS(Data!$G$6:$G$1085,Data!$D$6:$D$1085,$B6,Data!$A$6:$A$1085,"FY24") -> 43657852 | D6: =SUMIFS(Data!$G$6:$G$1085,Data!$D$6:$D$1085,$B6,Data!$A$6:$A$1085,"FY25") -> 47783218 | E6: =SUMIFS(Data!$G$6:$G$1085,Data!$D$6:$D$1085,$B6,Data!$A$6:$A$1085,"FY26") -> 51801767 | F6: =(SUMIFS(Data!$R$6:$R$1085,Data!$D$6:$D$1085,$B6,Data!$A$6:$A$1085,"FY24"))/C6 -> 0.2597426 | G6: =(SUMIFS(Data!$R$6:$R$1085,Data!$D$6:$D$1085,$B6,Data!$A$6:$A$1085,"FY25"))/D6 -> 0.25968017 | H6: =(SUMIFS(Data!$R$6:$R$1085,Data!$D$6:$D$1085,$B6,Data!$A$6:$A$1085,"FY26"))/E6 -> 0.24967905 | I6: =C6/(SUMIFS(Data!$F$6:$F$1085,Data!$D$6:$D$1085,$B6,Data!$A$6:$A$1085,"FY24"))-1 -> 0.029257118 | J6: =D6/(SUMIFS(Data!$F$6:$F$1085,Data!$D$6:$D$1085,$B6,Data!$A$6:$A$1085,"FY25"))-1 -> 0.0080185024 | K6: =E6/(SUMIFS(Data!$F$6:$F$1085,Data!$D$6:$D$1085,$B6,Data!$A$6:$A$1085,"FY26"))-1 -> -0.020776227
B7: Retail & Consumer | C7: =SUMIFS(Data!$G$6:$G$1085,Data!$D$6:$D$1085,$B7,Data!$A$6:$A$1085,"FY24") -> 33661462 | D7: =SUMIFS(Data!$G$6:$G$1085,Data!$D$6:$D$1085,$B7,Data!$A$6:$A$1085,"FY25") -> 35641222 | E7: =SUMIFS(Data!$G$6:$G$1085,Data!$D$6:$D$1085,$B7,Data!$A$6:$A$1085,"FY26") -> 36864343 | F7: =(SUMIFS(Data!$R$6:$R$1085,Data!$D$6:$D$1085,$B7,Data!$A$6:$A$1085,"FY24"))/C7 -> 0.22556941 | G7: =(SUMIFS(Data!$R$6:$R$1085,Data!$D$6:$D$1085,$B7,Data!$A$6:$A$1085,"FY25"))/D7 -> 0.22403202 | H7: =(SUMIFS(Data!$R$6:$R$1085,Data!$D$6:$D$1085,$B7,Data!$A$6:$A$1085,"FY26"))/E7 -> 0.2115997 | I7: =C7/(SUMIFS(Data!$F$6:$F$1085,Data!$D$6:$D$1085,$B7,Data!$A$6:$A$1085,"FY24"))-1 -> 0.0038424382 | J7: =D7/(SUMIFS(Data!$F$6:$F$1085,Data!$D$6:$D$1085,$B7,Data!$A$6:$A$1085,"FY25"))-1 -> -0.015921534 | K7: =E7/(SUMIFS(Data!$F$6:$F$1085,Data!$D$6:$D$1085,$B7,Data!$A$6:$A$1085,"FY26"))-1 -> -0.068522891
B8: Healthcare & Life Sciences | C8: =SUMIFS(Data!$G$6:$G$1085,Data!$D$6:$D$1085,$B8,Data!$A$6:$A$1085,"FY24") -> 21829426 | D8: =SUMIFS(Data!$G$6:$G$1085,Data!$D$6:$D$1085,$B8,Data!$A$6:$A$1085,"FY25") -> 25871048 | E8: =SUMIFS(Data!$G$6:$G$1085,Data!$D$6:$D$1085,$B8,Data!$A$6:$A$1085,"FY26") -> 30512053 | F8: =(SUMIFS(Data!$R$6:$R$1085,Data!$D$6:$D$1085,$B8,Data!$A$6:$A$1085,"FY24"))/C8 -> 0.29696846 | G8: =(SUMIFS(Data!$R$6:$R$1085,Data!$D$6:$D$1085,$B8,Data!$A$6:$A$1085,"FY25"))/D8 -> 0.29445556 | H8: =(SUMIFS(Data!$R$6:$R$1085,Data!$D$6:$D$1085,$B8,Data!$A$6:$A$1085,"FY26"))/E8 -> 0.28726887 | I8: =C8/(SUMIFS(Data!$F$6:$F$1085,Data!$D$6:$D$1085,$B8,Data!$A$6:$A$1085,"FY24"))-1 -> 0.028165021 | J8: =D8/(SUMIFS(Data!$F$6:$F$1085,Data!$D$6:$D$1085,$B8,Data!$A$6:$A$1085,"FY25"))-1 -> 0.060027451 | K8: =E8/(SUMIFS(Data!$F$6:$F$1085,Data!$D$6:$D$1085,$B8,Data!$A$6:$A$1085,"FY26"))-1 -> 0.071367931
B9: Manufacturing & Logistics | C9: =SUMIFS(Data!$G$6:$G$1085,Data!$D$6:$D$1085,$B9,Data!$A$6:$A$1085,"FY24") -> 30599428 | D9: =SUMIFS(Data!$G$6:$G$1085,Data!$D$6:$D$1085,$B9,Data!$A$6:$A$1085,"FY25") -> 31304979 | E9: =SUMIFS(Data!$G$6:$G$1085,Data!$D$6:$D$1085,$B9,Data!$A$6:$A$1085,"FY26") -> 32005589 | F9: =(SUMIFS(Data!$R$6:$R$1085,Data!$D$6:$D$1085,$B9,Data!$A$6:$A$1085,"FY24"))/C9 -> 0.1898324 | G9: =(SUMIFS(Data!$R$6:$R$1085,Data!$D$6:$D$1085,$B9,Data!$A$6:$A$1085,"FY25"))/D9 -> 0.17644771 | H9: =(SUMIFS(Data!$R$6:$R$1085,Data!$D$6:$D$1085,$B9,Data!$A$6:$A$1085,"FY26"))/E9 -> 0.15621375 | I9: =C9/(SUMIFS(Data!$F$6:$F$1085,Data!$D$6:$D$1085,$B9,Data!$A$6:$A$1085,"FY24"))-1 -> 0.011695618 | J9: =D9/(SUMIFS(Data!$F$6:$F$1085,Data!$D$6:$D$1085,$B9,Data!$A$6:$A$1085,"FY25"))-1 -> -0.026430539 | K9: =E9/(SUMIFS(Data!$F$6:$F$1085,Data!$D$6:$D$1085,$B9,Data!$A$6:$A$1085,"FY26"))-1 -> -0.061285284
B10: Public Sector & Utilities | C10: =SUMIFS(Data!$G$6:$G$1085,Data!$D$6:$D$1085,$B10,Data!$A$6:$A$1085,"FY24") -> 18257337 | D10: =SUMIFS(Data!$G$6:$G$1085,Data!$D$6:$D$1085,$B10,Data!$A$6:$A$1085,"FY25") -> 19375603 | E10: =SUMIFS(Data!$G$6:$G$1085,Data!$D$6:$D$1085,$B10,Data!$A$6:$A$1085,"FY26") -> 20552403 | F10: =(SUMIFS(Data!$R$6:$R$1085,Data!$D$6:$D$1085,$B10,Data!$A$6:$A$1085,"FY24"))/C10 -> 0.25312437 | G10: =(SUMIFS(Data!$R$6:$R$1085,Data!$D$6:$D$1085,$B10,Data!$A$6:$A$1085,"FY25"))/D10 -> 0.25195159 | H10: =(SUMIFS(Data!$R$6:$R$1085,Data!$D$6:$D$1085,$B10,Data!$A$6:$A$1085,"FY26"))/E10 -> 0.24616105 | I10: =C10/(SUMIFS(Data!$F$6:$F$1085,Data!$D$6:$D$1085,$B10,Data!$A$6:$A$1085,"FY24"))-1 -> 0.032018552 | J10: =D10/(SUMIFS(Data!$F$6:$F$1085,Data!$D$6:$D$1085,$B10,Data!$A$6:$A$1085,"FY25"))-1 -> 0.013322408 | K10: =E10/(SUMIFS(Data!$F$6:$F$1085,Data!$D$6:$D$1085,$B10,Data!$A$6:$A$1085,"FY26"))-1 -> -0.012326739
B13: Regions
B14: Segment | C14: Rev FY24 | D14: Rev FY25 | E14: Rev FY26 | F14: OM% FY24 | G14: OM% FY25 | H14: OM% FY26 | I14: Rev vs bud FY24 | J14: Rev vs bud FY25 | K14: Rev vs bud FY26
B15: UAE | C15: =SUMIFS(Data!$G$6:$G$1085,Data!$E$6:$E$1085,$B15,Data!$A$6:$A$1085,"FY24") -> 35632409 | D15: =SUMIFS(Data!$G$6:$G$1085,Data!$E$6:$E$1085,$B15,Data!$A$6:$A$1085,"FY25") -> 38447818 | E15: =SUMIFS(Data!$G$6:$G$1085,Data!$E$6:$E$1085,$B15,Data!$A$6:$A$1085,"FY26") -> 41463881 | F15: =(SUMIFS(Data!$R$6:$R$1085,Data!$E$6:$E$1085,$B15,Data!$A$6:$A$1085,"FY24"))/C15 -> 0.24091703 | G15: =(SUMIFS(Data!$R$6:$R$1085,Data!$E$6:$E$1085,$B15,Data!$A$6:$A$1085,"FY25"))/D15 -> 0.24231893 | H15: =(SUMIFS(Data!$R$6:$R$1085,Data!$E$6:$E$1085,$B15,Data!$A$6:$A$1085,"FY26"))/E15 -> 0.23956619 | I15: =C15/(SUMIFS(Data!$F$6:$F$1085,Data!$E$6:$E$1085,$B15,Data!$A$6:$A$1085,"FY24"))-1 -> 0.02286748 | J15: =D15/(SUMIFS(Data!$F$6:$F$1085,Data!$E$6:$E$1085,$B15,Data!$A$6:$A$1085,"FY25"))-1 -> 0.007035452 | K15: =E15/(SUMIFS(Data!$F$6:$F$1085,Data!$E$6:$E$1085,$B15,Data!$A$6:$A$1085,"FY26"))-1 -> -0.01913492
B16: KSA | C16: =SUMIFS(Data!$G$6:$G$1085,Data!$E$6:$E$1085,$B16,Data!$A$6:$A$1085,"FY24") -> 25147464 | D16: =SUMIFS(Data!$G$6:$G$1085,Data!$E$6:$E$1085,$B16,Data!$A$6:$A$1085,"FY25") -> 27337810 | E16: =SUMIFS(Data!$G$6:$G$1085,Data!$E$6:$E$1085,$B16,Data!$A$6:$A$1085,"FY26") -> 29043865 | F16: =(SUMIFS(Data!$R$6:$R$1085,Data!$E$6:$E$1085,$B16,Data!$A$6:$A$1085,"FY24"))/C16 -> 0.24076082 | G16: =(SUMIFS(Data!$R$6:$R$1085,Data!$E$6:$E$1085,$B16,Data!$A$6:$A$1085,"FY25"))/D16 -> 0.23061994 | H16: =(SUMIFS(Data!$R$6:$R$1085,Data!$E$6:$E$1085,$B16,Data!$A$6:$A$1085,"FY26"))/E16 -> 0.20914858 | I16: =C16/(SUMIFS(Data!$F$6:$F$1085,Data!$E$6:$E$1085,$B16,Data!$A$6:$A$1085,"FY24"))-1 -> 0.018521339 | J16: =D16/(SUMIFS(Data!$F$6:$F$1085,Data!$E$6:$E$1085,$B16,Data!$A$6:$A$1085,"FY25"))-1 -> 0.0081924225 | K16: =E16/(SUMIFS(Data!$F$6:$F$1085,Data!$E$6:$E$1085,$B16,Data!$A$6:$A$1085,"FY26"))-1 -> -0.027367782
B17: India | C17: =SUMIFS(Data!$G$6:$G$1085,Data!$E$6:$E$1085,$B17,Data!$A$6:$A$1085,"FY24") -> 29653279 | D17: =SUMIFS(Data!$G$6:$G$1085,Data!$E$6:$E$1085,$B17,Data!$A$6:$A$1085,"FY25") -> 31970185 | E17: =SUMIFS(Data!$G$6:$G$1085,Data!$E$6:$E$1085,$B17,Data!$A$6:$A$1085,"FY26") -> 34487273 | F17: =(SUMIFS(Data!$R$6:$R$1085,Data!$E$6:$E$1085,$B17,Data!$A$6:$A$1085,"FY24"))/C17 -> 0.2417103 | G17: =(SUMIFS(Data!$R$6:$R$1085,Data!$E$6:$E$1085,$B17,Data!$A$6:$A$1085,"FY25"))/D17 -> 0.2444466 | H17: =(SUMIFS(Data!$R$6:$R$1085,Data!$E$6:$E$1085,$B17,Data!$A$6:$A$1085,"FY26"))/E17 -> 0.22103716 | I17: =C17/(SUMIFS(Data!$F$6:$F$1085,Data!$E$6:$E$1085,$B17,Data!$A$6:$A$1085,"FY24"))-1 -> 0.022827997 | J17: =D17/(SUMIFS(Data!$F$6:$F$1085,Data!$E$6:$E$1085,$B17,Data!$A$6:$A$1085,"FY25"))-1 -> 0.0020348367 | K17: =E17/(SUMIFS(Data!$F$6:$F$1085,Data!$E$6:$E$1085,$B17,Data!$A$6:$A$1085,"FY26"))-1 -> -0.018936171
B18: UK | C18: =SUMIFS(Data!$G$6:$G$1085,Data!$E$6:$E$1085,$B18,Data!$A$6:$A$1085,"FY24") -> 22173019 | D18: =SUMIFS(Data!$G$6:$G$1085,Data!$E$6:$E$1085,$B18,Data!$A$6:$A$1085,"FY25") -> 23912893 | E18: =SUMIFS(Data!$G$6:$G$1085,Data!$E$6:$E$1085,$B18,Data!$A$6:$A$1085,"FY26") -> 25380235 | F18: =(SUMIFS(Data!$R$6:$R$1085,Data!$E$6:$E$1085,$B18,Data!$A$6:$A$1085,"FY24"))/C18 -> 0.2438087 | G18: =(SUMIFS(Data!$R$6:$R$1085,Data!$E$6:$E$1085,$B18,Data!$A$6:$A$1085,"FY25"))/D18 -> 0.24022091 | H18: =(SUMIFS(Data!$R$6:$R$1085,Data!$E$6:$E$1085,$B18,Data!$A$6:$A$1085,"FY26"))/E18 -> 0.23992898 | I18: =C18/(SUMIFS(Data!$F$6:$F$1085,Data!$E$6:$E$1085,$B18,Data!$A$6:$A$1085,"FY24"))-1 -> 0.017499107 | J18: =D18/(SUMIFS(Data!$F$6:$F$1085,Data!$E$6:$E$1085,$B18,Data!$A$6:$A$1085,"FY25"))-1 -> 0.00100507 | K18: =E18/(SUMIFS(Data!$F$6:$F$1085,Data!$E$6:$E$1085,$B18,Data!$A$6:$A$1085,"FY26"))-1 -> -0.0364145
B19: USA | C19: =SUMIFS(Data!$G$6:$G$1085,Data!$E$6:$E$1085,$B19,Data!$A$6:$A$1085,"FY24") -> 23577417 | D19: =SUMIFS(Data!$G$6:$G$1085,Data!$E$6:$E$1085,$B19,Data!$A$6:$A$1085,"FY25") -> 25539185 | E19: =SUMIFS(Data!$G$6:$G$1085,Data!$E$6:$E$1085,$B19,Data!$A$6:$A$1085,"FY26") -> 27640311 | F19: =(SUMIFS(Data!$R$6:$R$1085,Data!$E$6:$E$1085,$B19,Data!$A$6:$A$1085,"FY24"))/C19 -> 0.24441664 | G19: =(SUMIFS(Data!$R$6:$R$1085,Data!$E$6:$E$1085,$B19,Data!$A$6:$A$1085,"FY25"))/D19 -> 0.24231345 | H19: =(SUMIFS(Data!$R$6:$R$1085,Data!$E$6:$E$1085,$B19,Data!$A$6:$A$1085,"FY26"))/E19 -> 0.23737551 | I19: =C19/(SUMIFS(Data!$F$6:$F$1085,Data!$E$6:$E$1085,$B19,Data!$A$6:$A$1085,"FY24"))-1 -> 0.016114681 | J19: =D19/(SUMIFS(Data!$F$6:$F$1085,Data!$E$6:$E$1085,$B19,Data!$A$6:$A$1085,"FY25"))-1 -> 0.0016516013 | K19: =E19/(SUMIFS(Data!$F$6:$F$1085,Data!$E$6:$E$1085,$B19,Data!$A$6:$A$1085,"FY26"))-1 -> -0.018275359
B20: Singapore | C20: =SUMIFS(Data!$G$6:$G$1085,Data!$E$6:$E$1085,$B20,Data!$A$6:$A$1085,"FY24") -> 11821917 | D20: =SUMIFS(Data!$G$6:$G$1085,Data!$E$6:$E$1085,$B20,Data!$A$6:$A$1085,"FY25") -> 12768179 | E20: =SUMIFS(Data!$G$6:$G$1085,Data!$E$6:$E$1085,$B20,Data!$A$6:$A$1085,"FY26") -> 13720590 | F20: =(SUMIFS(Data!$R$6:$R$1085,Data!$E$6:$E$1085,$B20,Data!$A$6:$A$1085,"FY24"))/C20 -> 0.24280512 | G20: =(SUMIFS(Data!$R$6:$R$1085,Data!$E$6:$E$1085,$B20,Data!$A$6:$A$1085,"FY25"))/D20 -> 0.23866074 | H20: =(SUMIFS(Data!$R$6:$R$1085,Data!$E$6:$E$1085,$B20,Data!$A$6:$A$1085,"FY26"))/E20 -> 0.23883769 | I20: =C20/(SUMIFS(Data!$F$6:$F$1085,Data!$E$6:$E$1085,$B20,Data!$A$6:$A$1085,"FY24"))-1 -> 0.018701955 | J20: =D20/(SUMIFS(Data!$F$6:$F$1085,Data!$E$6:$E$1085,$B20,Data!$A$6:$A$1085,"FY25"))-1 -> 0.0040546158 | K20: =E20/(SUMIFS(Data!$F$6:$F$1085,Data!$E$6:$E$1085,$B20,Data!$A$6:$A$1085,"FY26"))-1 -> -0.025498732

Sheet Data
B1: Source data & variance engine
B2: 1,080 monthly rows = 5 business units × 6 regions × 36 months. Blue = source inputs; black = formulas. Adverse flag = operating income >15% below budget.
A5: FY | B5: Quarter | C5: Month | D5: Business Unit | E5: Region | F5: Revenue Budget | G5: Revenue Actual | H5: Direct Cost Budget | I5: Direct Cost Actual | J5: Opex Budget | K5: Opex Actual | L5: Headcount | M5: Revenue Var | N5: Revenue Var % | O5: Gross Profit Actual | P5: Gross Profit Budget | Q5: Op Income Budget | R5: Op Income Actual | S5: Op Income Var | T5: Op Income Var % | U5: Flag
A6: FY24 | B6: Q1 | C6: 45017 | D6: Banking & Financial Services | E6: UAE | F6: 806311 | G6: 811009 | H6: 463226 | I6: 454027 | J6: 131832 | K6: 140608 | L6: 56.2 | M6: =G6-F6 -> 4698 | N6: =IF(F6=0,0,M6/F6) -> 0.0058265359 | O6: =G6-I6 -> 356982 | P6: =F6-H6 -> 343085 | Q6: =F6-H6-J6 -> 211253 | R6: =G6-I6-K6 -> 216374 | S6: =R6-Q6 -> 5121 | T6: =IF(Q6=0,0,S6/Q6) -> 0.024241076 | U6: =IF(AND(Q6>0,T6<-0.15),"ADVERSE","")
A7: FY24 | B7: Q1 | C7: 45047 | D7: Banking & Financial Services | E7: UAE | F7: 800782 | G7: 823273 | H7: 460049 | I7: 475383 | J7: 130928 | K7: 134518 | L7: 55.8 | M7: =G7-F7 -> 22491 | N7: =IF(F7=0,0,M7/F7) -> 0.028086296 | O7: =G7-I7 -> 347890 | P7: =F7-H7 -> 340733 | Q7: =F7-H7-J7 -> 209805 | R7: =G7-I7-K7 -> 213372 | S7: =R7-Q7 -> 3567 | T7: =IF(Q7=0,0,S7/Q7) -> 0.017001501 | U7: =IF(AND(Q7>0,T7<-0.15),"ADVERSE","")
A8: FY24 | B8: Q1 | C8: 45078 | D8: Banking & Financial Services | E8: UAE | F8: 830929 | G8: 876235 | H8: 477369 | I8: 503386 | J8: 135857 | K8: 144129 | L8: 56.5 | M8: =G8-F8 -> 45306 | N8: =IF(F8=0,0,M8/F8) -> 0.054524514 | O8: =G8-I8 -> 372849 | P8: =F8-H8 -> 353560 | Q8: =F8-H8-J8 -> 217703 | R8: =G8-I8-K8 -> 228720 | S8: =R8-Q8 -> 11017 | T8: =IF(Q8=0,0,S8/Q8) -> 0.050605642 | U8: =IF(AND(Q8>0,T8<-0.15),"ADVERSE","")
A9: FY24 | B9: Q2 | C9: 45108 | D9: Banking & Financial Services | E9: UAE | F9: 838751 | G9: 850695 | H9: 481862 | I9: 492881 | J9: 137136 | K9: 139699 | L9: 55.5 | M9: =G9-F9 -> 11944 | N9: =IF(F9=0,0,M9/F9) -> 0.014240221 | O9: =G9-I9 -> 357814 | P9: =F9-H9 -> 356889 | Q9: =F9-H9-J9 -> 219753 | R9: =G9-I9-K9 -> 218115 | S9: =R9-Q9 -> -1638 | T9: =IF(Q9=0,0,S9/Q9) -> -0.0074538232 | U9: =IF(AND(Q9>0,T9<-0.15),"ADVERSE","")
A10: FY24 | B10: Q2 | C10: 45139 | D10: Banking & Financial Services | E10: UAE | F10: 821552 | G10: 827251 | H10: 471982 | I10: 474132 | J10: 134324 | K10: 135758 | L10: 57.5 | M10: =G10-F10 -> 5699 | N10: =IF(F10=0,0,M10/F10) -> 0.0069368707 | O10: =G10-I10 -> 353119 | P10: =F10-H10 -> 349570 | Q10: =F10-H10-J10 -> 215246 | R10: =G10-I10-K10 -> 217361 | S10: =R10-Q10 -> 2115 | T10: =IF(Q10=0,0,S10/Q10) -> 0.0098259666 | U10: =IF(AND(Q10>0,T10<-0.15),"ADVERSE","")
A11: FY24 | B11: Q2 | C11: 45170 | D11: Banking & Financial Services | E11: UAE | F11: 834133 | G11: 919880 | H11: 479209 | I11: 538853 | J11: 136381 | K11: 144991 | L11: 57.5 | M11: =G11-F11 -> 85747 | N11: =IF(F11=0,0,M11/F11) -> 0.10279776 | O11: =G11-I11 -> 381027 | P11: =F11-H11 -> 354924 | Q11: =F11-H11-J11 -> 218543 | R11: =G11-I11-K11 -> 236036 | S11: =R11-Q11 -> 17493 | T11: =IF(Q11=0,0,S11/Q11) -> 0.080043744 | U11: =IF(AND(Q11>0,T11<-0.15),"ADVERSE","")
A12: FY24 | B12: Q3 | C12: 45200 | D12: Banking & Financial Services | E12: UAE | F12: 884683 | G12: 860302 | H12: 508250 | I12: 500413 | J12: 144646 | K12: 147823 | L12: 56.9 | M12: =G12-F12 -> -24381 | N12: =IF(F12=0,0,M12/F12) -> -0.027559024 | O12: =G12-I12 -> 359889 | P12: =F12-H12 -> 376433 | Q12: =F12-H12-J12 -> 231787 | R12: =G12-I12-K12 -> 212066 | S12: =R12-Q12 -> -19721 | T12: =IF(Q12=0,0,S12/Q12) -> -0.085082425 | U12: =IF(AND(Q12>0,T12<-0.15),"ADVERSE","")
A13: FY24 | B13: Q3 | C13: 45231 | D13: Banking & Financial Services | E13: UAE | F13: 867436 | G13: 916151 | H13: 498342 | I13: 523434 | J13: 141826 | K13: 153949 | L13: 58.8 | M13: =G13-F13 -> 48715 | N13: =IF(F13=0,0,M13/F13) -> 0.056159763 | O13: =G13-I13 -> 392717 | P13: =F13-H13 -> 369094 | Q13: =F13-H13-J13 -> 227268 | R13: =G13-I13-K13 -> 238768 | S13: =R13-Q13 -> 11500 | T13: =IF(Q13=0,0,S13/Q13) -> 0.050601053 | U13: =IF(AND(Q13>0,T13<-0.15),"ADVERSE","")
A14: FY24 | B14: Q3 | C14: 45261 | D14: Banking & Financial Services | E14: UAE | F14: 856916 | G14: 889814 | H14: 492298 | I14: 505764 | J14: 140106 | K14: 154530 | L14: 58.8 | M14: =G14-F14 -> 32898 | N14: =IF(F14=0,0,M14/F14) -> 0.038391161 | O14: =G14-I14 -> 384050 | P14: =F14-H14 -> 364618 | Q14: =F14-H14-J14 -> 224512 | R14: =G14-I14-K14 -> 229520 | S14: =R14-Q14 -> 5008 | T14: =IF(Q14=0,0,S14/Q14) -> 0.022306157 | U14: =IF(AND(Q14>0,T14<-0.15),"ADVERSE","")
A15: FY24 | B15: Q4 | C15: 45292 | D15: Banking & Financial Services | E15: UAE | F15: 862191 | G15: 884908 | H15: 495329 | I15: 503046 | J15: 140968 | K15: 159599 | L15: 61.4 | M15: =G15-F15 -> 22717 | N15: =IF(F15=0,0,M15/F15) -> 0.02634799 | O15: =G15-I15 -> 381862 | P15: =F15-H15 -> 366862 | Q15: =F15-H15-J15 -> 225894 | R15: =G15-I15-K15 -> 222263 | S15: =R15-Q15 -> -3631 | T15: =IF(Q15=0,0,S15/Q15) -> -0.016073911 | U15: =IF(AND(Q15>0,T15<-0.15),"ADVERSE","")
A16: FY24 | B16: Q4 | C16: 45323 | D16: Banking & Financial Services | E16: UAE | F16: 867025 | G16: 928102 | H16: 498106 | I16: 528730 | J16: 141759 | K16: 158675 | L16: 58.6 | M16: =G16-F16 -> 61077 | N16: =IF(F16=0,0,M16/F16) -> 0.070444336 | O16: =G16-I16 -> 399372 | P16: =F16-H16 -> 368919 | Q16: =F16-H16-J16 -> 227160 | R16: =G16-I16-K16 -> 240697 | S16: =R16-Q16 -> 13537 | T16: =IF(Q16=0,0,S16/Q16) -> 0.059592358 | U16: =IF(AND(Q16>0,T16<-0.15),"ADVERSE","")
A17: FY24 | B17: Q4 | C17: 45352 | D17: Banking & Financial Services | E17: UAE | F17: 935509 | G17: 956172 | H17: 537450 | I17: 551970 | J17: 152956 | K17: 165158 | L17: 58.8 | M17: =G17-F17 -> 20663 | N17: =IF(F17=0,0,M17/F17) -> 0.022087441 | O17: =G17-I17 -> 404202 | P17: =F17-H17 -> 398059 | Q17: =F17-H17-J17 -> 245103 | R17: =G17-I17-K17 -> 239044 | S17: =R17-Q17 -> -6059 | T17: =IF(Q17=0,0,S17/Q17) -> -0.02472022 | U17: =IF(AND(Q17>0,T17<-0.15),"ADVERSE","")
... A1085: FY26 | B1085: Q4 | C1085: 46082 | D1085: Public Sector & Utilities | E1085: Singapore | F1085: 153711 | G1085: 151566 | H1085: 92150 | I1085: 91201 | J1085: 22057 | K1085: 22637 | L1085: 6.5 | M1085: =G1085-F1085 -> -2145 | N1085: =IF(F1085=0,0,M1085/F1085) -> -0.013954759 | O1085: =G1085-I1085 -> 60365 | P1085: =F1085-H1085 -> 61561 | Q1085: =F1085-H1085-J1085 -> 39504 | R1085: =G1085-I1085-K1085 -> 37728 | S1085: =R1085-Q1085 -> -1776 | T1085: =IF(Q1085=0,0,S1085/Q1085) -> -0.044957473 | U1085: =IF(AND(Q1085>0,T1085<-0.15),"ADVERSE","")

Sheet KPI_Dictionary
B1: KPI dictionary & definitions
B2: Every KPI in this pack, how it is calculated and why it matters
B4: KPI | C4: Definition / formula | D4: Why it matters | E4: Source
B5: Revenue | C5: Sum of monthly actual revenue for the fiscal year (Apr–Mar). | D5: Top-line growth and scale. | E5: Data!G
B6: Gross profit / margin % | C6: Revenue − direct cost; margin = GP ÷ revenue. | D6: Delivery efficiency; first line of defence on pricing and utilisation. | E6: Data!O
B7: Operating income / margin % | C7: Revenue − direct cost − operating expenses; margin = OI ÷ revenue. | D7: Core profitability after overheads. | E7: Data!R
B8: Variance / Var % | C8: Actual − budget; Var % = variance ÷ budget. | D8: Positive = favourable for revenue and profit lines. | E8: Exec_Summary
B9: RAG status | C9: On track if variance ≥ threshold (default −2%); Watch if ≥ −5%; else Off track. Margin RAG uses percentage points. | D9: Focus management attention; thresholds are editable inputs. | E9: Exec_Summary!C5:F6
B10: Revenue per head | C10: Revenue ÷ average monthly headcount, shown in $K. | D10: Productivity and pricing power. | E10: Data!L
B11: Forecast accuracy (1 − WAPE) | C11: 1 − Σ|actual − budget| ÷ Σ budget across the 30 BU × region cells. | D11: Quality of the budgeting process, independent of offsetting errors. | E11: Heatmap
B12: Adverse cell-month | C12: A BU-region-month where operating income is >15% below budget (and budget OI > 0). | D12: Early-warning indicator of control drift. | E12: Data!U
B13: Volume effect | C13: (Rev actual − Rev budget) × budget OI margin before rate changes. | D13: Isolates how much of the OI gap is simply revenue shortfall / outperformance. | E13: Bridge
B14: Direct-cost rate effect | C14: −Rev actual × (actual direct-cost % − budget direct-cost %). | D14: Pricing, utilisation, wage inflation, subcontract costs. | E14: Bridge
B15: Opex rate effect | C15: −Rev actual × (actual opex % − budget opex %). | D15: Overhead discipline. | E15: Bridge

Sheet Checks
B1: Model integrity checks
B2: Every check must show PASS. Tolerance is $1 (the FM tie-out allows $25 for unit rounding in the revenue build).
B4: Overall status | C4: =IF(COUNTIF(F8:F16,"FAIL")=0,"ALL CHECKS PASS","CHECK FAILURES") -> ALL CHECKS PASS
B7: Check | C7: Value A | D7: Value B | E7: Difference | F7: Result
B8: Data rows loaded (expected 1,080) | C8: =COUNTA(Data!$A$6:$A$1085) -> 1080 | D8: 1080 | E8: =C8-D8 -> 0 | F8: =IF(ABS(E8)<=1,"PASS","FAIL") -> PASS
B9: Business-unit revenue total = headline revenue | C9: =Exec_Summary!C26 -> 171736155 | D9: =Exec_Summary!C10 -> 171736155 | E9: =C9-D9 -> 0 | F9: =IF(ABS(E9)<=1,"PASS","FAIL") -> PASS
B10: Regional revenue total = headline revenue | C10: =Exec_Summary!C36 -> 171736155 | D10: =Exec_Summary!C10 -> 171736155 | E10: =C10-D10 -> 0 | F10: =IF(ABS(E10)<=1,"PASS","FAIL") -> PASS
B11: Heatmap grand total = headline revenue | C11: =Heatmap!I26 -> 171736155 | D11: =Exec_Summary!C10 -> 171736155 | E11: =C11-D11 -> 0 | F11: =IF(ABS(E11)<=1,"PASS","FAIL") -> PASS
B12: Bridge reconciles: budget OI + effects = actual OI | C12: =Bridge!C10 -> 39558377 | D12: =Exec_Summary!C12 -> 39558377 | E12: =C12-D12 -> 0 | F12: =IF(ABS(E12)<=1,"PASS","FAIL") -> PASS
B13: Bridge by-BU check column sums to zero | C13: =Bridge!N20 -> 0 | D13: 0 | E13: =C13-D13 -> 0 | F13: =IF(ABS(E13)<=1,"PASS","FAIL") -> PASS
B14: Monthly trend full-year revenue = headline revenue | C14: =Monthly_Trend!D18 -> 171736155 | D14: =Exec_Summary!C10 -> 171736155 | E14: =C14-D14 -> 0 | F14: =IF(ABS(E14)<=1,"PASS","FAIL") -> PASS
B15: All-year revenue by FY = all rows total | C15: =SUM(SUMIFS(Data!$G$6:$G$1085,Data!$A$6:$A$1085,"FY24"),SUMIFS(Data!$G$6:$G$1085,Data!$A$6:$A$1085,"FY25"),SUMIFS(Data!$G$6:$G$1085,Data!$A$6:$A$1085,"FY26")) -> 479717730 | D15: =SUM(Data!$G$6:$G$1085) -> 479717730 | E15: =C15-D15 -> 0 | F15: =IF(ABS(E15)<=1,"PASS","FAIL") -> PASS
B16: Revenue ties to Integrated_Financial_Model (selected FY) | C16: =Exec_Summary!C10 -> 171736155 | D16: =INDEX(C21:E21,MATCH(Exec_Summary!C4,C20:E20,0)) -> 171736155 | E16: =C16-D16 -> 0 | F16: =IF(ABS(E16)<=25,"PASS","FAIL") -> PASS
B19: Reference: revenue per Integrated_Financial_Model.xlsx (03_Revenue_Build)
B20: Item | C20: FY24 | D20: FY25 | E20: FY26
B21: Revenue (USD) | C21: 148005508 | D21: 159976068 | E21: 171736155
