Workbook

Sheet Exec_Summary
B1: Meridian Gulf Trading LLC — UAE VAT Compliance Pack
B2: Illustrative UAE taxable person · calendar 2025 · AED · quarterly VAT 201 returns · change the period in C4
B4: Return period ▸ | C4: FY2025 | E4: Quarter key | F4: =IF(C4="FY2025","*",LEFT(C4,2)) -> * | H4: Model status | I4: =Checks!C4 -> ALL CHECKS PASS
B6: 1 · HEADLINE KPIs (selected period)
B7: Total sales (net of VAT) | C7: =SUMIFS(Register!$G$6:$G$1255,Register!$F$6:$F$1255,"Standard-rated 5%",Register!$C$6:$C$1255,"Sales",Register!$K$6:$K$1255,Exec_Summary!$F$4)+SUMIFS(Register!$G$6:$G$1255,Register!$F$6:$F$1255,"Zero-rated export",Register!$K$6:$K$1255,Exec_Summary!$F$4)+SUMIFS(Register!$G$6:$G$1255,Register!$F$6:$F$1255,"Exempt (residential/financial)",Register!$K$6:$K$1255,Exec_Summary!$F$4)+SUMIFS(Register!$G$6:$G$1255,Register!$F$6:$F$1255,"Out of scope",Register!$K$6:$K$1255,Exec_Summary!$F$4) -> 36275033 | D7: standard + zero-rated + exempt + out of scope
B8: Standard-rated sales | C8: =SUMIFS(Register!$G$6:$G$1255,Register!$F$6:$F$1255,"Standard-rated 5%",Register!$C$6:$C$1255,"Sales",Register!$K$6:$K$1255,Exec_Summary!$F$4) -> 27542550
B9: Zero-rated exports | C9: =SUMIFS(Register!$G$6:$G$1255,Register!$F$6:$F$1255,"Zero-rated export",Register!$K$6:$K$1255,Exec_Summary!$F$4) -> 6427195.1 | E9: =IF(C7=0,0,C9/C7) -> 0.17717958 | F9: of sales
B10: Output VAT (standard-rated sales) | C10: =SUMIFS(Register!$M$6:$M$1255,Register!$K$6:$K$1255,Exec_Summary!$F$4) -> 1377127.6
B11: Output VAT — reverse charge (self-assessed) | C11: =SUMIFS(Register!$N$6:$N$1255,Register!$K$6:$K$1255,Exec_Summary!$F$4) -> 76877.93
B12: Input VAT recovered (incl. reverse charge) | C12: =SUMIFS(Register!$O$6:$O$1255,Register!$K$6:$K$1255,Exec_Summary!$F$4) -> 1276219.1
B13: NET VAT PAYABLE / (REFUNDABLE) | C13: =C10+C11-C12 -> 177786.43 | D13: positive = pay FTA · negative = refund claim | E13: =IF(C13>=0,"● Payable to FTA","● Refund position") -> ● Payable to FTA
B14: Input VAT not recoverable (blocked / no TRN) | C14: =SUMIFS(Register!$P$6:$P$1255,Register!$K$6:$K$1255,Exec_Summary!$F$4) -> 39770.56 | D14: cost leakage
B15: Input VAT recovery rate | C15: =IF((C12+C14)=0,0,C12/(C12+C14)) -> 0.96977897 | D15: recovered ÷ total input VAT incurred
B16: Effective VAT rate on total sales | C16: =IF(C7=0,0,C10/C7) -> 0.03796351 | D16: output VAT ÷ total sales (5% if all standard-rated)
B17: Compliance exceptions (documents) | C17: =COUNTIFS(Register!$R$6:$R$1255,"?*",Register!$K$6:$K$1255,Exec_Summary!$F$4) -> 50 | D17: invalid TRN, blocked input, late posting
B19: 2 · QUARTERLY VAT SUMMARY (all periods)
B20: Quarter | C20: Standard sales | D20: Zero-rated | E20: Exempt + OOS | F20: Total sales | G20: Output VAT | H20: Reverse-charge VAT | I20: Input VAT recovered | J20: Net VAT | K20: Position
B21: Q1 | C21: =SUMIFS(Register!$G$6:$G$1255,Register!$F$6:$F$1255,"Standard-rated 5%",Register!$C$6:$C$1255,"Sales",Register!$K$6:$K$1255,$B21) -> 6933825.6 | D21: =SUMIFS(Register!$G$6:$G$1255,Register!$F$6:$F$1255,"Zero-rated export",Register!$K$6:$K$1255,$B21) -> 892629.65 | E21: =SUMIFS(Register!$G$6:$G$1255,Register!$F$6:$F$1255,"Exempt (residential/financial)",Register!$K$6:$K$1255,$B21)+SUMIFS(Register!$G$6:$G$1255,Register!$F$6:$F$1255,"Out of scope",Register!$K$6:$K$1255,$B21) -> 518212.87 | F21: =SUM(C21:E21) -> 8344668.1 | G21: =SUMIFS(Register!$M$6:$M$1255,Register!$K$6:$K$1255,$B21) -> 346691.34 | H21: =SUMIFS(Register!$N$6:$N$1255,Register!$K$6:$K$1255,$B21) -> 18243.09 | I21: =SUMIFS(Register!$O$6:$O$1255,Register!$K$6:$K$1255,$B21) -> 353182.57 | J21: =G21+H21-I21 -> 11751.86 | K21: =IF(J21>=0,"● Payable","● Refund") -> ● Payable
B22: Q2 | C22: =SUMIFS(Register!$G$6:$G$1255,Register!$F$6:$F$1255,"Standard-rated 5%",Register!$C$6:$C$1255,"Sales",Register!$K$6:$K$1255,$B22) -> 7926446.2 | D22: =SUMIFS(Register!$G$6:$G$1255,Register!$F$6:$F$1255,"Zero-rated export",Register!$K$6:$K$1255,$B22) -> 2527984.9 | E22: =SUMIFS(Register!$G$6:$G$1255,Register!$F$6:$F$1255,"Exempt (residential/financial)",Register!$K$6:$K$1255,$B22)+SUMIFS(Register!$G$6:$G$1255,Register!$F$6:$F$1255,"Out of scope",Register!$K$6:$K$1255,$B22) -> 563490.4 | F22: =SUM(C22:E22) -> 11017922 | G22: =SUMIFS(Register!$M$6:$M$1255,Register!$K$6:$K$1255,$B22) -> 396322.31 | H22: =SUMIFS(Register!$N$6:$N$1255,Register!$K$6:$K$1255,$B22) -> 14308.32 | I22: =SUMIFS(Register!$O$6:$O$1255,Register!$K$6:$K$1255,$B22) -> 309105 | J22: =G22+H22-I22 -> 101525.63 | K22: =IF(J22>=0,"● Payable","● Refund") -> ● Payable
B23: Q3 | C23: =SUMIFS(Register!$G$6:$G$1255,Register!$F$6:$F$1255,"Standard-rated 5%",Register!$C$6:$C$1255,"Sales",Register!$K$6:$K$1255,$B23) -> 6462263.3 | D23: =SUMIFS(Register!$G$6:$G$1255,Register!$F$6:$F$1255,"Zero-rated export",Register!$K$6:$K$1255,$B23) -> 1804587.3 | E23: =SUMIFS(Register!$G$6:$G$1255,Register!$F$6:$F$1255,"Exempt (residential/financial)",Register!$K$6:$K$1255,$B23)+SUMIFS(Register!$G$6:$G$1255,Register!$F$6:$F$1255,"Out of scope",Register!$K$6:$K$1255,$B23) -> 629890.09 | F23: =SUM(C23:E23) -> 8896740.7 | G23: =SUMIFS(Register!$M$6:$M$1255,Register!$K$6:$K$1255,$B23) -> 323113.18 | H23: =SUMIFS(Register!$N$6:$N$1255,Register!$K$6:$K$1255,$B23) -> 33655.77 | I23: =SUMIFS(Register!$O$6:$O$1255,Register!$K$6:$K$1255,$B23) -> 349684.88 | J23: =G23+H23-I23 -> 7084.07 | K23: =IF(J23>=0,"● Payable","● Refund") -> ● Payable
B24: Q4 | C24: =SUMIFS(Register!$G$6:$G$1255,Register!$F$6:$F$1255,"Standard-rated 5%",Register!$C$6:$C$1255,"Sales",Register!$K$6:$K$1255,$B24) -> 6220014.8 | D24: =SUMIFS(Register!$G$6:$G$1255,Register!$F$6:$F$1255,"Zero-rated export",Register!$K$6:$K$1255,$B24) -> 1201993.3 | E24: =SUMIFS(Register!$G$6:$G$1255,Register!$F$6:$F$1255,"Exempt (residential/financial)",Register!$K$6:$K$1255,$B24)+SUMIFS(Register!$G$6:$G$1255,Register!$F$6:$F$1255,"Out of scope",Register!$K$6:$K$1255,$B24) -> 593694.71 | F24: =SUM(C24:E24) -> 8015702.8 | G24: =SUMIFS(Register!$M$6:$M$1255,Register!$K$6:$K$1255,$B24) -> 311000.77 | H24: =SUMIFS(Register!$N$6:$N$1255,Register!$K$6:$K$1255,$B24) -> 10670.75 | I24: =SUMIFS(Register!$O$6:$O$1255,Register!$K$6:$K$1255,$B24) -> 264246.65 | J24: =G24+H24-I24 -> 57424.87 | K24: =IF(J24>=0,"● Payable","● Refund") -> ● Payable
B25: FY2025 | C25: =SUM(C21:C24) -> 27542550 | D25: =SUM(D21:D24) -> 6427195.1 | E25: =SUM(E21:E24) -> 2305288.1 | F25: =SUM(F21:F24) -> 36275033 | G25: =SUM(G21:G24) -> 1377127.6 | H25: =SUM(H21:H24) -> 76877.93 | I25: =SUM(I21:I24) -> 1276219.1 | J25: =SUM(J21:J24) -> 177786.43 | K25: =IF(J25>=0,"● Payable","● Refund") -> ● Payable
B27: 3 · KEY MESSAGES (auto-generated)
B28: ="Selected period "&C4&": total sales AED "&TEXT(C7/1000000,"0.00")&"M"&", of which "&TEXT(E9,"0.0%")&" are zero-rated exports; output VAT AED "&TEXT(C10/1000000,"0.00")&"M"&" against recoverable input VAT AED "&TEXT(C12/1000000,"0.00")&"M"&"." -> Selected period FY2025: total sales AED 36.28M, of which 17.7% are zero-rated exports; output VAT AED 1.38M against recoverable input VAT AED 1.28M.
B29: ="Net VAT position is AED "&TEXT(ABS(C13)/1000,"#,##0")&"K "&IF(C13>=0,"payable to the FTA","refundable (input VAT exceeds output VAT)")&"; effective VAT rate on sales "&TEXT(C16,"0.00%")&"." -> Net VAT position is AED 178K payable to the FTA; effective VAT rate on sales 3.80%.
B30: ="Largest quarterly payment: "&INDEX(B21:B24,MATCH(MAX(J21:J24),J21:J24,0))&" (AED "&TEXT(MAX(J21:J24)/1000,"#,##0")&"K); lowest: "&INDEX(B21:B24,MATCH(MIN(J21:J24),J21:J24,0))&" (AED "&TEXT(MIN(J21:J24)/1000,"#,##0")&"K)." -> Largest quarterly payment: Q2 (AED 102K); lowest: Q3 (AED 7K).
B31: ="Control leakage: AED "&TEXT(C14/1000,"#,##0")&"K of input VAT ("&TEXT(1-C15,"0.0%")&" of VAT incurred) was not recoverable; "&C17&" documents carry compliance exceptions (see Exceptions)." -> Control leakage: AED 40K of input VAT (3.0% of VAT incurred) was not recoverable; 50 documents carry compliance exceptions (see Exceptions).

Sheet VAT201_Return
B1: VAT 201 return — box-by-box
B2: Maps the register to the FTA return layout for the period selected on Exec_Summary!C4 (amounts net of VAT, AED)
B3: Period | C3: =Exec_Summary!C4 -> FY2025 | D3: Taxable person | E3: Meridian Gulf Trading LLC
B5: Box | C5: Description | D5: Amount (AED) | E5: VAT (AED)
B6: 1a | C6: Standard-rated supplies — Abu Dhabi | D6: =SUMIFS(Register!$G$6:$G$1255,Register!$F$6:$F$1255,"Standard-rated 5%",Register!$C$6:$C$1255,"Sales",Register!$E$6:$E$1255,"Abu Dhabi",Register!$K$6:$K$1255,Exec_Summary!$F$4) -> 7049646.1 | E6: =SUMIFS(Register!$M$6:$M$1255,Register!$E$6:$E$1255,"Abu Dhabi",Register!$K$6:$K$1255,Exec_Summary!$F$4) -> 352482.38
B7: 1b | C7: Standard-rated supplies — Dubai | D7: =SUMIFS(Register!$G$6:$G$1255,Register!$F$6:$F$1255,"Standard-rated 5%",Register!$C$6:$C$1255,"Sales",Register!$E$6:$E$1255,"Dubai",Register!$K$6:$K$1255,Exec_Summary!$F$4) -> 13379603 | E7: =SUMIFS(Register!$M$6:$M$1255,Register!$E$6:$E$1255,"Dubai",Register!$K$6:$K$1255,Exec_Summary!$F$4) -> 668980.13
B8: 1c | C8: Standard-rated supplies — Sharjah | D8: =SUMIFS(Register!$G$6:$G$1255,Register!$F$6:$F$1255,"Standard-rated 5%",Register!$C$6:$C$1255,"Sales",Register!$E$6:$E$1255,"Sharjah",Register!$K$6:$K$1255,Exec_Summary!$F$4) -> 3507187.6 | E8: =SUMIFS(Register!$M$6:$M$1255,Register!$E$6:$E$1255,"Sharjah",Register!$K$6:$K$1255,Exec_Summary!$F$4) -> 175359.4
B9: 1d | C9: Standard-rated supplies — Ajman | D9: =SUMIFS(Register!$G$6:$G$1255,Register!$F$6:$F$1255,"Standard-rated 5%",Register!$C$6:$C$1255,"Sales",Register!$E$6:$E$1255,"Ajman",Register!$K$6:$K$1255,Exec_Summary!$F$4) -> 736458.65 | E9: =SUMIFS(Register!$M$6:$M$1255,Register!$E$6:$E$1255,"Ajman",Register!$K$6:$K$1255,Exec_Summary!$F$4) -> 36822.94
B10: 1e | C10: Standard-rated supplies — Umm Al Quwain | D10: =SUMIFS(Register!$G$6:$G$1255,Register!$F$6:$F$1255,"Standard-rated 5%",Register!$C$6:$C$1255,"Sales",Register!$E$6:$E$1255,"Umm Al Quwain",Register!$K$6:$K$1255,Exec_Summary!$F$4) -> 327552.56 | E10: =SUMIFS(Register!$M$6:$M$1255,Register!$E$6:$E$1255,"Umm Al Quwain",Register!$K$6:$K$1255,Exec_Summary!$F$4) -> 16377.64
B11: 1f | C11: Standard-rated supplies — Ras Al Khaimah | D11: =SUMIFS(Register!$G$6:$G$1255,Register!$F$6:$F$1255,"Standard-rated 5%",Register!$C$6:$C$1255,"Sales",Register!$E$6:$E$1255,"Ras Al Khaimah",Register!$K$6:$K$1255,Exec_Summary!$F$4) -> 1581289.9 | E11: =SUMIFS(Register!$M$6:$M$1255,Register!$E$6:$E$1255,"Ras Al Khaimah",Register!$K$6:$K$1255,Exec_Summary!$F$4) -> 79064.48
B12: 1g | C12: Standard-rated supplies — Fujairah | D12: =SUMIFS(Register!$G$6:$G$1255,Register!$F$6:$F$1255,"Standard-rated 5%",Register!$C$6:$C$1255,"Sales",Register!$E$6:$E$1255,"Fujairah",Register!$K$6:$K$1255,Exec_Summary!$F$4) -> 960812.19 | E12: =SUMIFS(Register!$M$6:$M$1255,Register!$E$6:$E$1255,"Fujairah",Register!$K$6:$K$1255,Exec_Summary!$F$4) -> 48040.63
B13: 2 | C13: Tax refunds provided to tourists | D13: 0 | E13: 0
B14: 3 | C14: Supplies subject to reverse charge provisions | D14: =SUMIFS(Register!$G$6:$G$1255,Register!$F$6:$F$1255,"Reverse charge (imported services)",Register!$K$6:$K$1255,Exec_Summary!$F$4) -> 1537558.9 | E14: =SUMIFS(Register!$N$6:$N$1255,Register!$K$6:$K$1255,Exec_Summary!$F$4) -> 76877.93
B15: 4 | C15: Zero-rated supplies | D15: =SUMIFS(Register!$G$6:$G$1255,Register!$F$6:$F$1255,"Zero-rated export",Register!$K$6:$K$1255,Exec_Summary!$F$4) -> 6427195.1 | E15: 0
B16: 5 | C16: Exempt supplies | D16: =SUMIFS(Register!$G$6:$G$1255,Register!$F$6:$F$1255,"Exempt (residential/financial)",Register!$K$6:$K$1255,Exec_Summary!$F$4) -> 1294118.3 | E16: 0
B17: 6 | C17: Goods imported into the UAE | D17: 0 | E17: 0
B18: 7 | C18: Adjustments to goods imported | D18: 0 | E18: 0
B19: 8 | C19: TOTALS (boxes 1–7) | D19: =SUM(D6:D16)+D17+D18 -> 36801422 | E19: =SUM(E6:E18) -> 1454005.5
B21: 9 | C21: Standard-rated expenses (incl. capital assets; excl. blocked / no TRN) | D21: =SUMIFS(Register!$G$6:$G$1255,Register!$F$6:$F$1255,"Standard-rated 5%",Register!$C$6:$C$1255,"Purchase",Register!$I$6:$I$1255,"Y",Register!$K$6:$K$1255,Exec_Summary!$F$4)+SUMIFS(Register!$G$6:$G$1255,Register!$F$6:$F$1255,"Capital asset",Register!$I$6:$I$1255,"Y",Register!$K$6:$K$1255,Exec_Summary!$F$4) -> 23986823 | E21: =SUMIFS(Register!$O$6:$O$1255,Register!$F$6:$F$1255,"Standard-rated 5%",Register!$C$6:$C$1255,"Purchase",Register!$K$6:$K$1255,Exec_Summary!$F$4)+SUMIFS(Register!$O$6:$O$1255,Register!$F$6:$F$1255,"Capital asset",Register!$K$6:$K$1255,Exec_Summary!$F$4) -> 1199341.2
B22: 10 | C22: Supplies subject to reverse charge provisions | D22: =D14 -> 1537558.9 | E22: =SUMIFS(Register!$O$6:$O$1255,Register!$F$6:$F$1255,"Reverse charge (imported services)",Register!$K$6:$K$1255,Exec_Summary!$F$4) -> 76877.93
B23: 11 | C23: TOTALS (boxes 9–10) | D23: =D21+D22 -> 25524381 | E23: =E21+E22 -> 1276219.1
B25: 12 | C25: Total due tax for the period | E25: =E19 -> 1454005.5
B26: 13 | C26: Total recoverable tax for the period | E26: =E23 -> 1276219.1
B27: 14 | C27: PAYABLE TAX / (REFUNDABLE) for the period | E27: =E25-E26 -> 177786.43
C29: Memo: input VAT not recoverable (blocked entertainment / no valid TRN) | E29: =SUMIFS(Register!$P$6:$P$1255,Register!$K$6:$K$1255,Exec_Summary!$F$4) -> 39770.56
C30: Memo: reconciliation to Exec_Summary net VAT (should be 0) | E30: =ROUND(E27-Exec_Summary!C13,2) -> 0

Sheet Monthly_Trend
B1: Monthly VAT trend — 2025
B2: Output VAT, recoverable input VAT and net position by month
B5: Month | C5: Total sales | D5: Output VAT | E5: Reverse-charge VAT | F5: Input VAT recovered | G5: Net VAT | H5: Documents
B6: =DATE(2025,1,1) -> 45658 | C6: =SUMIFS(Register!$G$6:$G$1255,Register!$C$6:$C$1255,"Sales",Register!$B$6:$B$1255,">="&$B6,Register!$B$6:$B$1255,"<"&EDATE($B6,1)) -> 2417900.6 | D6: =SUMIFS(Register!$M$6:$M$1255,Register!$B$6:$B$1255,">="&$B6,Register!$B$6:$B$1255,"<"&EDATE($B6,1)) -> 103832.79 | E6: =SUMIFS(Register!$N$6:$N$1255,Register!$B$6:$B$1255,">="&$B6,Register!$B$6:$B$1255,"<"&EDATE($B6,1)) -> 9045.61 | F6: =SUMIFS(Register!$O$6:$O$1255,Register!$B$6:$B$1255,">="&$B6,Register!$B$6:$B$1255,"<"&EDATE($B6,1)) -> 84703.02 | G6: =D6+E6-F6 -> 28175.38 | H6: =COUNTIFS(Register!$B$6:$B$1255,">="&$B6,Register!$B$6:$B$1255,"<"&EDATE($B6,1)) -> 113
B7: =EDATE(B6,1) -> 45689 | C7: =SUMIFS(Register!$G$6:$G$1255,Register!$C$6:$C$1255,"Sales",Register!$B$6:$B$1255,">="&$B7,Register!$B$6:$B$1255,"<"&EDATE($B7,1)) -> 2660923.6 | D7: =SUMIFS(Register!$M$6:$M$1255,Register!$B$6:$B$1255,">="&$B7,Register!$B$6:$B$1255,"<"&EDATE($B7,1)) -> 105333.72 | E7: =SUMIFS(Register!$N$6:$N$1255,Register!$B$6:$B$1255,">="&$B7,Register!$B$6:$B$1255,"<"&EDATE($B7,1)) -> 5265.89 | F7: =SUMIFS(Register!$O$6:$O$1255,Register!$B$6:$B$1255,">="&$B7,Register!$B$6:$B$1255,"<"&EDATE($B7,1)) -> 97182.89 | G7: =D7+E7-F7 -> 13416.72 | H7: =COUNTIFS(Register!$B$6:$B$1255,">="&$B7,Register!$B$6:$B$1255,"<"&EDATE($B7,1)) -> 95
B8: =EDATE(B7,1) -> 45717 | C8: =SUMIFS(Register!$G$6:$G$1255,Register!$C$6:$C$1255,"Sales",Register!$B$6:$B$1255,">="&$B8,Register!$B$6:$B$1255,"<"&EDATE($B8,1)) -> 3265843.9 | D8: =SUMIFS(Register!$M$6:$M$1255,Register!$B$6:$B$1255,">="&$B8,Register!$B$6:$B$1255,"<"&EDATE($B8,1)) -> 137524.83 | E8: =SUMIFS(Register!$N$6:$N$1255,Register!$B$6:$B$1255,">="&$B8,Register!$B$6:$B$1255,"<"&EDATE($B8,1)) -> 3931.59 | F8: =SUMIFS(Register!$O$6:$O$1255,Register!$B$6:$B$1255,">="&$B8,Register!$B$6:$B$1255,"<"&EDATE($B8,1)) -> 171296.66 | G8: =D8+E8-F8 -> -29840.24 | H8: =COUNTIFS(Register!$B$6:$B$1255,">="&$B8,Register!$B$6:$B$1255,"<"&EDATE($B8,1)) -> 123
B9: =EDATE(B8,1) -> 45748 | C9: =SUMIFS(Register!$G$6:$G$1255,Register!$C$6:$C$1255,"Sales",Register!$B$6:$B$1255,">="&$B9,Register!$B$6:$B$1255,"<"&EDATE($B9,1)) -> 3660039 | D9: =SUMIFS(Register!$M$6:$M$1255,Register!$B$6:$B$1255,">="&$B9,Register!$B$6:$B$1255,"<"&EDATE($B9,1)) -> 150584.77 | E9: =SUMIFS(Register!$N$6:$N$1255,Register!$B$6:$B$1255,">="&$B9,Register!$B$6:$B$1255,"<"&EDATE($B9,1)) -> 7592.59 | F9: =SUMIFS(Register!$O$6:$O$1255,Register!$B$6:$B$1255,">="&$B9,Register!$B$6:$B$1255,"<"&EDATE($B9,1)) -> 85548.19 | G9: =D9+E9-F9 -> 72629.17 | H9: =COUNTIFS(Register!$B$6:$B$1255,">="&$B9,Register!$B$6:$B$1255,"<"&EDATE($B9,1)) -> 108
B10: =EDATE(B9,1) -> 45778 | C10: =SUMIFS(Register!$G$6:$G$1255,Register!$C$6:$C$1255,"Sales",Register!$B$6:$B$1255,">="&$B10,Register!$B$6:$B$1255,"<"&EDATE($B10,1)) -> 3730667.5 | D10: =SUMIFS(Register!$M$6:$M$1255,Register!$B$6:$B$1255,">="&$B10,Register!$B$6:$B$1255,"<"&EDATE($B10,1)) -> 122145.02 | E10: =SUMIFS(Register!$N$6:$N$1255,Register!$B$6:$B$1255,">="&$B10,Register!$B$6:$B$1255,"<"&EDATE($B10,1)) -> 5819.31 | F10: =SUMIFS(Register!$O$6:$O$1255,Register!$B$6:$B$1255,">="&$B10,Register!$B$6:$B$1255,"<"&EDATE($B10,1)) -> 154631.07 | G10: =D10+E10-F10 -> -26666.74 | H10: =COUNTIFS(Register!$B$6:$B$1255,">="&$B10,Register!$B$6:$B$1255,"<"&EDATE($B10,1)) -> 116
B11: =EDATE(B10,1) -> 45809 | C11: =SUMIFS(Register!$G$6:$G$1255,Register!$C$6:$C$1255,"Sales",Register!$B$6:$B$1255,">="&$B11,Register!$B$6:$B$1255,"<"&EDATE($B11,1)) -> 3627215 | D11: =SUMIFS(Register!$M$6:$M$1255,Register!$B$6:$B$1255,">="&$B11,Register!$B$6:$B$1255,"<"&EDATE($B11,1)) -> 123592.52 | E11: =SUMIFS(Register!$N$6:$N$1255,Register!$B$6:$B$1255,">="&$B11,Register!$B$6:$B$1255,"<"&EDATE($B11,1)) -> 896.42 | F11: =SUMIFS(Register!$O$6:$O$1255,Register!$B$6:$B$1255,">="&$B11,Register!$B$6:$B$1255,"<"&EDATE($B11,1)) -> 68925.74 | G11: =D11+E11-F11 -> 55563.2 | H11: =COUNTIFS(Register!$B$6:$B$1255,">="&$B11,Register!$B$6:$B$1255,"<"&EDATE($B11,1)) -> 88
B12: =EDATE(B11,1) -> 45839 | C12: =SUMIFS(Register!$G$6:$G$1255,Register!$C$6:$C$1255,"Sales",Register!$B$6:$B$1255,">="&$B12,Register!$B$6:$B$1255,"<"&EDATE($B12,1)) -> 3173938.9 | D12: =SUMIFS(Register!$M$6:$M$1255,Register!$B$6:$B$1255,">="&$B12,Register!$B$6:$B$1255,"<"&EDATE($B12,1)) -> 109274.07 | E12: =SUMIFS(Register!$N$6:$N$1255,Register!$B$6:$B$1255,">="&$B12,Register!$B$6:$B$1255,"<"&EDATE($B12,1)) -> 2531.61 | F12: =SUMIFS(Register!$O$6:$O$1255,Register!$B$6:$B$1255,">="&$B12,Register!$B$6:$B$1255,"<"&EDATE($B12,1)) -> 124225.64 | G12: =D12+E12-F12 -> -12419.96 | H12: =COUNTIFS(Register!$B$6:$B$1255,">="&$B12,Register!$B$6:$B$1255,"<"&EDATE($B12,1)) -> 106
B13: =EDATE(B12,1) -> 45870 | C13: =SUMIFS(Register!$G$6:$G$1255,Register!$C$6:$C$1255,"Sales",Register!$B$6:$B$1255,">="&$B13,Register!$B$6:$B$1255,"<"&EDATE($B13,1)) -> 3095598.3 | D13: =SUMIFS(Register!$M$6:$M$1255,Register!$B$6:$B$1255,">="&$B13,Register!$B$6:$B$1255,"<"&EDATE($B13,1)) -> 127128.65 | E13: =SUMIFS(Register!$N$6:$N$1255,Register!$B$6:$B$1255,">="&$B13,Register!$B$6:$B$1255,"<"&EDATE($B13,1)) -> 27156.39 | F13: =SUMIFS(Register!$O$6:$O$1255,Register!$B$6:$B$1255,">="&$B13,Register!$B$6:$B$1255,"<"&EDATE($B13,1)) -> 123453 | G13: =D13+E13-F13 -> 30832.04 | H13: =COUNTIFS(Register!$B$6:$B$1255,">="&$B13,Register!$B$6:$B$1255,"<"&EDATE($B13,1)) -> 107
B14: =EDATE(B13,1) -> 45901 | C14: =SUMIFS(Register!$G$6:$G$1255,Register!$C$6:$C$1255,"Sales",Register!$B$6:$B$1255,">="&$B14,Register!$B$6:$B$1255,"<"&EDATE($B14,1)) -> 2627203.5 | D14: =SUMIFS(Register!$M$6:$M$1255,Register!$B$6:$B$1255,">="&$B14,Register!$B$6:$B$1255,"<"&EDATE($B14,1)) -> 86710.46 | E14: =SUMIFS(Register!$N$6:$N$1255,Register!$B$6:$B$1255,">="&$B14,Register!$B$6:$B$1255,"<"&EDATE($B14,1)) -> 3967.77 | F14: =SUMIFS(Register!$O$6:$O$1255,Register!$B$6:$B$1255,">="&$B14,Register!$B$6:$B$1255,"<"&EDATE($B14,1)) -> 102006.24 | G14: =D14+E14-F14 -> -11328.01 | H14: =COUNTIFS(Register!$B$6:$B$1255,">="&$B14,Register!$B$6:$B$1255,"<"&EDATE($B14,1)) -> 94
B15: =EDATE(B14,1) -> 45931 | C15: =SUMIFS(Register!$G$6:$G$1255,Register!$C$6:$C$1255,"Sales",Register!$B$6:$B$1255,">="&$B15,Register!$B$6:$B$1255,"<"&EDATE($B15,1)) -> 2878154.2 | D15: =SUMIFS(Register!$M$6:$M$1255,Register!$B$6:$B$1255,">="&$B15,Register!$B$6:$B$1255,"<"&EDATE($B15,1)) -> 117219.47 | E15: =SUMIFS(Register!$N$6:$N$1255,Register!$B$6:$B$1255,">="&$B15,Register!$B$6:$B$1255,"<"&EDATE($B15,1)) -> 4003.32 | F15: =SUMIFS(Register!$O$6:$O$1255,Register!$B$6:$B$1255,">="&$B15,Register!$B$6:$B$1255,"<"&EDATE($B15,1)) -> 88538.42 | G15: =D15+E15-F15 -> 32684.37 | H15: =COUNTIFS(Register!$B$6:$B$1255,">="&$B15,Register!$B$6:$B$1255,"<"&EDATE($B15,1)) -> 94
B16: =EDATE(B15,1) -> 45962 | C16: =SUMIFS(Register!$G$6:$G$1255,Register!$C$6:$C$1255,"Sales",Register!$B$6:$B$1255,">="&$B16,Register!$B$6:$B$1255,"<"&EDATE($B16,1)) -> 2474655.7 | D16: =SUMIFS(Register!$M$6:$M$1255,Register!$B$6:$B$1255,">="&$B16,Register!$B$6:$B$1255,"<"&EDATE($B16,1)) -> 101833.62 | E16: =SUMIFS(Register!$N$6:$N$1255,Register!$B$6:$B$1255,">="&$B16,Register!$B$6:$B$1255,"<"&EDATE($B16,1)) -> 3379.06 | F16: =SUMIFS(Register!$O$6:$O$1255,Register!$B$6:$B$1255,">="&$B16,Register!$B$6:$B$1255,"<"&EDATE($B16,1)) -> 107341.65 | G16: =D16+E16-F16 -> -2128.97 | H16: =COUNTIFS(Register!$B$6:$B$1255,">="&$B16,Register!$B$6:$B$1255,"<"&EDATE($B16,1)) -> 106
B17: =EDATE(B16,1) -> 45992 | C17: =SUMIFS(Register!$G$6:$G$1255,Register!$C$6:$C$1255,"Sales",Register!$B$6:$B$1255,">="&$B17,Register!$B$6:$B$1255,"<"&EDATE($B17,1)) -> 2662892.9 | D17: =SUMIFS(Register!$M$6:$M$1255,Register!$B$6:$B$1255,">="&$B17,Register!$B$6:$B$1255,"<"&EDATE($B17,1)) -> 91947.68 | E17: =SUMIFS(Register!$N$6:$N$1255,Register!$B$6:$B$1255,">="&$B17,Register!$B$6:$B$1255,"<"&EDATE($B17,1)) -> 3288.37 | F17: =SUMIFS(Register!$O$6:$O$1255,Register!$B$6:$B$1255,">="&$B17,Register!$B$6:$B$1255,"<"&EDATE($B17,1)) -> 68366.58 | G17: =D17+E17-F17 -> 26869.47 | H17: =COUNTIFS(Register!$B$6:$B$1255,">="&$B17,Register!$B$6:$B$1255,"<"&EDATE($B17,1)) -> 100
B18: Total | C18: =SUM(C6:C17) -> 36275033 | D18: =SUM(D6:D17) -> 1377127.6 | E18: =SUM(E6:E17) -> 76877.93 | F18: =SUM(F6:F17) -> 1276219.1 | G18: =SUM(G6:G17) -> 177786.43 | H18: =SUM(H6:H17) -> 1250

Sheet Emirate_Split
B1: Standard-rated sales by emirate (VAT 201 boxes 1a–1g)
B2: Full-year 2025 · AED · supports place-of-supply review
B5: Emirate | C5: Q1 | D5: Q2 | E5: Q3 | F5: Q4 | G5: FY2025 | H5: Share
B6: Dubai | C6: =SUMIFS(Register!$G$6:$G$1255,Register!$F$6:$F$1255,"Standard-rated 5%",Register!$C$6:$C$1255,"Sales",Register!$E$6:$E$1255,$B6,Register!$K$6:$K$1255,"Q1") -> 2878250.7 | D6: =SUMIFS(Register!$G$6:$G$1255,Register!$F$6:$F$1255,"Standard-rated 5%",Register!$C$6:$C$1255,"Sales",Register!$E$6:$E$1255,$B6,Register!$K$6:$K$1255,"Q2") -> 3301520.6 | E6: =SUMIFS(Register!$G$6:$G$1255,Register!$F$6:$F$1255,"Standard-rated 5%",Register!$C$6:$C$1255,"Sales",Register!$E$6:$E$1255,$B6,Register!$K$6:$K$1255,"Q3") -> 3589811.7 | F6: =SUMIFS(Register!$G$6:$G$1255,Register!$F$6:$F$1255,"Standard-rated 5%",Register!$C$6:$C$1255,"Sales",Register!$E$6:$E$1255,$B6,Register!$K$6:$K$1255,"Q4") -> 3610020 | G6: =SUM(C6:F6) -> 13379603 | H6: =G6/G$13 -> 0.48577939
B7: Abu Dhabi | C7: =SUMIFS(Register!$G$6:$G$1255,Register!$F$6:$F$1255,"Standard-rated 5%",Register!$C$6:$C$1255,"Sales",Register!$E$6:$E$1255,$B7,Register!$K$6:$K$1255,"Q1") -> 2063647.8 | D7: =SUMIFS(Register!$G$6:$G$1255,Register!$F$6:$F$1255,"Standard-rated 5%",Register!$C$6:$C$1255,"Sales",Register!$E$6:$E$1255,$B7,Register!$K$6:$K$1255,"Q2") -> 2411882.7 | E7: =SUMIFS(Register!$G$6:$G$1255,Register!$F$6:$F$1255,"Standard-rated 5%",Register!$C$6:$C$1255,"Sales",Register!$E$6:$E$1255,$B7,Register!$K$6:$K$1255,"Q3") -> 1308600 | F7: =SUMIFS(Register!$G$6:$G$1255,Register!$F$6:$F$1255,"Standard-rated 5%",Register!$C$6:$C$1255,"Sales",Register!$E$6:$E$1255,$B7,Register!$K$6:$K$1255,"Q4") -> 1265515.6 | G7: =SUM(C7:F7) -> 7049646.1 | H7: =G7/G$13 -> 0.25595473
B8: Sharjah | C8: =SUMIFS(Register!$G$6:$G$1255,Register!$F$6:$F$1255,"Standard-rated 5%",Register!$C$6:$C$1255,"Sales",Register!$E$6:$E$1255,$B8,Register!$K$6:$K$1255,"Q1") -> 1105421.1 | D8: =SUMIFS(Register!$G$6:$G$1255,Register!$F$6:$F$1255,"Standard-rated 5%",Register!$C$6:$C$1255,"Sales",Register!$E$6:$E$1255,$B8,Register!$K$6:$K$1255,"Q2") -> 966743 | E8: =SUMIFS(Register!$G$6:$G$1255,Register!$F$6:$F$1255,"Standard-rated 5%",Register!$C$6:$C$1255,"Sales",Register!$E$6:$E$1255,$B8,Register!$K$6:$K$1255,"Q3") -> 806774.26 | F8: =SUMIFS(Register!$G$6:$G$1255,Register!$F$6:$F$1255,"Standard-rated 5%",Register!$C$6:$C$1255,"Sales",Register!$E$6:$E$1255,$B8,Register!$K$6:$K$1255,"Q4") -> 628249.2 | G8: =SUM(C8:F8) -> 3507187.6 | H8: =G8/G$13 -> 0.12733707
B9: Ajman | C9: =SUMIFS(Register!$G$6:$G$1255,Register!$F$6:$F$1255,"Standard-rated 5%",Register!$C$6:$C$1255,"Sales",Register!$E$6:$E$1255,$B9,Register!$K$6:$K$1255,"Q1") -> 143096.49 | D9: =SUMIFS(Register!$G$6:$G$1255,Register!$F$6:$F$1255,"Standard-rated 5%",Register!$C$6:$C$1255,"Sales",Register!$E$6:$E$1255,$B9,Register!$K$6:$K$1255,"Q2") -> 160628.76 | E9: =SUMIFS(Register!$G$6:$G$1255,Register!$F$6:$F$1255,"Standard-rated 5%",Register!$C$6:$C$1255,"Sales",Register!$E$6:$E$1255,$B9,Register!$K$6:$K$1255,"Q3") -> 228397.01 | F9: =SUMIFS(Register!$G$6:$G$1255,Register!$F$6:$F$1255,"Standard-rated 5%",Register!$C$6:$C$1255,"Sales",Register!$E$6:$E$1255,$B9,Register!$K$6:$K$1255,"Q4") -> 204336.39 | G9: =SUM(C9:F9) -> 736458.65 | H9: =G9/G$13 -> 0.026738942
B10: Ras Al Khaimah | C10: =SUMIFS(Register!$G$6:$G$1255,Register!$F$6:$F$1255,"Standard-rated 5%",Register!$C$6:$C$1255,"Sales",Register!$E$6:$E$1255,$B10,Register!$K$6:$K$1255,"Q1") -> 381261.16 | D10: =SUMIFS(Register!$G$6:$G$1255,Register!$F$6:$F$1255,"Standard-rated 5%",Register!$C$6:$C$1255,"Sales",Register!$E$6:$E$1255,$B10,Register!$K$6:$K$1255,"Q2") -> 759828.55 | E10: =SUMIFS(Register!$G$6:$G$1255,Register!$F$6:$F$1255,"Standard-rated 5%",Register!$C$6:$C$1255,"Sales",Register!$E$6:$E$1255,$B10,Register!$K$6:$K$1255,"Q3") -> 253654.82 | F10: =SUMIFS(Register!$G$6:$G$1255,Register!$F$6:$F$1255,"Standard-rated 5%",Register!$C$6:$C$1255,"Sales",Register!$E$6:$E$1255,$B10,Register!$K$6:$K$1255,"Q4") -> 186545.37 | G10: =SUM(C10:F10) -> 1581289.9 | H10: =G10/G$13 -> 0.057412618
B11: Fujairah | C11: =SUMIFS(Register!$G$6:$G$1255,Register!$F$6:$F$1255,"Standard-rated 5%",Register!$C$6:$C$1255,"Sales",Register!$E$6:$E$1255,$B11,Register!$K$6:$K$1255,"Q1") -> 261378.64 | D11: =SUMIFS(Register!$G$6:$G$1255,Register!$F$6:$F$1255,"Standard-rated 5%",Register!$C$6:$C$1255,"Sales",Register!$E$6:$E$1255,$B11,Register!$K$6:$K$1255,"Q2") -> 325842.58 | E11: =SUMIFS(Register!$G$6:$G$1255,Register!$F$6:$F$1255,"Standard-rated 5%",Register!$C$6:$C$1255,"Sales",Register!$E$6:$E$1255,$B11,Register!$K$6:$K$1255,"Q3") -> 126367.13 | F11: =SUMIFS(Register!$G$6:$G$1255,Register!$F$6:$F$1255,"Standard-rated 5%",Register!$C$6:$C$1255,"Sales",Register!$E$6:$E$1255,$B11,Register!$K$6:$K$1255,"Q4") -> 247223.84 | G11: =SUM(C11:F11) -> 960812.19 | H11: =G11/G$13 -> 0.034884649
B12: Umm Al Quwain | C12: =SUMIFS(Register!$G$6:$G$1255,Register!$F$6:$F$1255,"Standard-rated 5%",Register!$C$6:$C$1255,"Sales",Register!$E$6:$E$1255,$B12,Register!$K$6:$K$1255,"Q1") -> 100769.68 | D12: =SUMIFS(Register!$G$6:$G$1255,Register!$F$6:$F$1255,"Standard-rated 5%",Register!$C$6:$C$1255,"Sales",Register!$E$6:$E$1255,$B12,Register!$K$6:$K$1255,"Q2") -> 0 | E12: =SUMIFS(Register!$G$6:$G$1255,Register!$F$6:$F$1255,"Standard-rated 5%",Register!$C$6:$C$1255,"Sales",Register!$E$6:$E$1255,$B12,Register!$K$6:$K$1255,"Q3") -> 148658.43 | F12: =SUMIFS(Register!$G$6:$G$1255,Register!$F$6:$F$1255,"Standard-rated 5%",Register!$C$6:$C$1255,"Sales",Register!$E$6:$E$1255,$B12,Register!$K$6:$K$1255,"Q4") -> 78124.45 | G12: =SUM(C12:F12) -> 327552.56 | H12: =G12/G$13 -> 0.011892601
B13: Total | C13: =SUM(C6:C12) -> 6933825.6 | D13: =SUM(D6:D12) -> 7926446.2 | E13: =SUM(E6:E12) -> 6462263.3 | F13: =SUM(F6:F12) -> 6220014.8 | G13: =SUM(G6:G12) -> 27542550 | H13: =SUM(H6:H12) -> 1

Sheet Exceptions
B1: Compliance exceptions
B2: Automatically flagged by the VAT engine in the Register (column R)
B5: Exception type | C5: Q1 | D5: Q2 | E5: Q3 | F5: Q4 | G5: Documents | H5: Net value (AED) | I5: VAT at risk (AED)
B6: Invalid / missing TRN | C6: =COUNTIFS(Register!$R$6:$R$1255,$B6,Register!$K$6:$K$1255,"Q1") -> 1 | D6: =COUNTIFS(Register!$R$6:$R$1255,$B6,Register!$K$6:$K$1255,"Q2") -> 1 | E6: =COUNTIFS(Register!$R$6:$R$1255,$B6,Register!$K$6:$K$1255,"Q3") -> 1 | F6: =COUNTIFS(Register!$R$6:$R$1255,$B6,Register!$K$6:$K$1255,"Q4") -> 0 | G6: =SUM(C6:F6) -> 3 | H6: =SUMIFS(Register!$G$6:$G$1255,Register!$R$6:$R$1255,$B6) -> 200601.6 | I6: =SUMIFS(Register!$L$6:$L$1255,Register!$R$6:$R$1255,$B6,Register!$C$6:$C$1255,"Purchase") -> 10030.07
B7: Blocked input | C7: =COUNTIFS(Register!$R$6:$R$1255,$B7,Register!$K$6:$K$1255,"Q1") -> 7 | D7: =COUNTIFS(Register!$R$6:$R$1255,$B7,Register!$K$6:$K$1255,"Q2") -> 3 | E7: =COUNTIFS(Register!$R$6:$R$1255,$B7,Register!$K$6:$K$1255,"Q3") -> 4 | F7: =COUNTIFS(Register!$R$6:$R$1255,$B7,Register!$K$6:$K$1255,"Q4") -> 3 | G7: =SUM(C7:F7) -> 17 | H7: =SUMIFS(Register!$G$6:$G$1255,Register!$R$6:$R$1255,$B7) -> 594809.56 | I7: =SUMIFS(Register!$L$6:$L$1255,Register!$R$6:$R$1255,$B7,Register!$C$6:$C$1255,"Purchase") -> 29740.49
B8: Late posting (>30d) | C8: =COUNTIFS(Register!$R$6:$R$1255,$B8,Register!$K$6:$K$1255,"Q1") -> 11 | D8: =COUNTIFS(Register!$R$6:$R$1255,$B8,Register!$K$6:$K$1255,"Q2") -> 7 | E8: =COUNTIFS(Register!$R$6:$R$1255,$B8,Register!$K$6:$K$1255,"Q3") -> 6 | F8: =COUNTIFS(Register!$R$6:$R$1255,$B8,Register!$K$6:$K$1255,"Q4") -> 6 | G8: =SUM(C8:F8) -> 30 | H8: =SUMIFS(Register!$G$6:$G$1255,Register!$R$6:$R$1255,$B8) -> 1357022.5 | I8: =SUMIFS(Register!$L$6:$L$1255,Register!$R$6:$R$1255,$B8) -> 54511.24
B9: Total | C9: =SUM(C6:C8) -> 19 | D9: =SUM(D6:D8) -> 11 | E9: =SUM(E6:E8) -> 11 | F9: =SUM(F6:F8) -> 9 | G9: =SUM(G6:G8) -> 50 | H9: =SUM(H6:H8) -> 2152433.6 | I9: =SUM(I6:I8) -> 94281.8
B11: Exception rate (documents flagged ÷ total documents) | G11: =G9/COUNTA(Register!$A$6:$A$1255) -> 0.04
B12: Recommended actions
B13: • Invalid TRN: obtain valid supplier TRN / tax invoice before claiming input VAT; hold payment until resolved.
B14: • Blocked input: confirm entertainment-type spend is coded to non-recoverable GL; review policy for client events.
B15: • Late posting: tighten month-end cut-off so tax points fall in the correct VAT return period (penalty exposure).

Sheet Turnover_Recon
B1: Turnover reconciliation — VAT returns vs financial statements
B2: A standard FTA-audit control: sales declared in VAT returns must reconcile to revenue in the accounts
B5: Item | C5: AED | D5: Note
B6: Standard-rated supplies (Box 1a–1g) | C6: =Exec_Summary!F25-Exec_Summary!D25-Exec_Summary!E25 -> 27542550
B7: Zero-rated supplies (Box 4) | C7: =Exec_Summary!D25 -> 6427195.1
B8: Exempt + out-of-scope supplies (Box 5 and non-VAT) | C8: =Exec_Summary!E25 -> 2305288.1
B9: Total supplies per VAT returns | C9: =SUM(C6:C8) -> 36275033
B11: Revenue per general ledger / financial statements | C11: 36423761 | D11: Input from the trial balance (illustrative)
B12: Difference to explain | C12: =C11-C9 -> 148727.83
B14: Reconciling items
B15: Credit notes issued after period-end (timing) | C15: 76178
B16: FX revaluation on foreign-currency invoices | C16: 47158
B17: Total explained | C17: =SUM(C15:C16) -> 123336
B18: UNEXPLAINED DIFFERENCE | C18: =C12-C17 -> 25391.83
B19: Unexplained as % of GL revenue | C19: =C18/C11 -> 0.00069712268
B20: Tolerance (management policy) | C20: 0.0015
B21: Result | C21: =IF(ABS(C19)<=C20,"● Within tolerance","● Investigate") -> ● Within tolerance

Sheet Register
B1: Invoice register — calendar 2025
B2: 1,250 sales & purchase documents (AED). Blue = source data; black = VAT engine formulas.
A5: Doc no | B5: Doc date | C5: Type | D5: Counterparty | E5: Emirate | F5: VAT category | G5: Net amount (AED) | H5: VAT rate | I5: TRN valid | J5: Posting date | K5: Quarter | L5: VAT amount | M5: Output VAT (std-rated sales) | N5: Output VAT (reverse charge) | O5: Input VAT recoverable | P5: VAT not recoverable | Q5: Posting lag (days) | R5: Exception
A6: SI-2025-0095 | B6: 45658 | C6: Sales | D6: Pinnacle Contracting | E6: Dubai | F6: Standard-rated 5% | G6: 31622.09 | H6: 0.05 | I6: Y | J6: 45658 | K6: ="Q"&ROUNDUP(MONTH(B6)/3,0) -> Q1 | L6: =ROUND(G6*H6,2) -> 1581.1 | M6: =IF(AND(C6="Sales",F6="Standard-rated 5%"),L6,0) -> 1581.1 | N6: =IF(F6="Reverse charge (imported services)",L6,0) -> 0 | O6: =IF(C6<>"Purchase",0,IF(OR(I6="N",F6="Blocked input (entertainment)"),0,L6)) -> 0 | P6: =IF(C6<>"Purchase",0,L6-O6) -> 0 | Q6: =J6-B6 -> 0 | R6: =IF(I6="N","Invalid / missing TRN",IF(F6="Blocked input (entertainment)","Blocked input",IF(Q6>30,"Late posting (>30d)","")))
A7: SI-2025-0502 | B7: 45658 | C7: Sales | D7: Summit General Trading | E7: Dubai | F7: Standard-rated 5% | G7: 65824.8 | H7: 0.05 | I7: Y | J7: 45658 | K7: ="Q"&ROUNDUP(MONTH(B7)/3,0) -> Q1 | L7: =ROUND(G7*H7,2) -> 3291.24 | M7: =IF(AND(C7="Sales",F7="Standard-rated 5%"),L7,0) -> 3291.24 | N7: =IF(F7="Reverse charge (imported services)",L7,0) -> 0 | O7: =IF(C7<>"Purchase",0,IF(OR(I7="N",F7="Blocked input (entertainment)"),0,L7)) -> 0 | P7: =IF(C7<>"Purchase",0,L7-O7) -> 0 | Q7: =J7-B7 -> 0 | R7: =IF(I7="N","Invalid / missing TRN",IF(F7="Blocked input (entertainment)","Blocked input",IF(Q7>30,"Late posting (>30d)","")))
A8: PI-2025-0595 | B8: 45659 | C8: Purchase | D8: Delta Supplies LLC | E8: Dubai | F8: Standard-rated 5% | G8: 10519.94 | H8: 0.05 | I8: Y | J8: 45659 | K8: ="Q"&ROUNDUP(MONTH(B8)/3,0) -> Q1 | L8: =ROUND(G8*H8,2) -> 526 | M8: =IF(AND(C8="Sales",F8="Standard-rated 5%"),L8,0) -> 0 | N8: =IF(F8="Reverse charge (imported services)",L8,0) -> 0 | O8: =IF(C8<>"Purchase",0,IF(OR(I8="N",F8="Blocked input (entertainment)"),0,L8)) -> 526 | P8: =IF(C8<>"Purchase",0,L8-O8) -> 0 | Q8: =J8-B8 -> 0 | R8: =IF(I8="N","Invalid / missing TRN",IF(F8="Blocked input (entertainment)","Blocked input",IF(Q8>30,"Late posting (>30d)","")))
A9: PI-2025-0029 | B9: 45660 | C9: Purchase | D9: Delta Supplies LLC | E9: Dubai | F9: Standard-rated 5% | G9: 18109.3 | H9: 0.05 | I9: Y | J9: 45660 | K9: ="Q"&ROUNDUP(MONTH(B9)/3,0) -> Q1 | L9: =ROUND(G9*H9,2) -> 905.47 | M9: =IF(AND(C9="Sales",F9="Standard-rated 5%"),L9,0) -> 0 | N9: =IF(F9="Reverse charge (imported services)",L9,0) -> 0 | O9: =IF(C9<>"Purchase",0,IF(OR(I9="N",F9="Blocked input (entertainment)"),0,L9)) -> 905.47 | P9: =IF(C9<>"Purchase",0,L9-O9) -> 0 | Q9: =J9-B9 -> 0 | R9: =IF(I9="N","Invalid / missing TRN",IF(F9="Blocked input (entertainment)","Blocked input",IF(Q9>30,"Late posting (>30d)","")))
A10: PI-2025-0173 | B10: 45660 | C10: Purchase | D10: Delta Supplies LLC | E10: Sharjah | F10: Blocked input (entertainment) | G10: 11298.13 | H10: 0.05 | I10: Y | J10: 45660 | K10: ="Q"&ROUNDUP(MONTH(B10)/3,0) -> Q1 | L10: =ROUND(G10*H10,2) -> 564.91 | M10: =IF(AND(C10="Sales",F10="Standard-rated 5%"),L10,0) -> 0 | N10: =IF(F10="Reverse charge (imported services)",L10,0) -> 0 | O10: =IF(C10<>"Purchase",0,IF(OR(I10="N",F10="Blocked input (entertainment)"),0,L10)) -> 0 | P10: =IF(C10<>"Purchase",0,L10-O10) -> 564.91 | Q10: =J10-B10 -> 0 | R10: =IF(I10="N","Invalid / missing TRN",IF(F10="Blocked input (entertainment)","Blocked input",IF(Q10>30,"Late posting (>30d)",""))) -> Blocked input
A11: PI-2025-0192 | B11: 45660 | C11: Purchase | D11: Granite Supplies LLC | E11: Abu Dhabi | F11: Reverse charge (imported services) | G11: 11049.53 | H11: 0.05 | I11: Y | J11: 45660 | K11: ="Q"&ROUNDUP(MONTH(B11)/3,0) -> Q1 | L11: =ROUND(G11*H11,2) -> 552.48 | M11: =IF(AND(C11="Sales",F11="Standard-rated 5%"),L11,0) -> 0 | N11: =IF(F11="Reverse charge (imported services)",L11,0) -> 552.48 | O11: =IF(C11<>"Purchase",0,IF(OR(I11="N",F11="Blocked input (entertainment)"),0,L11)) -> 552.48 | P11: =IF(C11<>"Purchase",0,L11-O11) -> 0 | Q11: =J11-B11 -> 0 | R11: =IF(I11="N","Invalid / missing TRN",IF(F11="Blocked input (entertainment)","Blocked input",IF(Q11>30,"Late posting (>30d)","")))
A12: SI-2025-0267 | B12: 45660 | C12: Sales | D12: Alpha FZE | E12: Dubai | F12: Standard-rated 5% | G12: 22251.01 | H12: 0.05 | I12: Y | J12: 45660 | K12: ="Q"&ROUNDUP(MONTH(B12)/3,0) -> Q1 | L12: =ROUND(G12*H12,2) -> 1112.55 | M12: =IF(AND(C12="Sales",F12="Standard-rated 5%"),L12,0) -> 1112.55 | N12: =IF(F12="Reverse charge (imported services)",L12,0) -> 0 | O12: =IF(C12<>"Purchase",0,IF(OR(I12="N",F12="Blocked input (entertainment)"),0,L12)) -> 0 | P12: =IF(C12<>"Purchase",0,L12-O12) -> 0 | Q12: =J12-B12 -> 0 | R12: =IF(I12="N","Invalid / missing TRN",IF(F12="Blocked input (entertainment)","Blocked input",IF(Q12>30,"Late posting (>30d)","")))
A13: SI-2025-0312 | B13: 45661 | C13: Sales | D13: Delta FZE | E13: Abu Dhabi | F13: Standard-rated 5% | G13: 158101.16 | H13: 0.05 | I13: Y | J13: 45701 | K13: ="Q"&ROUNDUP(MONTH(B13)/3,0) -> Q1 | L13: =ROUND(G13*H13,2) -> 7905.06 | M13: =IF(AND(C13="Sales",F13="Standard-rated 5%"),L13,0) -> 7905.06 | N13: =IF(F13="Reverse charge (imported services)",L13,0) -> 0 | O13: =IF(C13<>"Purchase",0,IF(OR(I13="N",F13="Blocked input (entertainment)"),0,L13)) -> 0 | P13: =IF(C13<>"Purchase",0,L13-O13) -> 0 | Q13: =J13-B13 -> 40 | R13: =IF(I13="N","Invalid / missing TRN",IF(F13="Blocked input (entertainment)","Blocked input",IF(Q13>30,"Late posting (>30d)",""))) -> Late posting (>30d)
A14: SI-2025-0365 | B14: 45661 | C14: Sales | D14: Horizon Contracting | E14: Abu Dhabi | F14: Standard-rated 5% | G14: 24165.13 | H14: 0.05 | I14: Y | J14: 45663 | K14: ="Q"&ROUNDUP(MONTH(B14)/3,0) -> Q1 | L14: =ROUND(G14*H14,2) -> 1208.26 | M14: =IF(AND(C14="Sales",F14="Standard-rated 5%"),L14,0) -> 1208.26 | N14: =IF(F14="Reverse charge (imported services)",L14,0) -> 0 | O14: =IF(C14<>"Purchase",0,IF(OR(I14="N",F14="Blocked input (entertainment)"),0,L14)) -> 0 | P14: =IF(C14<>"Purchase",0,L14-O14) -> 0 | Q14: =J14-B14 -> 2 | R14: =IF(I14="N","Invalid / missing TRN",IF(F14="Blocked input (entertainment)","Blocked input",IF(Q14>30,"Late posting (>30d)","")))
A15: PI-2025-0302 | B15: 45662 | C15: Purchase | D15: Granite Technologies | E15: Umm Al Quwain | F15: Standard-rated 5% | G15: 48577.89 | H15: 0.05 | I15: Y | J15: 45662 | K15: ="Q"&ROUNDUP(MONTH(B15)/3,0) -> Q1 | L15: =ROUND(G15*H15,2) -> 2428.89 | M15: =IF(AND(C15="Sales",F15="Standard-rated 5%"),L15,0) -> 0 | N15: =IF(F15="Reverse charge (imported services)",L15,0) -> 0 | O15: =IF(C15<>"Purchase",0,IF(OR(I15="N",F15="Blocked input (entertainment)"),0,L15)) -> 2428.89 | P15: =IF(C15<>"Purchase",0,L15-O15) -> 0 | Q15: =J15-B15 -> 0 | R15: =IF(I15="N","Invalid / missing TRN",IF(F15="Blocked input (entertainment)","Blocked input",IF(Q15>30,"Late posting (>30d)","")))
A16: SI-2025-0012 | B16: 45662 | C16: Sales | D16: Delta FZE | E16: Abu Dhabi | F16: Standard-rated 5% | G16: 51783.1 | H16: 0.05 | I16: Y | J16: 45662 | K16: ="Q"&ROUNDUP(MONTH(B16)/3,0) -> Q1 | L16: =ROUND(G16*H16,2) -> 2589.16 | M16: =IF(AND(C16="Sales",F16="Standard-rated 5%"),L16,0) -> 2589.16 | N16: =IF(F16="Reverse charge (imported services)",L16,0) -> 0 | O16: =IF(C16<>"Purchase",0,IF(OR(I16="N",F16="Blocked input (entertainment)"),0,L16)) -> 0 | P16: =IF(C16<>"Purchase",0,L16-O16) -> 0 | Q16: =J16-B16 -> 0 | R16: =IF(I16="N","Invalid / missing TRN",IF(F16="Blocked input (entertainment)","Blocked input",IF(Q16>30,"Late posting (>30d)","")))
A17: PI-2025-0337 | B17: 45663 | C17: Purchase | D17: Summit Supplies LLC | E17: Fujairah | F17: Standard-rated 5% | G17: 7359.07 | H17: 0.05 | I17: Y | J17: 45663 | K17: ="Q"&ROUNDUP(MONTH(B17)/3,0) -> Q1 | L17: =ROUND(G17*H17,2) -> 367.95 | M17: =IF(AND(C17="Sales",F17="Standard-rated 5%"),L17,0) -> 0 | N17: =IF(F17="Reverse charge (imported services)",L17,0) -> 0 | O17: =IF(C17<>"Purchase",0,IF(OR(I17="N",F17="Blocked input (entertainment)"),0,L17)) -> 367.95 | P17: =IF(C17<>"Purchase",0,L17-O17) -> 0 | Q17: =J17-B17 -> 0 | R17: =IF(I17="N","Invalid / missing TRN",IF(F17="Blocked input (entertainment)","Blocked input",IF(Q17>30,"Late posting (>30d)","")))
... A1255: SI-2025-0529 | B1255: 46022 | C1255: Sales | D1255: Nova Contracting | E1255: Dubai | F1255: Standard-rated 5% | G1255: 141619.07 | H1255: 0.05 | I1255: Y | J1255: 46022 | K1255: ="Q"&ROUNDUP(MONTH(B1255)/3,0) -> Q4 | L1255: =ROUND(G1255*H1255,2) -> 7080.95 | M1255: =IF(AND(C1255="Sales",F1255="Standard-rated 5%"),L1255,0) -> 7080.95 | N1255: =IF(F1255="Reverse charge (imported services)",L1255,0) -> 0 | O1255: =IF(C1255<>"Purchase",0,IF(OR(I1255="N",F1255="Blocked input (entertainment)"),0,L1255)) -> 0 | P1255: =IF(C1255<>"Purchase",0,L1255-O1255) -> 0 | Q1255: =J1255-B1255 -> 0 | R1255: =IF(I1255="N","Invalid / missing TRN",IF(F1255="Blocked input (entertainment)","Blocked input",IF(Q1255>30,"Late posting (>30d)","")))

Sheet KPI_Dictionary
B1: KPI dictionary
B2: Definitions used in this VAT pack
B4: KPI | C4: Definition | D4: Why it matters
B5: Total sales | C5: Net value of all outward supplies (standard, zero-rated, exempt, out of scope). | D5: Basis for turnover and registration thresholds.
B6: Output VAT | C6: 5% × standard-rated sales, plus self-assessed reverse-charge VAT. | D6: Tax collected on behalf of the FTA.
B7: Input VAT recovered | C7: VAT on purchases with a valid TRN that are not blocked, including capital assets and reverse charge. | D7: Cash recovered through the return.
B8: Net VAT payable | C8: Output VAT (incl. reverse charge) − recoverable input VAT. Negative = refund. | D8: Cash outflow to/inflow from the FTA.
B9: Input VAT recovery rate | C9: Recovered ÷ (recovered + not recoverable). | D9: Measures purchase-to-pay compliance quality.
B10: Effective VAT rate | C10: Output VAT ÷ total sales. | D10: Falls below 5% when exports / exempt supplies are significant.
B11: Exception | C11: Invalid TRN, blocked input or posting more than 30 days after the document date. | D11: Compliance risk and penalty exposure.
B12: Turnover reconciliation | C12: VAT-return supplies vs GL revenue; unexplained difference must be inside tolerance. | D12: Primary FTA audit trigger.

Sheet Checks
B1: Integrity checks
B2: All checks must show PASS (tolerance AED 1)
B4: Overall status | C4: =IF(COUNTIF(F8:F16,"FAIL")=0,"ALL CHECKS PASS","CHECK FAILURES") -> ALL CHECKS PASS
B7: Check | C7: Value A | D7: Value B | E7: Difference | F7: Result
B8: Register documents loaded (1,250) | C8: =COUNTA(Register!$A$6:$A$1255) -> 1250 | D8: 1250 | E8: =C8-D8 -> 0 | F8: =IF(ABS(E8)<=1,"PASS","FAIL") -> PASS
B9: Sum of quarters = full-year net VAT | C9: =Exec_Summary!J25 -> 177786.43 | D9: =SUM(Register!$M$6:$M$1255)+SUM(Register!$N$6:$N$1255)-SUM(Register!$O$6:$O$1255) -> 177786.43 | E9: =C9-D9 -> 0 | F9: =IF(ABS(E9)<=1,"PASS","FAIL") -> PASS
B10: VAT201 box 14 = Exec_Summary net VAT (selected period) | C10: =VAT201_Return!E27 -> 177786.43 | D10: =Exec_Summary!C13 -> 177786.43 | E10: =C10-D10 -> 0 | F10: =IF(ABS(E10)<=1,"PASS","FAIL") -> PASS
B11: Monthly trend net VAT = quarterly net VAT | C11: =Monthly_Trend!G18 -> 177786.43 | D11: =Exec_Summary!J25 -> 177786.43 | E11: =C11-D11 -> 0 | F11: =IF(ABS(E11)<=1,"PASS","FAIL") -> PASS
B12: Emirate split total = standard-rated sales (FY) | C12: =Emirate_Split!G13 -> 27542550 | D12: =Exec_Summary!C25 -> 27542550 | E12: =C12-D12 -> 0 | F12: =IF(ABS(E12)<=1,"PASS","FAIL") -> PASS
B13: Recoverable + not recoverable = VAT on all purchases | C13: =SUM(Register!$O$6:$O$1255)+SUM(Register!$P$6:$P$1255) -> 1315989.7 | D13: =SUMIFS(Register!$L$6:$L$1255,Register!$C$6:$C$1255,"Purchase") -> 1315989.7 | E13: =C13-D13 -> 0 | F13: =IF(ABS(E13)<=1,"PASS","FAIL") -> PASS
B14: Exceptions: sum by type = flagged documents | C14: =Exceptions!G9 -> 50 | D14: =COUNTIF(Register!$R$6:$R$1255,"?*") -> 50 | E14: =C14-D14 -> 0 | F14: =IF(ABS(E14)<=1,"PASS","FAIL") -> PASS
B15: Every document has a VAT category | C15: =COUNTA(Register!$F$6:$F$1255) -> 1250 | D15: =COUNTA(Register!$A$6:$A$1255) -> 1250 | E15: =C15-D15 -> 0 | F15: =IF(ABS(E15)<=1,"PASS","FAIL") -> PASS
B16: Turnover recon unexplained difference within tolerance (1 = yes) | C16: =IF(ABS(Turnover_Recon!C19)<=Turnover_Recon!C20,1,0) -> 1 | D16: 1 | E16: =C16-D16 -> 0 | F16: =IF(ABS(E16)<=1,"PASS","FAIL") -> PASS
