Workbook

Sheet Exec_Summary
B1: Meridian Gulf Trading LLC — UAE Corporate Tax Pack
B2: Illustrative taxable person · period FY2025 (1 Jan – 31 Dec 2025) · AED · mainland entity, not a Qualifying Free Zone Person
B4: Model status | C4: =Checks!C4 -> ALL CHECKS PASS
B6: 1 · HEADLINE KPIs
B7: Accounting profit before tax | C7: =CT_Computation!C7 -> 24846239
B8: Total tax adjustments | C8: =CT_Computation!C17 -> -3669734.7 | D8: add-backs less exempt income
B9: Taxable income before losses | C9: =CT_Computation!C18 -> 21176504
B10: Losses utilised | C10: =CT_Computation!C23 -> 3200000 | D10: capped at 75% of taxable income
B11: Taxable income | C11: =CT_Computation!C25 -> 17976504
B12: NET CORPORATE TAX PAYABLE | C12: =CT_Computation!C32 -> 1499135.4 | D12: after foreign tax credit
B13: Effective tax rate on accounting profit | C13: =CT_Computation!C34 -> 0.060336511 | D13: vs 9.00% headline
B14: Tax saved by exempt income | C14: =-Rate_Reconciliation!C7 -> 369900 | D14: participation exemption × 9%
B15: Tax cost of non-deductible items | C15: =Rate_Reconciliation!C8 -> 39623.881 | D15: policy leakage × 9%
B16: Interest headroom under the cap | C16: =Interest_Limitation!C19 -> 11025852 | D16: greater of 30% EBITDA and AED 12M
B17: Tax losses carried forward | C17: =CT_Computation!C24 -> 0 | D17: future tax shield
B18: Small Business Relief eligible? | C18: =IF(CT_Computation!C5<=Parameters!$C$14,"Yes","No — revenue above AED 3M") -> No — revenue above AED 3M
B20: 2 · PROFIT-TO-TAXABLE-INCOME BRIDGE
B21: Step | C21: Movement | D21: Cumulative | E21: Base (hidden) | F21: Increase | G21: Decrease | H21: Total
B22: Accounting profit | C22: =CT_Computation!C7 -> 24846239 | D22: =C22 -> 24846239 | E22: =0 -> 0 | F22: =0 -> 0 | G22: =0 -> 0 | H22: =C22 -> 24846239
B23: Non-deductible add-backs | C23: =CT_Computation!C10+CT_Computation!C11+CT_Computation!C12+CT_Computation!C15+CT_Computation!C16 -> 440265.34 | D23: =D22+C23 -> 25286504 | E23: =MIN(D22,D23) -> 24846239 | F23: =MAX(C23,0) -> 440265.34 | G23: =MAX(-C23,0) -> 0 | H23: =0 -> 0
B24: Exempt income | C24: =CT_Computation!C13+CT_Computation!C14 -> -4110000 | D24: =D23+C24 -> 21176504 | E24: =MIN(D23,D24) -> 21176504 | F24: =MAX(C24,0) -> 0 | G24: =MAX(-C24,0) -> 4110000 | H24: =0 -> 0
B25: Losses utilised | C25: =-CT_Computation!C23 -> -3200000 | D25: =D24+C25 -> 17976504 | E25: =MIN(D24,D25) -> 17976504 | F25: =MAX(C25,0) -> 0 | G25: =MAX(-C25,0) -> 3200000 | H25: =0 -> 0
B26: Taxable income | C26: =CT_Computation!C25 -> 17976504 | D26: =C26 -> 17976504 | E26: =0 -> 0 | F26: =0 -> 0 | G26: =0 -> 0 | H26: =C26 -> 17976504
B28: 3 · KEY MESSAGES (auto-generated)
B29: ="Accounting profit of AED "&TEXT((C7)/1000000,"0.00")&"M"&" converts to taxable income of AED "&TEXT((C11)/1000000,"0.00")&"M"&" after add-backs of AED "&TEXT((CT_Computation!C10+CT_Computation!C11+CT_Computation!C12+CT_Computation!C15+CT_Computation!C16)/1000000,"0.00")&"M"&", exempt income of AED "&TEXT((-(CT_Computation!C13+CT_Computation!C14))/1000000,"0.00")&"M"&" and loss relief of AED "&TEXT((C10)/1000000,"0.00")&"M"&"." -> Accounting profit of AED 24.85M converts to taxable income of AED 17.98M after add-backs of AED 0.44M, exempt income of AED 4.11M and loss relief of AED 3.20M.
B30: ="Net corporate tax payable is AED "&TEXT(C12,"#,##0")&" — an effective rate of "&TEXT(C13,"0.00%")&" versus the 9% headline, driven mainly by the participation exemption (AED "&TEXT(C14/1000,"#,##0")&"K saved) and loss relief." -> Net corporate tax payable is AED 1,499,135 — an effective rate of 6.03% versus the 9% headline, driven mainly by the participation exemption (AED 370K saved) and loss relief.
B31: ="Policy leakage: non-deductible items cost AED "&TEXT(C15/1000,"#,##0")&"K of tax; the largest drivers are in Adjustment_Summary (entertainment, general provisions, non-qualifying donations)." -> Policy leakage: non-deductible items cost AED 40K of tax; the largest drivers are in Adjustment_Summary (entertainment, general provisions, non-qualifying donations).
B32: ="Interest: net interest expense is within the AED 12M de-minimis (headroom AED "&TEXT((C16)/1000000,"0.00")&"M"&"), so no limitation applies. "&IF(C17=0,"Brought-forward losses were fully utilised in the year.","Losses carried forward: AED "&TEXT((C17)/1000000,"0.00")&"M"&".") -> Interest: net interest expense is within the AED 12M de-minimis (headroom AED 11.03M), so no limitation applies. Brought-forward losses were fully utilised in the year.

Sheet CT_Computation
B1: Corporate tax computation — FY2025
B2: Accounting profit → taxable income → CT payable (AED). All lines are formulas over GL_Register and Parameters.
B4: Line | C4: AED | D4: Basis
B5: Total income (accounting) | C5: =SUMIFS(GL_Register!$F$6:$F$1092,GL_Register!$D$6:$D$1092,"Income") -> 69279628 | D5: GL_Register class = Income
B6: Total expenses (accounting) | C6: =SUMIFS(GL_Register!$F$6:$F$1092,GL_Register!$D$6:$D$1092,"Expense") -> 44433390 | D6: GL_Register class = Expense
B7: ACCOUNTING PROFIT BEFORE TAX | C7: =C5-C6 -> 24846239
B9: ADJUSTMENTS
B10: Add: non-deductible expenses (100%) | C10: =SUMIFS(GL_Register!$I$6:$I$1092,GL_Register!$E$6:$E$1092,"DIS100") -> 260677.48 | D10: Fines, personal, non-qualifying donations, general provisions
B11: Add: entertainment (50% disallowed) | C11: =SUMIFS(GL_Register!$I$6:$I$1092,GL_Register!$E$6:$E$1092,"DIS50") -> 154015.63 | D11: Treatment DIS50
B12: Add: transfer-pricing adjustment | C12: =SUMIFS(GL_Register!$I$6:$I$1092,GL_Register!$E$6:$E$1092,"TP") -> 25572.23 | D12: Related-party excess
B13: Less: exempt dividends (qualifying participations) | C13: =SUMIFS(GL_Register!$I$6:$I$1092,GL_Register!$E$6:$E$1092,"EXEMPT",GL_Register!$C$6:$C$1092,"Dividend*") -> -2790000 | D13: Participation exemption
B14: Less: exempt capital gains (qualifying shareholdings) | C14: =SUMIFS(GL_Register!$I$6:$I$1092,GL_Register!$E$6:$E$1092,"EXEMPT",GL_Register!$C$6:$C$1092,"Gain*") -> -1320000 | D14: Participation exemption
B15: Add: donations in excess of cap | C15: =MAX(0,SUMIFS(GL_Register!$F$6:$F$1092,GL_Register!$C$6:$C$1092,"Donations - qualifying*")-Parameters!$C$12*(C7+SUM(C10:C14)+SUMIFS(GL_Register!$F$6:$F$1092,GL_Register!$C$6:$C$1092,"Donations - qualifying*"))) -> 0 | D15: Qualifying donations above 5% of taxable income
B16: Add: interest limitation disallowance | C16: =Interest_Limitation!C18 -> 0 | D16: See Interest_Limitation
B17: TOTAL ADJUSTMENTS | C17: =SUM(C10:C16) -> -3669734.7
B18: TAXABLE INCOME BEFORE LOSSES | C18: =C7+C17 -> 21176504
B20: TAX-LOSS RELIEF
B21: Brought-forward tax losses | C21: =Parameters!$C$9 -> 3200000
B22: Utilisation cap (75% of taxable income) | C22: =MAX(0,C18)*Parameters!$C$8 -> 15882378
B23: Losses utilised | C23: =MIN(C21,C22) -> 3200000
B24: Losses carried forward | C24: =C21-C23 -> 0
B25: TAXABLE INCOME | C25: =MAX(0,C18-C23) -> 17976504
B27: TAX CALCULATION
B28: Taxable income taxed at 0% | C28: =MIN(C25,Parameters!$C$6) -> 375000
B29: Taxable income taxed at 9% | C29: =MAX(0,C25-Parameters!$C$6) -> 17601504
B30: Corporate tax at 9% | C30: =C29*Parameters!$C$7 -> 1584135.4
B31: Less: foreign tax credit (capped at liability) | C31: =-MIN(C30,Parameters!$C$13) -> -85000
B32: NET CORPORATE TAX PAYABLE | C32: =C30+C31 -> 1499135.4
B34: Effective tax rate on accounting profit | C34: =C32/C7 -> 0.060336511
B35: Taxable income ÷ accounting profit | C35: =C25/C7 -> 0.72351008

Sheet Rate_Reconciliation
B1: Effective-rate reconciliation
B2: From the 9% headline rate to the effective rate paid — the CFO view of why tax ≠ 9% × profit
B4: Step | C4: AED | D4: % of accounting profit
B5: Accounting profit before tax | C5: =CT_Computation!C7 -> 24846239
B6: Notional tax at headline 9% | C6: =C5*Parameters!$C$7 -> 2236161.5 | D6: =C6/$C$5 -> 0.09
B7: Exempt dividends and gains | C7: =(CT_Computation!C13+CT_Computation!C14)*Parameters!$C$7 -> -369900 | D7: =C7/$C$5 -> -0.014887565
B8: Non-deductible expenses and TP / donation / interest add-backs | C8: =(CT_Computation!C10+CT_Computation!C11+CT_Computation!C12+CT_Computation!C15+CT_Computation!C16)*Parameters!$C$7 -> 39623.881 | D8: =C8/$C$5 -> 0.0015947637
B9: Utilisation of brought-forward losses | C9: =-CT_Computation!C23*Parameters!$C$7 -> -288000 | D9: =C9/$C$5 -> -0.011591292
B10: 0% band on first AED 375,000 | C10: =-CT_Computation!C28*Parameters!$C$7 -> -33750 | D10: =C10/$C$5 -> -0.0013583545
B11: Foreign tax credit | C11: =CT_Computation!C31 -> -85000 | D11: =C11/$C$5 -> -0.003421041
B12: NET CT PAYABLE | C12: =SUM(C6:C11) -> 1499135.4 | D12: =C12/$C$5 -> 0.060336511
B13: Check vs CT_Computation (should be 0) | C13: =ROUND(C12-CT_Computation!C32,2) -> 0

Sheet Interest_Limitation
B1: Interest deductibility test
B2: Net interest above the greater of 30% of tax EBITDA and the de-minimis amount is disallowed
B4: Step | C4: AED | D4: Note
B5: Interest expense (treatment INTLIM) | C5: =SUMIFS(GL_Register!$F$6:$F$1092,GL_Register!$E$6:$E$1092,"INTLIM") -> 1384148.4 | D5: Third-party + related-party
B6: Less: interest income | C6: =SUMIFS(GL_Register!$F$6:$F$1092,GL_Register!$C$6:$C$1092,"Interest income*") -> 410000 | D6: Bank deposit interest
B7: Net interest expense | C7: =MAX(0,C5-C6) -> 974148.39
B9: Accounting profit | C9: =CT_Computation!C7 -> 24846239
B10: Add: non-deductibles, TP, less exempt income | C10: =CT_Computation!C10+CT_Computation!C11+CT_Computation!C12+CT_Computation!C13+CT_Computation!C14 -> -3669734.7 | D10: Adjustments before interest / donations limits
B11: Add: net interest expense | C11: =C7 -> 974148.39
B12: Add: depreciation | C12: =SUMIFS(GL_Register!$F$6:$F$1092,GL_Register!$C$6:$C$1092,"Depreciation") -> 1568782.8
B13: TAX EBITDA | C13: =SUM(C9:C12) -> 23719435
B15: 30% of tax EBITDA | C15: =C13*Parameters!$C$10 -> 7115830.5
B16: De-minimis threshold | C16: =Parameters!$C$11 -> 12000000
B17: Deductible interest cap (greater of) | C17: =MAX(C15,C16) -> 12000000
B18: DISALLOWED INTEREST | C18: =MAX(0,C7-C17) -> 0 | D18: Added back in CT_Computation
B19: Headroom (cap − net interest) | C19: =C17-C7 -> 11025852
B20: Result | C20: =IF(C18=0,"● Within de-minimis / cap","● Interest restricted") -> ● Within de-minimis / cap

Sheet Adjustment_Summary
B1: Adjustment summary by account
B2: Every ledger account, its treatment and the resulting tax adjustment
B5: Account | C5: Treatment | D5: Lines | E5: Amount (AED) | F5: Tax adjustment | G5: Share of total add-backs
B6: Dividend income - qualifying participation (>=5%, held >=12m) | C6: EXEMPT | D6: =COUNTIFS(GL_Register!$C$6:$C$1092,$B6,GL_Register!$E$6:$E$1092,$C6) -> 2 | E6: =SUMIFS(GL_Register!$F$6:$F$1092,GL_Register!$C$6:$C$1092,$B6,GL_Register!$E$6:$E$1092,$C6) -> 2790000 | F6: =SUMIFS(GL_Register!$I$6:$I$1092,GL_Register!$C$6:$C$1092,$B6,GL_Register!$E$6:$E$1092,$C6) -> -2790000 | G6: =IF(F6>0,F6/SUMIF($F$6:$F$31,">0"),0) -> 0
B7: Gain on disposal - qualifying shareholding | C7: EXEMPT | D7: =COUNTIFS(GL_Register!$C$6:$C$1092,$B7,GL_Register!$E$6:$E$1092,$C7) -> 1 | E7: =SUMIFS(GL_Register!$F$6:$F$1092,GL_Register!$C$6:$C$1092,$B7,GL_Register!$E$6:$E$1092,$C7) -> 1320000 | F7: =SUMIFS(GL_Register!$I$6:$I$1092,GL_Register!$C$6:$C$1092,$B7,GL_Register!$E$6:$E$1092,$C7) -> -1320000 | G7: =IF(F7>0,F7/SUMIF($F$6:$F$31,">0"),0) -> 0
B8: FX gain (realised) | C8: TAXABLE | D8: =COUNTIFS(GL_Register!$C$6:$C$1092,$B8,GL_Register!$E$6:$E$1092,$C8) -> 1 | E8: =SUMIFS(GL_Register!$F$6:$F$1092,GL_Register!$C$6:$C$1092,$B8,GL_Register!$E$6:$E$1092,$C8) -> 185000 | F8: =SUMIFS(GL_Register!$I$6:$I$1092,GL_Register!$C$6:$C$1092,$B8,GL_Register!$E$6:$E$1092,$C8) -> 0 | G8: =IF(F8>0,F8/SUMIF($F$6:$F$31,">0"),0) -> 0
B9: Interest income - bank deposits | C9: TAXABLE | D9: =COUNTIFS(GL_Register!$C$6:$C$1092,$B9,GL_Register!$E$6:$E$1092,$C9) -> 1 | E9: =SUMIFS(GL_Register!$F$6:$F$1092,GL_Register!$C$6:$C$1092,$B9,GL_Register!$E$6:$E$1092,$C9) -> 410000 | F9: =SUMIFS(GL_Register!$I$6:$I$1092,GL_Register!$C$6:$C$1092,$B9,GL_Register!$E$6:$E$1092,$C9) -> 0 | G9: =IF(F9>0,F9/SUMIF($F$6:$F$31,">0"),0) -> 0
B10: Revenue - Projects | C10: TAXABLE | D10: =COUNTIFS(GL_Register!$C$6:$C$1092,$B10,GL_Register!$E$6:$E$1092,$C10) -> 107 | E10: =SUMIFS(GL_Register!$F$6:$F$1092,GL_Register!$C$6:$C$1092,$B10,GL_Register!$E$6:$E$1092,$C10) -> 22937100 | F10: =SUMIFS(GL_Register!$I$6:$I$1092,GL_Register!$C$6:$C$1092,$B10,GL_Register!$E$6:$E$1092,$C10) -> 0 | G10: =IF(F10>0,F10/SUMIF($F$6:$F$31,">0"),0) -> 0
B11: Revenue - Services | C11: TAXABLE | D11: =COUNTIFS(GL_Register!$C$6:$C$1092,$B11,GL_Register!$E$6:$E$1092,$C11) -> 223 | E11: =SUMIFS(GL_Register!$F$6:$F$1092,GL_Register!$C$6:$C$1092,$B11,GL_Register!$E$6:$E$1092,$C11) -> 41637528 | F11: =SUMIFS(GL_Register!$I$6:$I$1092,GL_Register!$C$6:$C$1092,$B11,GL_Register!$E$6:$E$1092,$C11) -> 0 | G11: =IF(F11>0,F11/SUMIF($F$6:$F$31,">0"),0) -> 0
B12: Bad debt written off (specific) | C12: ALLOW | D12: =COUNTIFS(GL_Register!$C$6:$C$1092,$B12,GL_Register!$E$6:$E$1092,$C12) -> 5 | E12: =SUMIFS(GL_Register!$F$6:$F$1092,GL_Register!$C$6:$C$1092,$B12,GL_Register!$E$6:$E$1092,$C12) -> 60270.87 | F12: =SUMIFS(GL_Register!$I$6:$I$1092,GL_Register!$C$6:$C$1092,$B12,GL_Register!$E$6:$E$1092,$C12) -> 0 | G12: =IF(F12>0,F12/SUMIF($F$6:$F$31,">0"),0) -> 0
B13: Bank charges | C13: ALLOW | D13: =COUNTIFS(GL_Register!$C$6:$C$1092,$B13,GL_Register!$E$6:$E$1092,$C13) -> 10 | E13: =SUMIFS(GL_Register!$F$6:$F$1092,GL_Register!$C$6:$C$1092,$B13,GL_Register!$E$6:$E$1092,$C13) -> 20441.19 | F13: =SUMIFS(GL_Register!$I$6:$I$1092,GL_Register!$C$6:$C$1092,$B13,GL_Register!$E$6:$E$1092,$C13) -> 0 | G13: =IF(F13>0,F13/SUMIF($F$6:$F$31,">0"),0) -> 0
B14: Cost of delivery - subcontractors | C14: ALLOW | D14: =COUNTIFS(GL_Register!$C$6:$C$1092,$B14,GL_Register!$E$6:$E$1092,$C14) -> 137 | E14: =SUMIFS(GL_Register!$F$6:$F$1092,GL_Register!$C$6:$C$1092,$B14,GL_Register!$E$6:$E$1092,$C14) -> 15810150 | F14: =SUMIFS(GL_Register!$I$6:$I$1092,GL_Register!$C$6:$C$1092,$B14,GL_Register!$E$6:$E$1092,$C14) -> 0 | G14: =IF(F14>0,F14/SUMIF($F$6:$F$31,">0"),0) -> 0
B15: Depreciation | C15: ALLOW | D15: =COUNTIFS(GL_Register!$C$6:$C$1092,$B15,GL_Register!$E$6:$E$1092,$C15) -> 35 | E15: =SUMIFS(GL_Register!$F$6:$F$1092,GL_Register!$C$6:$C$1092,$B15,GL_Register!$E$6:$E$1092,$C15) -> 1568782.8 | F15: =SUMIFS(GL_Register!$I$6:$I$1092,GL_Register!$C$6:$C$1092,$B15,GL_Register!$E$6:$E$1092,$C15) -> 0 | G15: =IF(F15>0,F15/SUMIF($F$6:$F$31,">0"),0) -> 0
B16: Donations - qualifying public benefit entity | C16: ALLOW | D16: =COUNTIFS(GL_Register!$C$6:$C$1092,$B16,GL_Register!$E$6:$E$1092,$C16) -> 4 | E16: =SUMIFS(GL_Register!$F$6:$F$1092,GL_Register!$C$6:$C$1092,$B16,GL_Register!$E$6:$E$1092,$C16) -> 27443.67 | F16: =SUMIFS(GL_Register!$I$6:$I$1092,GL_Register!$C$6:$C$1092,$B16,GL_Register!$E$6:$E$1092,$C16) -> 0 | G16: =IF(F16>0,F16/SUMIF($F$6:$F$31,">0"),0) -> 0
B17: IT & software | C17: ALLOW | D17: =COUNTIFS(GL_Register!$C$6:$C$1092,$B17,GL_Register!$E$6:$E$1092,$C17) -> 65 | E17: =SUMIFS(GL_Register!$F$6:$F$1092,GL_Register!$C$6:$C$1092,$B17,GL_Register!$E$6:$E$1092,$C17) -> 1935197.7 | F17: =SUMIFS(GL_Register!$I$6:$I$1092,GL_Register!$C$6:$C$1092,$B17,GL_Register!$E$6:$E$1092,$C17) -> 0 | G17: =IF(F17>0,F17/SUMIF($F$6:$F$31,">0"),0) -> 0
... B31: Related-party management fee (non-arm's length excess) | C31: TP | D31: =COUNTIFS(GL_Register!$C$6:$C$1092,$B31,GL_Register!$E$6:$E$1092,$C31) -> 1 | E31: =SUMIFS(GL_Register!$F$6:$F$1092,GL_Register!$C$6:$C$1092,$B31,GL_Register!$E$6:$E$1092,$C31) -> 25572.23 | F31: =SUMIFS(GL_Register!$I$6:$I$1092,GL_Register!$C$6:$C$1092,$B31,GL_Register!$E$6:$E$1092,$C31) -> 25572.23 | G31: =IF(F31>0,F31/SUMIF($F$6:$F$31,">0"),0) -> 0.058083677
B32: Total | D32: =SUM(D6:D31) -> 1087 | E32: =SUMIF(C6:C31,"<>",E6:E31) -> 1.1371302e+08 | F32: =SUM(F6:F31) -> -3669734.7

Sheet Sensitivity
B1: Sensitivity — profit change vs corporate tax
B2: What happens to CT if pre-tax profit moves, holding the adjustments constant
B5: Change in accounting profit | C5: -0.2 | D5: -0.1 | E5: 0 | F5: 0.1 | G5: 0.2
B6: Accounting profit | C6: =CT_Computation!$C$7*(1+C$5) -> 19876991 | D6: =CT_Computation!$C$7*(1+D$5) -> 22361615 | E6: =CT_Computation!$C$7*(1+E$5) -> 24846239 | F6: =CT_Computation!$C$7*(1+F$5) -> 27330863 | G6: =CT_Computation!$C$7*(1+G$5) -> 29815486
B7: Total adjustments (held constant) | C7: =CT_Computation!$C$17 -> -3669734.7 | D7: =CT_Computation!$C$17 -> -3669734.7 | E7: =CT_Computation!$C$17 -> -3669734.7 | F7: =CT_Computation!$C$17 -> -3669734.7 | G7: =CT_Computation!$C$17 -> -3669734.7
B8: Taxable income before losses | C8: =C6+C7 -> 16207256 | D8: =D6+D7 -> 18691880 | E8: =E6+E7 -> 21176504 | F8: =F6+F7 -> 23661128 | G8: =G6+G7 -> 26145752
B9: Losses utilised | C9: =MIN(Parameters!$C$9,MAX(0,C8)*Parameters!$C$8) -> 3200000 | D9: =MIN(Parameters!$C$9,MAX(0,D8)*Parameters!$C$8) -> 3200000 | E9: =MIN(Parameters!$C$9,MAX(0,E8)*Parameters!$C$8) -> 3200000 | F9: =MIN(Parameters!$C$9,MAX(0,F8)*Parameters!$C$8) -> 3200000 | G9: =MIN(Parameters!$C$9,MAX(0,G8)*Parameters!$C$8) -> 3200000
B10: Taxable income | C10: =MAX(0,C8-C9) -> 13007256 | D10: =MAX(0,D8-D9) -> 15491880 | E10: =MAX(0,E8-E9) -> 17976504 | F10: =MAX(0,F8-F9) -> 20461128 | G10: =MAX(0,G8-G9) -> 22945752
B11: Corporate tax at 9% | C11: =MAX(0,C10-Parameters!$C$6)*Parameters!$C$7 -> 1136903.1 | D11: =MAX(0,D10-Parameters!$C$6)*Parameters!$C$7 -> 1360519.2 | E11: =MAX(0,E10-Parameters!$C$6)*Parameters!$C$7 -> 1584135.4 | F11: =MAX(0,F10-Parameters!$C$6)*Parameters!$C$7 -> 1807751.5 | G11: =MAX(0,G10-Parameters!$C$6)*Parameters!$C$7 -> 2031367.7
B12: Foreign tax credit | C12: =-MIN(C11,Parameters!$C$13) -> -85000 | D12: =-MIN(D11,Parameters!$C$13) -> -85000 | E12: =-MIN(E11,Parameters!$C$13) -> -85000 | F12: =-MIN(F11,Parameters!$C$13) -> -85000 | G12: =-MIN(G11,Parameters!$C$13) -> -85000
B13: NET CT PAYABLE | C13: =C11+C12 -> 1051903.1 | D13: =D11+D12 -> 1275519.2 | E13: =E11+E12 -> 1499135.4 | F13: =F11+F12 -> 1722751.5 | G13: =G11+G12 -> 1946367.7
B14: Effective rate on profit | C14: =C13/C6 -> 0.052920639 | D14: =D13/D6 -> 0.057040568 | E14: =E13/E6 -> 0.060336511 | F14: =F13/F6 -> 0.063033192 | G14: =G13/G6 -> 0.065280426
B16: Base-case check (should be 0) | C16: =ROUND(E13-CT_Computation!C32,2) -> 0

Sheet Parameters
B1: Parameters — UAE Corporate Tax
B2: Federal Decree-Law No. 47 of 2022 (as amended) and related Ministerial Decisions · rules summarised for illustration; confirm against current law before filing
B4: Parameter | C4: Value | D4: Note
B5: Tax period | C5: FY2025 (1 Jan – 31 Dec 2025) | D5: Return due within 9 months of period end
B6: Taxable-income band taxed at 0% (AED) | C6: 375000 | D6: Applies to taxable income up to this amount
B7: Standard CT rate | C7: 0.09 | D7: On taxable income above the band
B8: Tax-loss offset cap (% of taxable income) | C8: 0.75 | D8: Brought-forward losses can offset up to 75% of taxable income
B9: Brought-forward tax losses (AED) | C9: 3200000 | D9: Per prior-year CT returns (input)
B10: Interest deductibility: % of tax EBITDA | C10: 0.3 | D10: Net interest expense cap
B11: Interest deductibility: de-minimis threshold (AED) | C11: 12000000 | D11: Net interest up to this amount always deductible
B12: Donations cap (% of taxable income) | C12: 0.05 | D12: Qualifying public-benefit donations only
B13: Foreign tax credit claimed (AED) | C13: 85000 | D13: Withholding tax suffered on foreign dividends/fees (input)
B14: Small Business Relief revenue threshold (AED) | C14: 3000000 | D14: Not eligible if revenue exceeds threshold

Sheet Treatment_Table
B1: Tax treatment codes
B2: Each GL line carries a code; the adjustment factor drives the computation
B4: Code | C4: Description | D4: Class | E4: Adjustment factor | F4: Rationale
B5: TAXABLE | C5: Taxable income | D5: Income | E5: 0 | F5: Included in accounting profit and in taxable income
B6: EXEMPT | C6: Exempt income (qualifying participation dividends / gains) | D6: Income | E6: -1 | F6: Deducted from accounting profit: participation exemption conditions assumed met
B7: ALLOW | C7: Deductible expense | D7: Expense | E7: 0 | F7: Deductible when incurred wholly and exclusively for business
B8: DIS100 | C8: Non-deductible expense (100% add-back) | D8: Expense | E8: 1 | F8: Fines, personal expenses, non-qualifying donations, general provisions
B9: DIS50 | C9: Entertainment (50% add-back) | D9: Expense | E9: 0.5 | F9: Client entertainment deductible at 50%
B10: INTLIM | C10: Interest expense (subject to limitation test) | D10: Expense | E10: 0 | F10: See Interest_Limitation: disallowance computed separately
B11: TP | C11: Related-party excess over arm's-length price | D11: Expense | E11: 1 | F11: Transfer-pricing adjustment

Sheet GL_Register
B1: General-ledger register — FY2025
B2: 1,087 P&L lines used to build accounting profit and tax adjustments (AED). Blue = ledger data; black = tax engine.
A5: Line ID | B5: Period | C5: Account | D5: Class | E5: Treatment | F5: Amount (AED) | G5: Description | H5: Adj. factor | I5: Tax adjustment | J5: P&L effect
A6: GL00001 | B6: 2025-08 | C6: Revenue - Services | D6: Income | E6: TAXABLE | F6: 38802.06 | G6: Revenue - Services invoice batch | H6: =VLOOKUP(E6,Treatment_Table!$B$5:$E$11,4,FALSE()) -> 0 | I6: =F6*H6 -> 0 | J6: =IF(D6="Income",F6,-F6) -> 38802.06
A7: GL00002 | B7: 2025-06 | C7: Revenue - Services | D7: Income | E7: TAXABLE | F7: 46355.09 | G7: Revenue - Services invoice batch | H7: =VLOOKUP(E7,Treatment_Table!$B$5:$E$11,4,FALSE()) -> 0 | I7: =F7*H7 -> 0 | J7: =IF(D7="Income",F7,-F7) -> 46355.09
A8: GL00003 | B8: 2025-10 | C8: Revenue - Projects | D8: Income | E8: TAXABLE | F8: 102998.01 | G8: Revenue - Projects invoice batch | H8: =VLOOKUP(E8,Treatment_Table!$B$5:$E$11,4,FALSE()) -> 0 | I8: =F8*H8 -> 0 | J8: =IF(D8="Income",F8,-F8) -> 102998.01
A9: GL00004 | B9: 2025-10 | C9: Revenue - Services | D9: Income | E9: TAXABLE | F9: 183473.81 | G9: Revenue - Services invoice batch | H9: =VLOOKUP(E9,Treatment_Table!$B$5:$E$11,4,FALSE()) -> 0 | I9: =F9*H9 -> 0 | J9: =IF(D9="Income",F9,-F9) -> 183473.81
A10: GL00005 | B10: 2025-05 | C10: Revenue - Projects | D10: Income | E10: TAXABLE | F10: 115032.33 | G10: Revenue - Projects invoice batch | H10: =VLOOKUP(E10,Treatment_Table!$B$5:$E$11,4,FALSE()) -> 0 | I10: =F10*H10 -> 0 | J10: =IF(D10="Income",F10,-F10) -> 115032.33
A11: GL00006 | B11: 2025-04 | C11: Revenue - Projects | D11: Income | E11: TAXABLE | F11: 167041.47 | G11: Revenue - Projects invoice batch | H11: =VLOOKUP(E11,Treatment_Table!$B$5:$E$11,4,FALSE()) -> 0 | I11: =F11*H11 -> 0 | J11: =IF(D11="Income",F11,-F11) -> 167041.47
A12: GL00007 | B12: 2025-09 | C12: Revenue - Projects | D12: Income | E12: TAXABLE | F12: 499797.61 | G12: Revenue - Projects invoice batch | H12: =VLOOKUP(E12,Treatment_Table!$B$5:$E$11,4,FALSE()) -> 0 | I12: =F12*H12 -> 0 | J12: =IF(D12="Income",F12,-F12) -> 499797.61
A13: GL00008 | B13: 2025-04 | C13: Revenue - Services | D13: Income | E13: TAXABLE | F13: 151282.94 | G13: Revenue - Services invoice batch | H13: =VLOOKUP(E13,Treatment_Table!$B$5:$E$11,4,FALSE()) -> 0 | I13: =F13*H13 -> 0 | J13: =IF(D13="Income",F13,-F13) -> 151282.94
A14: GL00009 | B14: 2025-04 | C14: Revenue - Projects | D14: Income | E14: TAXABLE | F14: 98012.15 | G14: Revenue - Projects invoice batch | H14: =VLOOKUP(E14,Treatment_Table!$B$5:$E$11,4,FALSE()) -> 0 | I14: =F14*H14 -> 0 | J14: =IF(D14="Income",F14,-F14) -> 98012.15
A15: GL00010 | B15: 2025-05 | C15: Revenue - Services | D15: Income | E15: TAXABLE | F15: 111581.78 | G15: Revenue - Services invoice batch | H15: =VLOOKUP(E15,Treatment_Table!$B$5:$E$11,4,FALSE()) -> 0 | I15: =F15*H15 -> 0 | J15: =IF(D15="Income",F15,-F15) -> 111581.78
A16: GL00011 | B16: 2025-12 | C16: Revenue - Services | D16: Income | E16: TAXABLE | F16: 535621.02 | G16: Revenue - Services invoice batch | H16: =VLOOKUP(E16,Treatment_Table!$B$5:$E$11,4,FALSE()) -> 0 | I16: =F16*H16 -> 0 | J16: =IF(D16="Income",F16,-F16) -> 535621.02
A17: GL00012 | B17: 2025-08 | C17: Revenue - Projects | D17: Income | E17: TAXABLE | F17: 42156.19 | G17: Revenue - Projects invoice batch | H17: =VLOOKUP(E17,Treatment_Table!$B$5:$E$11,4,FALSE()) -> 0 | I17: =F17*H17 -> 0 | J17: =IF(D17="Income",F17,-F17) -> 42156.19
... A1092: GL01087 | B1092: 2025-07 | C1092: Rent & facilities | D1092: Expense | E1092: ALLOW | F1092: 58002.82 | G1092: Rent & facilities | H1092: =VLOOKUP(E1092,Treatment_Table!$B$5:$E$11,4,FALSE()) -> 0 | I1092: =F1092*H1092 -> 0 | J1092: =IF(D1092="Income",F1092,-F1092) -> -58002.82

Sheet KPI_Dictionary
B1: KPI dictionary
B2: Definitions used in this corporate-tax pack
B4: KPI | C4: Definition | D4: Why it matters
B5: Accounting profit before tax | C5: Total income − total expenses from the GL register. | D5: Starting point for the tax computation.
B6: Taxable income | C6: Accounting profit ± adjustments − losses utilised. | D6: Base on which the 9% rate applies.
B7: Effective tax rate | C7: Net CT payable ÷ accounting profit. | D7: Shows how exempt income, losses and the 0% band reduce the headline 9%.
B8: Tax cost of non-deductibles | C8: Total add-backs × 9%. | D8: Quantifies the cash cost of policy leakage (fines, personal items, entertainment).
B9: Tax saved by exempt income | C9: Exempt income × 9%. | D9: Value of the participation exemption.
B10: Interest headroom | C10: Deductible-interest cap − net interest expense. | D10: Capacity before the interest limitation bites.
B11: Losses carried forward | C11: B/F losses − losses utilised. | D11: Future tax shield.

Sheet Checks
B1: Integrity checks
B2: All checks must show PASS (tolerance AED 1)
B4: Overall status | C4: =IF(COUNTIF(F8:F16,"FAIL")=0,"ALL CHECKS PASS","CHECK FAILURES") -> ALL CHECKS PASS
B7: Check | C7: Value A | D7: Value B | E7: Difference | F7: Result
B8: GL lines loaded (1,087) | C8: =COUNTA(GL_Register!$A$6:$A$1092) -> 1087 | D8: 1087 | E8: =C8-D8 -> 0 | F8: =IF(ABS(E8)<=1,"PASS","FAIL") -> PASS
B9: Accounting profit = sum of P&L effect column | C9: =CT_Computation!C7 -> 24846239 | D9: =SUM(GL_Register!$J$6:$J$1092) -> 24846239 | E9: =C9-D9 -> 0 | F9: =IF(ABS(E9)<=1,"PASS","FAIL") -> PASS
B10: Total adjustments = register adjustments (excl. interest / donation cap) | C10: =CT_Computation!C17-CT_Computation!C15-CT_Computation!C16 -> -3669734.7 | D10: =SUM(GL_Register!$I$6:$I$1092) -> -3669734.7 | E10: =C10-D10 -> 0 | F10: =IF(ABS(E10)<=1,"PASS","FAIL") -> PASS
B11: Rate reconciliation = computation | C11: =Rate_Reconciliation!C12 -> 1499135.4 | D11: =CT_Computation!C32 -> 1499135.4 | E11: =C11-D11 -> 0 | F11: =IF(ABS(E11)<=1,"PASS","FAIL") -> PASS
B12: Sensitivity base case = computation | C12: =Sensitivity!E13 -> 1499135.4 | D12: =CT_Computation!C32 -> 1499135.4 | E12: =C12-D12 -> 0 | F12: =IF(ABS(E12)<=1,"PASS","FAIL") -> PASS
B13: Every GL line has a valid treatment code | C13: =COUNT(GL_Register!$H$6:$H$1092) -> 1087 | D13: =COUNTA(GL_Register!$A$6:$A$1092) -> 1087 | E13: =C13-D13 -> 0 | F13: =IF(ABS(E13)<=1,"PASS","FAIL") -> PASS
B14: Adjustment summary lines = register lines | C14: =Adjustment_Summary!D32 -> 1087 | D14: =COUNTA(GL_Register!$A$6:$A$1092) -> 1087 | E14: =C14-D14 -> 0 | F14: =IF(ABS(E14)<=1,"PASS","FAIL") -> PASS
B15: Taxable income is non-negative (1 = yes) | C15: =IF(CT_Computation!C25>=0,1,0) -> 1 | D15: 1 | E15: =C15-D15 -> 0 | F15: =IF(ABS(E15)<=1,"PASS","FAIL") -> PASS
B16: Loss roll-forward: b/f − utilised = c/f | C16: =CT_Computation!C21-CT_Computation!C23 -> 0 | D16: =CT_Computation!C24 -> 0 | E16: =C16-D16 -> 0 | F16: =IF(ABS(E16)<=1,"PASS","FAIL") -> PASS
